{"status": 1, "date": "14.07.2018", "data": [{"type": 0, "stations": [{"ind": "3020103", "name": "Селенгинск", "nom": "1", "place": "Южный мкр.", "label": "Селенгинск, №1, Южный мкр.", "lng": "106.86742", "lat": "52.00384", "date": "14.07.2018", "si": [{"name": "Взвешенные в-ва", "val": -32768}, {"name": "Диоксид серы", "val": 0}, {"name": "Оксид углерода", "val": 0.1}, {"name": "Диоксид азота", "val": 0.1}, {"name": "Оксид азота", "val": 0}, {"name": "Озон", "val": 0.6}, {"name": "Сероводород", "val": 0}, {"name": "Фенол", "val": -32768}, {"name": "Формальдегид", "val": -32768}, {"name": "Частицы 10 мкм (сут.)", "val": -32768}], "maxSi": 0.6, "meteoParamsNames": ["\"Температура\"", "\"Скорость ветра\"", "\"Влажность отн.\"", "\"Давление\"", "\"Направление ветра\""], "meteoParamsValues": [{"dt": "2018-07-08_01:00", "vals": [10, 1, 88, 716, 209]}, {"dt": "2018-07-08_07:00", "vals": [15, 1, 72, 716, 289]}, {"dt": "2018-07-08_13:00", "vals": [20, 2, 51, 715, 273]}, {"dt": "2018-07-08_19:00", "vals": [16, 2, 64, 715, 267]}, {"dt": "2018-07-09_01:00", "vals": [14, 1, 72, 715, 245]}, {"dt": "2018-07-09_07:00", "vals": [14, 1, 71, 715, 292]}, {"dt": "2018-07-09_13:00", "vals": [18, 2, 50, 716, 263]}, {"dt": "2018-07-09_19:00", "vals": [17, 1, 54, 717, 298]}, {"dt": "2018-07-10_01:00", "vals": [11, 1, 84, 718, 205]}, {"dt": "2018-07-10_07:00", "vals": [11, 1, 87, 718, 134]}, {"dt": "2018-07-10_13:00", "vals": [18, 1, 54, 716, 319]}, {"dt": "2018-07-10_19:00", "vals": [16, 1, 63, 716, 253]}, {"dt": "2018-07-11_01:00", "vals": [12, 1, 80, 715, 208]}, {"dt": "2018-07-11_07:00", "vals": [11, 1, 94, 714, 203]}, {"dt": "2018-07-11_13:00", "vals": [12, 1, 95, 712, 251]}, {"dt": "2018-07-11_19:00", "vals": [12, 1, 96, 712, 227]}, {"dt": "2018-07-12_01:00", "vals": [13, 0, 96, 710, 0]}, {"dt": "2018-07-12_07:00", "vals": [14, 2, 91, 710, 224]}, {"dt": "2018-07-12_13:00", "vals": [19, 2, 67, 710, 242]}, {"dt": "2018-07-12_19:00", "vals": [19, 2, 61, 710, 229]}, {"dt": "2018-07-13_01:00", "vals": [16, 2, 75, 710, 233]}, {"dt": "2018-07-13_07:00", "vals": [16, 1, 92, 710, 154]}, {"dt": "2018-07-13_13:00", "vals": [22, 2, 69, 711, 303]}, {"dt": "2018-07-13_19:00", "vals": [21, 1, 62, 711, 231]}, {"dt": "2018-07-14_01:00", "vals": [13, 1, 94, 711, 186]}, {"dt": "2018-07-14_07:00", "vals": [15, 1, 87, 712, 128]}, {"dt": "2018-07-14_13:00", "vals": [26, 2, 49, 711, 236]}, {"dt": "2018-07-14_19:00", "vals": [26, 1, 38, 711, 184]}], "siRange": "08.07.2018 - 14.07.2018", "meteoRange": "08.07.2018 - 14.07.2018", "maxSiWeek": [{"dt": "08.07.2018", "val": 0.5, "name": "Озон"}, {"dt": "09.07.2018", "val": 0.5, "name": "Озон"}, {"dt": "10.07.2018", "val": 0.7, "name": "Озон"}, {"dt": "11.07.2018", "val": 0.4, "name": "Сероводород"}, {"dt": "12.07.2018", "val": 0.3, "name": "Озон"}, {"dt": "13.07.2018", "val": 0.4, "name": "Озон"}, {"dt": "14.07.2018", "val": 0.6, "name": "Озон"}], "primsSS": [{"dt": "2018-07-08_00:00", "vals": [null, 0.003, 0.1, 0.007, 0.003, 0.057, 0, null, null, null]}, {"dt": "2018-07-09_00:00", "vals": [null, 0.004, 0.1, 0.01, 0.004, 0.064, 0.001, null, null, null]}, {"dt": "2018-07-10_00:00", "vals": [null, 0.001, 0.2, 0.009, 0.005, 0.056, 0.001, null, null, null]}, {"dt": "2018-07-11_00:00", "vals": [null, 0, 0.2, 0.009, 0.004, 0.035, 0.001, null, null, null]}, {"dt": "2018-07-12_00:00", "vals": [null, 0.002, 0.2, 0.006, 0.002, 0.041, 0.001, null, null, null]}, {"dt": "2018-07-13_00:00", "vals": [null, 0.002, 0.3, 0.01, 0.004, 0.05, 0, null, null, null]}, {"dt": "2018-07-14_00:00", "vals": [null, 0.004, 0.4, 0.014, 0.006, 0.051, 0, null, null, null]}], "mpcAD": [{"name": "Взвешенные в-ва", "val": 0.15}, {"name": "Диоксид серы", "val": 0.05}, {"name": "Оксид углерода", "val": 3}, {"name": "Диоксид азота", "val": 0.1}, {"name": "Оксид азота", "val": null}, {"name": "Озон", "val": 0.1}, {"name": "Сероводород", "val": null}, {"name": "Фенол", "val": 0.006}, {"name": "Формальдегид", "val": 0.01}, {"name": "Частицы 10 мкм (сут.)", "val": 0.06}], "ispel": 0}, {"ind": "38020112", "name": "Свирск", "nom": "1", "place": "ул.Ангарская, д.2", "label": "Свирск, ул.Ангарская, д.2", "lng": "103.343486", "lat": "53.083278", "date": "14.07.2018", "si": [{"name": "Взвешенные в-ва", "val": -32768}, {"name": "Диоксид серы", "val": 0}, {"name": "Оксид углерода", "val": -32768}, {"name": "Диоксид азота", "val": 0.1}, {"name": "Оксид азота", "val": 0}, {"name": "Сероводород", "val": 0.2}, {"name": "Формальдегид", "val": -32768}], "maxSi": 0.2, "meteoParamsNames": ["\"Температура\"", "\"Скорость ветра\"", "\"Влажность отн.\"", "\"Давление\"", "\"Направление ветра\""], "meteoParamsValues": [{"dt": "2018-07-08_01:00", "vals": [13, 2, 87, 724, 311]}, {"dt": "2018-07-08_19:00", "vals": [20, 3, 46, 723, 166]}, {"dt": "2018-07-09_01:00", "vals": [12, 0, 86, 723, 181]}, {"dt": "2018-07-09_13:00", "vals": [15, 2, 73, 723, 304]}, {"dt": "2018-07-09_19:00", "vals": [15, 2, 59, 724, 335]}, {"dt": "2018-07-10_01:00", "vals": [9, 0, 99, 725, 176]}, {"dt": "2018-07-10_07:00", "vals": [11, 1, 86, 724, 180]}, {"dt": "2018-07-10_19:00", "vals": [19, 1, 47, 722, 325]}, {"dt": "2018-07-12_07:00", "vals": [15, 1, 77, 718, 154]}, {"dt": "2018-07-13_01:00", "vals": [15, 0, 99, 718, 299]}, {"dt": "2018-07-13_07:00", "vals": [16, 0, 96, 718, 279]}, {"dt": "2018-07-14_01:00", "vals": [13, 0, 92, 718, null]}], "siRange": "08.07.2018 - 14.07.2018", "meteoRange": "08.07.2018 - 14.07.2018", "maxSiWeek": [{"dt": "08.07.2018", "val": 0.1, "name": "Сероводород"}, {"dt": "09.07.2018", "val": 0, "name": "Диоксид серы"}, {"dt": "10.07.2018", "val": 0.1, "name": "Диоксид азота"}, {"dt": "11.07.2018", "val": -32768, "name": ""}, {"dt": "12.07.2018", "val": 0.1, "name": "Сероводород"}, {"dt": "13.07.2018", "val": 0.1, "name": "Диоксид азота"}, {"dt": "14.07.2018", "val": 0.2, "name": "Сероводород"}], "primsSS": [{"dt": "2018-07-08_00:00", "vals": [null, 0.002, null, 0.003, 0, 0, null]}, {"dt": "2018-07-09_00:00", "vals": [null, 0, null, 0.004, 0.001, 0, null]}, {"dt": "2018-07-10_00:00", "vals": [null, 0, null, 0.014, 0.006, 0, null]}, {"dt": "2018-07-12_00:00", "vals": [null, 0.002, null, 0.006, 0.001, 0, null]}, {"dt": "2018-07-13_00:00", "vals": [null, 0, null, 0.012, 0.003, 0, null]}, {"dt": "2018-07-14_00:00", "vals": [null, 0.002, null, 0.022, 0.002, 0.002, null]}], "mpcAD": [{"name": "Взвешенные в-ва", "val": 0.15}, {"name": "Диоксид серы", "val": 0.05}, {"name": "Оксид углерода", "val": 3}, {"name": "Диоксид азота", "val": 0.1}, {"name": "Оксид азота", "val": null}, {"name": "Сероводород", "val": null}, {"name": "Формальдегид", "val": 0.01}], "ispel": 0}, {"ind": "38020106", "name": "Шелехов", "nom": "1", "place": "Комсомольский бульвар, д.14", "label": "Шелехов, Комсомольский бульвар, д.14", "lng": "104.091367", "lat": "52.206767", "date": "14.07.2018", "si": [{"name": "Взвешенные в-ва", "val": -32768}, {"name": "Диоксид серы", "val": 0}, {"name": "Оксид углерода", "val": 0.1}, {"name": "Диоксид азота", "val": 0.3}, {"name": "Оксид азота", "val": 0}, {"name": "Озон", "val": 0.4}, {"name": "Твердые фториды", "val": -32768}, {"name": "Фторид водорода", "val": -32768}, {"name": "Частицы 10 мкм (сут.)", "val": -32768}], "maxSi": 0.4, "meteoParamsNames": ["\"Температура\"", "\"Скорость ветра\"", "\"Влажность отн.\"", "\"Давление\"", "\"Направление ветра\""], "meteoParamsValues": [{"dt": "2018-07-08_13:00", "vals": [18, 2, 62, 723, 263]}, {"dt": "2018-07-09_19:00", "vals": [17, 1, 59, 723, 104]}, {"dt": "2018-07-10_01:00", "vals": [11, 0, 86, 723, null]}, {"dt": "2018-07-10_07:00", "vals": [11, 0, 84, 722, null]}, {"dt": "2018-07-10_13:00", "vals": [17, 1, 55, 723, 21]}, {"dt": "2018-07-11_13:00", "vals": [16, 1, 71, 720, 266]}, {"dt": "2018-07-12_19:00", "vals": [16, 1, 81, 718, 264]}, {"dt": "2018-07-13_01:00", "vals": [15, 0, 89, 718, 226]}, {"dt": "2018-07-13_07:00", "vals": [17, 1, 83, 718, 268]}, {"dt": "2018-07-13_13:00", "vals": [24, 1, 53, 719, 271]}, {"dt": "2018-07-13_19:00", "vals": [24, 1, 52, 719, 36]}, {"dt": "2018-07-14_01:00", "vals": [14, 0, 97, 717, null]}, {"dt": "2018-07-14_07:00", "vals": [16, 0, 82, 717, null]}, {"dt": "2018-07-14_13:00", "vals": [27, 1, 44, 719, 78]}, {"dt": "2018-07-14_19:00", "vals": [27, 0, 42, 719, 64]}], "siRange": "08.07.2018 - 14.07.2018", "meteoRange": "08.07.2018 - 14.07.2018", "maxSiWeek": [{"dt": "08.07.2018", "val": 0.3, "name": "Озон"}, {"dt": "09.07.2018", "val": 0.6, "name": "Оксид углерода"}, {"dt": "10.07.2018", "val": 0.7, "name": "Оксид углерода"}, {"dt": "11.07.2018", "val": 0.2, "name": "Озон"}, {"dt": "12.07.2018", "val": 0.2, "name": "Озон"}, {"dt": "13.07.2018", "val": 0.3, "name": "Озон"}, {"dt": "14.07.2018", "val": 0.4, "name": "Озон"}], "primsSS": [{"dt": "2018-07-08_00:00", "vals": [null, 0.004, 0.1, 0.009, 0.003, 0.043, null, null, null]}, {"dt": "2018-07-09_00:00", "vals": [null, 0.032, 3.2, 0.01, 0.004, 0.058, null, null, null]}, {"dt": "2018-07-10_00:00", "vals": [null, 0.06, 2.2, 0.023, 0.009, 0.034, null, null, null]}, {"dt": "2018-07-11_00:00", "vals": [null, 0.01, 0.1, 0.016, 0.005, 0.038, null, null, null]}, {"dt": "2018-07-12_00:00", "vals": [null, 0.004, 0.1, 0.014, 0.003, 0.034, null, null, null]}, {"dt": "2018-07-13_00:00", "vals": [null, 0.003, 0.2, 0.018, 0.004, 0.042, null, null, null]}, {"dt": "2018-07-14_00:00", "vals": [null, 0.009, 0.2, 0.037, 0.01, 0.039, null, null, null]}], "mpcAD": [{"name": "Взвешенные в-ва", "val": 0.15}, {"name": "Диоксид серы", "val": 0.05}, {"name": "Оксид углерода", "val": 3}, {"name": "Диоксид азота", "val": 0.1}, {"name": "Оксид азота", "val": null}, {"name": "Озон", "val": 0.1}, {"name": "Твердые фториды", "val": 0.01}, {"name": "Фторид водорода", "val": 0.014}, {"name": "Частицы 10 мкм (сут.)", "val": 0.06}], "ispel": 0}, {"ind": "75020103", "name": "Петровск-Забайкальский", "nom": "1", "place": "ул.Маяковского, д.25а, МС", "label": "Петровск-Забайкальский, №1, ул.Маяковского, д.25а, МС", "lng": "108.870057", "lat": "51.312577", "date": "14.07.2018", "si": [{"name": "Взвешенные в-ва", "val": -32768}, {"name": "Диоксид серы", "val": 0}, {"name": "Оксид углерода", "val": 0.1}, {"name": "Диоксид азота", "val": 0.1}, {"name": "Оксид азота", "val": 0}, {"name": "Сероводород", "val": 0}, {"name": "Аммиак", "val": 0}], "maxSi": 0.1, "meteoParamsNames": ["\"Температура\"", "\"Скорость ветра\"", "\"Влажность отн.\"", "\"Давление\"", "\"Направление ветра\""], "meteoParamsValues": [{"dt": "2018-07-08_01:00", "vals": [11, 1, 67, 688, 255]}, {"dt": "2018-07-08_07:00", "vals": [11, 2, 66, 687, 269]}, {"dt": "2018-07-08_13:00", "vals": [15, 2, 51, 687, 310]}, {"dt": "2018-07-08_19:00", "vals": [16, 2, 46, 687, 329]}, {"dt": "2018-07-09_01:00", "vals": [11, 2, 79, 688, 241]}, {"dt": "2018-07-09_07:00", "vals": [9, 2, 84, 687, 207]}, {"dt": "2018-07-09_13:00", "vals": [18, 5, 40, 688, 253]}, {"dt": "2018-07-09_19:00", "vals": [17, 3, 45, 689, 166]}, {"dt": "2018-07-10_01:00", "vals": [5, 1, 92, 691, 33]}, {"dt": "2018-07-10_07:00", "vals": [4, 1, 92, 691, 30]}, {"dt": "2018-07-10_13:00", "vals": [14, 3, 70, 689, 238]}, {"dt": "2018-07-10_19:00", "vals": [13, 3, 85, 688, 16]}, {"dt": "2018-07-11_01:00", "vals": [12, 3, 83, 687, 9]}, {"dt": "2018-07-11_07:00", "vals": [11, 2, 97, 684, 34]}, {"dt": "2018-07-11_13:00", "vals": [15, 2, 88, 683, 15]}, {"dt": "2018-07-11_19:00", "vals": [13, 3, 95, 683, 233]}, {"dt": "2018-07-12_01:00", "vals": [11, 2, 95, 683, 234]}, {"dt": "2018-07-12_07:00", "vals": [11, 2, 96, 682, 213]}, {"dt": "2018-07-12_13:00", "vals": [15, 4, 83, 683, 241]}, {"dt": "2018-07-12_19:00", "vals": [17, 3, 63, 683, 243]}, {"dt": "2018-07-13_01:00", "vals": [14, 1, 75, 683, 239]}, {"dt": "2018-07-13_07:00", "vals": [13, 3, 83, 683, 239]}, {"dt": "2018-07-13_13:00", "vals": [14, 2, 90, 684, 216]}, {"dt": "2018-07-13_19:00", "vals": [19, 1, 67, 684, 223]}, {"dt": "2018-07-14_01:00", "vals": [12, 0, 94, 685, 162]}, {"dt": "2018-07-14_07:00", "vals": [8, 0, 99, 685, 35]}, {"dt": "2018-07-14_13:00", "vals": [23, 3, 51, 684, 248]}, {"dt": "2018-07-14_19:00", "vals": [25, 2, 41, 684, 243]}], "siRange": "08.07.2018 - 14.07.2018", "meteoRange": "08.07.2018 - 14.07.2018", "maxSiWeek": [{"dt": "08.07.2018", "val": 0, "name": "Диоксид серы"}, {"dt": "09.07.2018", "val": 0.1, "name": "Оксид углерода"}, {"dt": "10.07.2018", "val": 0.1, "name": "Оксид углерода"}, {"dt": "11.07.2018", "val": 4.3, "name": "Сероводород"}, {"dt": "12.07.2018", "val": 0.1, "name": "Оксид углерода"}, {"dt": "13.07.2018", "val": 7.8, "name": "Сероводород"}, {"dt": "14.07.2018", "val": 0.1, "name": "Оксид углерода"}], "primsSS": [{"dt": "2018-07-08_00:00", "vals": [null, 0, 0.2, 0, 0, 0, 0]}, {"dt": "2018-07-09_00:00", "vals": [null, 0, 0.2, 0.002, 0, 0, 0]}, {"dt": "2018-07-10_00:00", "vals": [null, 0, 0.3, 0, 0, 0, 0]}, {"dt": "2018-07-11_00:00", "vals": [null, 0, 0.2, 0, 0, 0.022, 0]}, {"dt": "2018-07-12_00:00", "vals": [null, 0, 0.2, 0.001, 0, 0, 0]}, {"dt": "2018-07-13_00:00", "vals": [null, 0, 0.3, 0, 0, 0.021, 0]}, {"dt": "2018-07-14_00:00", "vals": [null, 0.003, 0.4, 0.003, 0, 0, 0]}], "mpcAD": [{"name": "Взвешенные в-ва", "val": 0.15}, {"name": "Диоксид серы", "val": 0.05}, {"name": "Оксид углерода", "val": 3}, {"name": "Диоксид азота", "val": 0.1}, {"name": "Оксид азота", "val": null}, {"name": "Сероводород", "val": null}, {"name": "Аммиак", "val": 0.1}], "ispel": 0}, {"ind": "3020101", "name": "Улан-Удэ", "nom": "1", "place": "пр.50 лет Октября, д.15", "label": "Улан-Удэ, №1, пр.50 лет Октября, д.15", "lng": "107.597501", "lat": "51.838996", "date": "14.07.2018", "si": [{"name": "Взвешенные в-ва", "val": -32768}, {"name": "Диоксид серы", "val": 0}, {"name": "Оксид углерода", "val": 0.1}, {"name": "Диоксид азота", "val": 0.3}, {"name": "Оксид азота", "val": 0}, {"name": "Озон", "val": 0.4}, {"name": "Сероводород", "val": 0.2}, {"name": "Фенол", "val": -32768}, {"name": "Аммиак", "val": -32768}, {"name": "Формальдегид", "val": -32768}], "maxSi": 0.4, "meteoParamsNames": ["\"Температура\"", "\"Скорость ветра\"", "\"Влажность отн.\"", "\"Давление\"", "\"Направление ветра\""], "meteoParamsValues": [{"dt": "2018-07-08_01:00", "vals": [14, 1, 59, 709, 198]}, {"dt": "2018-07-08_07:00", "vals": [14, 1, 65, 708, 226]}, {"dt": "2018-07-08_13:00", "vals": [19, 2, 38, 708, 122]}, {"dt": "2018-07-08_19:00", "vals": [17, 1, 58, 708, 187]}, {"dt": "2018-07-09_01:00", "vals": [13, 1, 72, 708, 201]}, {"dt": "2018-07-09_07:00", "vals": [13, 1, 62, 708, 218]}, {"dt": "2018-07-09_13:00", "vals": [16, 1, 53, 709, 136]}, {"dt": "2018-07-09_19:00", "vals": [17, 1, 48, 710, 131]}, {"dt": "2018-07-10_01:00", "vals": [12, 1, 74, 711, 132]}, {"dt": "2018-07-10_07:00", "vals": [12, 1, 73, 711, 82]}, {"dt": "2018-07-10_13:00", "vals": [18, 2, 48, 709, 112]}, {"dt": "2018-07-10_19:00", "vals": [18, 2, 45, 709, 56]}, {"dt": "2018-07-11_01:00", "vals": [15, 1, 58, 708, 79]}, {"dt": "2018-07-11_07:00", "vals": [13, 1, 77, 705, 80]}, {"dt": "2018-07-11_13:00", "vals": [14, 1, 79, 704, 133]}, {"dt": "2018-07-11_19:00", "vals": [12, 1, 94, 704, 238]}, {"dt": "2018-07-12_01:00", "vals": [13, 1, 87, 703, 224]}, {"dt": "2018-07-12_07:00", "vals": [13, 1, 94, 703, 198]}, {"dt": "2018-07-12_13:00", "vals": [18, 2, 61, 703, 215]}, {"dt": "2018-07-12_19:00", "vals": [18, 1, 67, 703, 166]}, {"dt": "2018-07-13_01:00", "vals": [16, 1, 69, 704, 184]}, {"dt": "2018-07-13_07:00", "vals": [14, 1, 90, 703, 181]}, {"dt": "2018-07-13_13:00", "vals": [19, 1, 73, 704, 198]}, {"dt": "2018-07-13_19:00", "vals": [22, 1, 61, 704, 163]}, {"dt": "2018-07-14_01:00", "vals": [15, 0, 82, 705, 44]}, {"dt": "2018-07-14_07:00", "vals": [16, 1, 81, 705, 215]}, {"dt": "2018-07-14_13:00", "vals": [27, 2, 34, 704, 126]}, {"dt": "2018-07-14_19:00", "vals": [26, 1, 35, 704, 66]}], "siRange": "08.07.2018 - 14.07.2018", "meteoRange": "08.07.2018 - 14.07.2018", "maxSiWeek": [{"dt": "08.07.2018", "val": 0.3, "name": "Озон"}, {"dt": "09.07.2018", "val": 0.3, "name": "Озон"}, {"dt": "10.07.2018", "val": 0.3, "name": "Диоксид азота"}, {"dt": "11.07.2018", "val": 0.3, "name": "Озон"}, {"dt": "12.07.2018", "val": 0.2, "name": "Диоксид азота"}, {"dt": "13.07.2018", "val": 0.2, "name": "Диоксид азота"}, {"dt": "14.07.2018", "val": 0.4, "name": "Озон"}], "primsSS": [{"dt": "2018-07-08_00:00", "vals": [null, 0.003, 0.1, 0.008, 0.001, 0.046, 0.001, null, 0, null]}, {"dt": "2018-07-09_00:00", "vals": [null, 0.004, 0.3, 0.012, 0.001, 0.044, 0.001, null, 0, null]}, {"dt": "2018-07-10_00:00", "vals": [null, 0.007, 0.4, 0.045, 0.016, 0.027, 0.002, null, 0, null]}, {"dt": "2018-07-11_00:00", "vals": [null, 0.002, 0.3, 0.013, 0.006, 0.027, 0.002, null, 0, null]}, {"dt": "2018-07-12_00:00", "vals": [null, 0.002, 0.2, 0.022, 0.009, 0.021, 0.001, null, 0, null]}, {"dt": "2018-07-13_00:00", "vals": [null, 0.002, 0.4, 0.025, 0.008, 0.028, 0.001, null, null, null]}, {"dt": "2018-07-14_00:00", "vals": [null, 0.002, 0.3, 0.029, 0.01, 0.039, 0.001, null, null, null]}], "mpcAD": [{"name": "Взвешенные в-ва", "val": 0.15}, {"name": "Диоксид серы", "val": 0.05}, {"name": "Оксид углерода", "val": 3}, {"name": "Диоксид азота", "val": 0.1}, {"name": "Оксид азота", "val": null}, {"name": "Озон", "val": 0.1}, {"name": "Сероводород", "val": null}, {"name": "Фенол", "val": 0.006}, {"name": "Аммиак", "val": 0.1}, {"name": "Формальдегид", "val": 0.01}], "ispel": 0}, {"ind": "3020105", "name": "Гусиноозерск", "nom": "1", "place": "ул.Ленина, д.24", "label": "Гусиноозерск, №1, ул.Ленина, д.24", "lng": "106.53054", "lat": "51.28585", "date": "14.07.2018", "si": [{"name": "Взвешенные в-ва", "val": -32768}, {"name": "Диоксид серы", "val": 0.1}, {"name": "Оксид углерода", "val": 0.1}, {"name": "Диоксид азота", "val": 0.1}, {"name": "Оксид азота", "val": 0.1}, {"name": "Озон", "val": 0.4}, {"name": "Сероводород", "val": 0.3}, {"name": "Аммиак", "val": 0}, {"name": "Частицы 10 мкм (сут.)", "val": -32768}, {"name": "Частицы 2.5 мкм (сут.)", "val": -32768}], "maxSi": 0.4, "meteoParamsNames": ["\"Температура\"", "\"Скорость ветра\"", "\"Влажность отн.\"", "\"Давление\"", "\"Направление ветра\""], "meteoParamsValues": [{"dt": "2018-07-08_01:00", "vals": [13, 1, 60, 704, 82]}, {"dt": "2018-07-08_07:00", "vals": [15, 1, 62, 704, 241]}, {"dt": "2018-07-08_13:00", "vals": [18, 2, 48, 704, 29]}, {"dt": "2018-07-08_19:00", "vals": [17, 1, 54, 704, 235]}, {"dt": "2018-07-09_01:00", "vals": [14, 1, 61, 704, 93]}, {"dt": "2018-07-09_07:00", "vals": [15, 3, 62, 704, 242]}, {"dt": "2018-07-09_13:00", "vals": [20, 2, 34, 704, 130]}, {"dt": "2018-07-09_19:00", "vals": [19, 3, 38, 704, 46]}, {"dt": "2018-07-10_01:00", "vals": [14, 2, 61, 706, 38]}, {"dt": "2018-07-10_07:00", "vals": [13, 2, 66, 706, 38]}, {"dt": "2018-07-11_07:00", "vals": [14, 3, 64, 701, 41]}, {"dt": "2018-07-11_13:00", "vals": [13, 3, 76, 700, 44]}, {"dt": "2018-07-11_19:00", "vals": [13, 2, 76, 699, 42]}, {"dt": "2018-07-12_01:00", "vals": [13, 2, 84, 699, 44]}, {"dt": "2018-07-12_07:00", "vals": [13, 0, 88, 699, 73]}, {"dt": "2018-07-12_13:00", "vals": [19, 2, 55, 699, 219]}, {"dt": "2018-07-12_19:00", "vals": [19, 2, 51, 699, 265]}, {"dt": "2018-07-13_01:00", "vals": [16, 1, 65, 700, 238]}, {"dt": "2018-07-13_07:00", "vals": [15, 3, 82, 699, 224]}, {"dt": "2018-07-13_13:00", "vals": [20, 2, 63, 700, 333]}, {"dt": "2018-07-13_19:00", "vals": [22, 1, 53, 700, 40]}, {"dt": "2018-07-14_01:00", "vals": [19, 1, 64, 700, 215]}, {"dt": "2018-07-14_07:00", "vals": [16, 2, 80, 701, 244]}, {"dt": "2018-07-14_13:00", "vals": [26, 2, 43, 699, 260]}, {"dt": "2018-07-14_19:00", "vals": [28, 1, 36, 699, 40]}], "siRange": "08.07.2018 - 14.07.2018", "meteoRange": "08.07.2018 - 14.07.2018", "maxSiWeek": [{"dt": "08.07.2018", "val": 0.3, "name": "Озон"}, {"dt": "09.07.2018", "val": 0.4, "name": "Озон"}, {"dt": "10.07.2018", "val": 0.3, "name": "Озон"}, {"dt": "11.07.2018", "val": 0.7, "name": "Диоксид азота"}, {"dt": "12.07.2018", "val": 0.2, "name": "Диоксид серы"}, {"dt": "13.07.2018", "val": 0.3, "name": "Озон"}, {"dt": "14.07.2018", "val": 0.4, "name": "Озон"}], "primsSS": [{"dt": "2018-07-08_00:00", "vals": [null, 0.006, 0.2, 0.014, 0.006, 0.037, 0.001, 0, null, null]}, {"dt": "2018-07-09_00:00", "vals": [null, 0.011, 0.2, 0.014, 0.006, 0.046, 0, 0, null, null]}, {"dt": "2018-07-10_00:00", "vals": [null, 0.006, 0.2, 0.014, 0.004, 0.039, 0, 0, null, null]}, {"dt": "2018-07-11_00:00", "vals": [null, 0, 0.5, 0.066, 0.013, 0.031, 0, 0, null, null]}, {"dt": "2018-07-12_00:00", "vals": [null, 0.036, 0.3, 0.03, 0.021, 0.028, 0.001, 0, null, null]}, {"dt": "2018-07-13_00:00", "vals": [null, 0.013, 0.3, 0.02, 0.012, 0.04, 0.001, 0, null, null]}, {"dt": "2018-07-14_00:00", "vals": [null, 0.014, 0.4, 0.021, 0.011, 0.048, 0.001, 0, null, null]}], "mpcAD": [{"name": "Взвешенные в-ва", "val": 0.15}, {"name": "Диоксид серы", "val": 0.05}, {"name": "Оксид углерода", "val": 3}, {"name": "Диоксид азота", "val": 0.1}, {"name": "Оксид азота", "val": null}, {"name": "Озон", "val": 0.1}, {"name": "Сероводород", "val": null}, {"name": "Аммиак", "val": 0.1}, {"name": "Частицы 10 мкм (сут.)", "val": 0.06}, {"name": "Частицы 2.5 мкм (сут.)", "val": 0.035}], "ispel": 0}, {"ind": "38020110", "name": "Иркутск", "nom": "2", "place": "ул.Сухэ-Батора, д.5", "label": "Иркутск, ул.Сухэ-Батора, д.5", "lng": "104.282", "lat": "52.288917", "date": "14.07.2018", "si": [{"name": "Взвешенные в-ва", "val": -32768}, {"name": "Диоксид серы", "val": 0}, {"name": "Оксид углерода", "val": 0.1}, {"name": "Диоксид азота", "val": 0.2}, {"name": "Оксид азота", "val": 0}, {"name": "Формальдегид", "val": -32768}], "maxSi": 0.2, "meteoParamsNames": ["\"Температура\"", "\"Скорость ветра\"", "\"Влажность отн.\"", "\"Давление\"", "\"Направление ветра\""], "meteoParamsValues": [{"dt": "2018-07-08_07:00", "vals": [13, 2, 83, 723, 27]}, {"dt": "2018-07-08_13:00", "vals": [16, 3, 67, 722, 45]}, {"dt": "2018-07-08_19:00", "vals": [16, 1, 67, 722, 51]}, {"dt": "2018-07-09_01:00", "vals": [14, 1, 76, 722, 54]}, {"dt": "2018-07-09_07:00", "vals": [12, 2, 81, 722, 31]}, {"dt": "2018-07-09_13:00", "vals": [19, 2, 43, 721, 22]}, {"dt": "2018-07-09_19:00", "vals": [16, 1, 63, 722, 25]}, {"dt": "2018-07-10_01:00", "vals": [12, 0, 77, 723, null]}, {"dt": "2018-07-10_07:00", "vals": [10, 0, 80, 723, null]}, {"dt": "2018-07-10_13:00", "vals": [17, 1, 54, 722, 18]}, {"dt": "2018-07-10_19:00", "vals": [20, 1, 45, 720, 17]}, {"dt": "2018-07-11_01:00", "vals": [15, 0, 69, 720, 29]}, {"dt": "2018-07-11_07:00", "vals": [12, 1, 78, 720, 24]}, {"dt": "2018-07-11_13:00", "vals": [17, 1, 68, 718, 36]}, {"dt": "2018-07-11_19:00", "vals": [14, 1, 92, 718, 55]}, {"dt": "2018-07-12_01:00", "vals": [13, 0, 93, 717, 51]}, {"dt": "2018-07-12_07:00", "vals": [14, 1, 81, 717, 43]}, {"dt": "2018-07-12_13:00", "vals": [21, 2, 53, 716, 32]}, {"dt": "2018-07-12_19:00", "vals": [16, 1, 86, 717, 45]}, {"dt": "2018-07-13_01:00", "vals": [16, 1, 85, 717, 41]}, {"dt": "2018-07-13_07:00", "vals": [16, 1, 82, 717, 31]}, {"dt": "2018-07-14_19:00", "vals": [29, 0, 33, 709, null]}], "siRange": "08.07.2018 - 14.07.2018", "meteoRange": "08.07.2018 - 14.07.2018", "maxSiWeek": [{"dt": "08.07.2018", "val": 0.3, "name": "Диоксид азота"}, {"dt": "09.07.2018", "val": 0.4, "name": "Диоксид азота"}, {"dt": "10.07.2018", "val": 0.3, "name": "Диоксид азота"}, {"dt": "11.07.2018", "val": 0.7, "name": "Диоксид азота"}, {"dt": "12.07.2018", "val": 0.5, "name": "Диоксид азота"}, {"dt": "13.07.2018", "val": 0.5, "name": "Диоксид азота"}, {"dt": "14.07.2018", "val": 0.2, "name": "Диоксид азота"}], "primsSS": [{"dt": "2018-07-08_00:00", "vals": [null, 0.007, 0.2, 0.04, 0.021, null]}, {"dt": "2018-07-09_00:00", "vals": [null, 0.018, 0.3, 0.048, 0.029, null]}, {"dt": "2018-07-10_00:00", "vals": [null, 0.021, 0.4, 0.052, 0.023, null]}, {"dt": "2018-07-11_00:00", "vals": [null, 0.031, 0.7, 0.089, 0.069, null]}, {"dt": "2018-07-12_00:00", "vals": [null, 0.005, 0.5, 0.066, 0.057, null]}, {"dt": "2018-07-13_00:00", "vals": [null, 0.003, 0.4, 0.057, 0.052, null]}, {"dt": "2018-07-14_00:00", "vals": [null, 0.002, 0.4, 0.041, 0.011, null]}], "mpcAD": [{"name": "Взвешенные в-ва", "val": 0.15}, {"name": "Диоксид серы", "val": 0.05}, {"name": "Оксид углерода", "val": 3}, {"name": "Диоксид азота", "val": 0.1}, {"name": "Оксид азота", "val": null}, {"name": "Формальдегид", "val": 0.01}], "ispel": 0}, {"ind": "3020104", "name": "Селенгинск", "nom": "2", "place": "с.Брянск, ул.Новая, д.19", "label": "Селенгинск, №2, с.Брянск, ул.Новая, д.19", "lng": "106.83843", "lat": "52.02293", "date": "14.07.2018", "si": [{"name": "Взвешенные в-ва", "val": -32768}, {"name": "Диоксид серы", "val": 0}, {"name": "Сульфаты растворимые", "val": -32768}, {"name": "Оксид углерода", "val": 0}, {"name": "Диоксид азота", "val": 0.1}, {"name": "Оксид азота", "val": 0}, {"name": "Сероводород", "val": 0.6}, {"name": "Фенол", "val": -32768}, {"name": "Аммиак", "val": 0}, {"name": "Формальдегид", "val": -32768}, {"name": "Частицы 10 мкм (сут.)", "val": -32768}, {"name": "Частицы 2.5 мкм (сут.)", "val": -32768}], "maxSi": 0.6, "meteoParamsNames": ["\"Температура\"", "\"Скорость ветра\"", "\"Влажность отн.\"", "\"Давление\"", "\"Направление ветра\""], "meteoParamsValues": [{"dt": "2018-07-08_01:00", "vals": [10, 1, 87, 717, 87]}, {"dt": "2018-07-08_07:00", "vals": [14, 4, 78, 716, 181]}, {"dt": "2018-07-08_13:00", "vals": [18, 5, 58, 716, 178]}, {"dt": "2018-07-08_19:00", "vals": [15, 4, 69, 716, 177]}, {"dt": "2018-07-09_01:00", "vals": [13, 3, 80, 716, 173]}, {"dt": "2018-07-09_07:00", "vals": [13, 4, 79, 716, 178]}, {"dt": "2018-07-09_13:00", "vals": [17, 5, 56, 716, 176]}, {"dt": "2018-07-09_19:00", "vals": [16, 3, 61, 717, 176]}, {"dt": "2018-07-10_01:00", "vals": [11, 1, 83, 718, 90]}, {"dt": "2018-07-10_07:00", "vals": [10, 1, 90, 718, 307]}, {"dt": "2018-07-10_13:00", "vals": [18, 2, 57, 717, 186]}, {"dt": "2018-07-10_19:00", "vals": [15, 2, 68, 717, 165]}, {"dt": "2018-07-11_01:00", "vals": [11, 1, 86, 716, 163]}, {"dt": "2018-07-11_07:00", "vals": [11, 2, 92, 714, 166]}, {"dt": "2018-07-11_13:00", "vals": [12, 3, 97, 713, 184]}, {"dt": "2018-07-11_19:00", "vals": [12, 2, 96, 712, 163]}, {"dt": "2018-07-12_01:00", "vals": [13, 1, 93, 711, 157]}, {"dt": "2018-07-12_07:00", "vals": [13, 4, 92, 711, 173]}, {"dt": "2018-07-12_13:00", "vals": [18, 5, 71, 711, 163]}, {"dt": "2018-07-12_19:00", "vals": [18, 4, 64, 711, 162]}, {"dt": "2018-07-13_01:00", "vals": [16, 5, 79, 711, 166]}, {"dt": "2018-07-13_07:00", "vals": [15, 5, 94, 711, 171]}, {"dt": "2018-07-13_13:00", "vals": [21, 5, 75, 712, 169]}, {"dt": "2018-07-13_19:00", "vals": [21, 2, 67, 712, 179]}, {"dt": "2018-07-14_01:00", "vals": [13, 1, 96, 712, 227]}, {"dt": "2018-07-14_07:00", "vals": [15, 2, 92, 712, 311]}, {"dt": "2018-07-14_13:00", "vals": [25, 2, 55, 712, 220]}, {"dt": "2018-07-14_19:00", "vals": [25, 1, 46, 711, 209]}], "siRange": "08.07.2018 - 14.07.2018", "meteoRange": "08.07.2018 - 14.07.2018", "maxSiWeek": [{"dt": "08.07.2018", "val": 2.3, "name": "Сероводород"}, {"dt": "09.07.2018", "val": 0, "name": "Диоксид серы"}, {"dt": "10.07.2018", "val": 0.1, "name": "Диоксид азота"}, {"dt": "11.07.2018", "val": 0, "name": "Диоксид серы"}, {"dt": "12.07.2018", "val": 0.2, "name": "Сероводород"}, {"dt": "13.07.2018", "val": 0.2, "name": "Сероводород"}, {"dt": "14.07.2018", "val": 0.6, "name": "Сероводород"}], "primsSS": [{"dt": "2018-07-08_00:00", "vals": [null, 0.001, null, 0, 0.003, 0.001, 0.005, null, 0, null, null, null]}, {"dt": "2018-07-09_00:00", "vals": [null, 0.002, null, 0, 0.001, 0, 0, null, 0, null, null, null]}, {"dt": "2018-07-10_00:00", "vals": [null, 0.005, null, 0, 0.005, 0.001, 0, null, 0, null, null, null]}, {"dt": "2018-07-11_00:00", "vals": [null, 0.002, null, 0.1, 0.003, 0, 0, null, 0, null, null, null]}, {"dt": "2018-07-12_00:00", "vals": [null, 0.002, null, 0, 0.003, 0.001, 0.001, null, 0, null, null, null]}, {"dt": "2018-07-13_00:00", "vals": [null, 0.005, null, 0.1, 0.004, 0.001, 0.001, null, 0, null, null, null]}, {"dt": "2018-07-14_00:00", "vals": [null, 0.002, null, 0.1, 0.007, 0.004, 0.002, null, 0.01, null, null, null]}], "mpcAD": [{"name": "Взвешенные в-ва", "val": 0.15}, {"name": "Диоксид серы", "val": 0.05}, {"name": "Сульфаты растворимые", "val": null}, {"name": "Оксид углерода", "val": 3}, {"name": "Диоксид азота", "val": 0.1}, {"name": "Оксид азота", "val": null}, {"name": "Сероводород", "val": null}, {"name": "Фенол", "val": 0.006}, {"name": "Аммиак", "val": 0.1}, {"name": "Формальдегид", "val": 0.01}, {"name": "Частицы 10 мкм (сут.)", "val": 0.06}, {"name": "Частицы 2.5 мкм (сут.)", "val": 0.035}], "ispel": 0}, {"ind": "3020102", "name": "Улан-Удэ", "nom": "2", "place": "ул.Бабушкина, участок № 16", "label": "Улан-Удэ, №2, ул.Бабушкина, участок № 16", "lng": "107.594363", "lat": "51.815382", "date": "14.07.2018", "si": [{"name": "Взвешенные в-ва", "val": -32768}, {"name": "Диоксид серы", "val": 0}, {"name": "Оксид углерода", "val": 0.1}, {"name": "Диоксид азота", "val": 0.2}, {"name": "Оксид азота", "val": 0}, {"name": "Сероводород", "val": 0.4}, {"name": "Фенол", "val": -32768}, {"name": "Аммиак", "val": 0}], "maxSi": 0.4, "meteoParamsNames": ["\"Температура\"", "\"Скорость ветра\"", "\"Влажность отн.\"", "\"Давление\"", "\"Направление ветра\""], "meteoParamsValues": [{"dt": "2018-07-08_01:00", "vals": [14, 1, 65, 712, 253]}, {"dt": "2018-07-08_07:00", "vals": [15, 3, 66, 712, 256]}, {"dt": "2018-07-08_13:00", "vals": [20, 5, 39, 711, 268]}, {"dt": "2018-07-08_19:00", "vals": [18, 5, 58, 712, 260]}, {"dt": "2018-07-09_01:00", "vals": [12, 2, 77, 712, 252]}, {"dt": "2018-07-09_07:00", "vals": [14, 4, 63, 712, 258]}, {"dt": "2018-07-09_13:00", "vals": [17, 5, 51, 712, 266]}, {"dt": "2018-07-09_19:00", "vals": [19, 3, 46, 713, 262]}, {"dt": "2018-07-10_01:00", "vals": [12, 1, 73, 715, 141]}, {"dt": "2018-07-10_07:00", "vals": [12, 1, 74, 715, 58]}, {"dt": "2018-07-10_13:00", "vals": [19, 2, 47, 713, 94]}, {"dt": "2018-07-10_19:00", "vals": [19, 2, 45, 712, 57]}, {"dt": "2018-07-11_01:00", "vals": [16, 2, 59, 711, 270]}, {"dt": "2018-07-11_07:00", "vals": [14, 3, 76, 709, 267]}, {"dt": "2018-07-11_13:00", "vals": [14, 3, 80, 708, 260]}, {"dt": "2018-07-11_19:00", "vals": [13, 2, 94, 708, 250]}, {"dt": "2018-07-12_01:00", "vals": [14, 2, 89, 707, 254]}, {"dt": "2018-07-12_07:00", "vals": [14, 2, 92, 706, 263]}, {"dt": "2018-07-12_13:00", "vals": [20, 5, 60, 707, 259]}, {"dt": "2018-07-12_19:00", "vals": [19, 3, 64, 707, 257]}, {"dt": "2018-07-13_01:00", "vals": [17, 3, 70, 707, 257]}, {"dt": "2018-07-13_07:00", "vals": [15, 3, 88, 707, 262]}, {"dt": "2018-07-13_13:00", "vals": [20, 3, 73, 708, 260]}, {"dt": "2018-07-13_19:00", "vals": [23, 3, 61, 708, 262]}, {"dt": "2018-07-14_01:00", "vals": [15, 1, 86, 709, 158]}, {"dt": "2018-07-14_07:00", "vals": [16, 1, 85, 709, 278]}, {"dt": "2018-07-14_13:00", "vals": [27, 3, 39, 708, 274]}, {"dt": "2018-07-14_19:00", "vals": [28, 2, 32, 708, 136]}], "siRange": "08.07.2018 - 14.07.2018", "meteoRange": "08.07.2018 - 14.07.2018", "maxSiWeek": [{"dt": "08.07.2018", "val": 0.2, "name": "Сероводород"}, {"dt": "09.07.2018", "val": 0.2, "name": "Сероводород"}, {"dt": "10.07.2018", "val": 0.4, "name": "Сероводород"}, {"dt": "11.07.2018", "val": 0.1, "name": "Диоксид азота"}, {"dt": "12.07.2018", "val": 0.1, "name": "Оксид углерода"}, {"dt": "13.07.2018", "val": 0.3, "name": "Сероводород"}, {"dt": "14.07.2018", "val": 0.4, "name": "Сероводород"}], "primsSS": [{"dt": "2018-07-08_00:00", "vals": [null, 0.006, 0.3, 0.011, 0.002, 0.001, null, 0]}, {"dt": "2018-07-09_00:00", "vals": [null, 0.003, 0.1, 0.009, 0.002, 0.001, null, 0]}, {"dt": "2018-07-10_00:00", "vals": [null, 0.007, 0.6, 0.042, 0.037, 0.002, null, 0]}, {"dt": "2018-07-11_00:00", "vals": [null, 0.004, 0.1, 0.012, 0.003, 0, null, 0]}, {"dt": "2018-07-12_00:00", "vals": [null, 0.001, 0.4, 0.011, 0.003, 0, null, 0]}, {"dt": "2018-07-13_00:00", "vals": [null, 0.004, 0.2, 0.011, 0.003, 0.002, null, 0]}, {"dt": "2018-07-14_00:00", "vals": [null, 0.004, 0.1, 0.02, 0.007, 0.002, null, 0]}], "mpcAD": [{"name": "Взвешенные в-ва", "val": 0.15}, {"name": "Диоксид серы", "val": 0.05}, {"name": "Оксид углерода", "val": 3}, {"name": "Диоксид азота", "val": 0.1}, {"name": "Оксид азота", "val": null}, {"name": "Сероводород", "val": null}, {"name": "Фенол", "val": 0.006}, {"name": "Аммиак", "val": 0.1}], "ispel": 0}, {"ind": "38020107", "name": "Иркутск", "nom": "3", "place": "ул.Лермонтова, д.317", "label": "Иркутск, ул.Лермонтова, д.317", "lng": "104.272667", "lat": "52.242567", "date": "14.07.2018", "si": [{"name": "Взвешенные в-ва", "val": -32768}, {"name": "Диоксид серы", "val": 0}, {"name": "Оксид углерода", "val": 0.2}, {"name": "Диоксид азота", "val": 0.1}, {"name": "Оксид азота", "val": 0.4}, {"name": "Сероводород", "val": 0.4}, {"name": "Формальдегид", "val": -32768}, {"name": "Частицы 2.5 мкм (сут.)", "val": -32768}], "maxSi": 0.4, "meteoParamsNames": ["\"Температура\"", "\"Скорость ветра\"", "\"Влажность отн.\"", "\"Давление\"", "\"Направление ветра\""], "meteoParamsValues": [{"dt": "2018-07-08_01:00", "vals": [13, 1, 79, 720, 292]}, {"dt": "2018-07-08_07:00", "vals": [13, 1, 82, 720, 302]}, {"dt": "2018-07-08_13:00", "vals": [17, 1, 65, 719, 314]}, {"dt": "2018-07-08_19:00", "vals": [16, 0, 66, 719, 271]}, {"dt": "2018-07-09_01:00", "vals": [13, 0, 78, 719, null]}, {"dt": "2018-07-09_07:00", "vals": [13, 1, 77, 719, 304]}, {"dt": "2018-07-09_13:00", "vals": [19, 1, 42, 718, 308]}, {"dt": "2018-07-09_19:00", "vals": [16, 1, 60, 719, 295]}, {"dt": "2018-07-10_01:00", "vals": [12, 0, 72, 721, null]}, {"dt": "2018-07-10_07:00", "vals": [12, 0, 78, 720, null]}, {"dt": "2018-07-10_13:00", "vals": [17, 0, 54, 719, 290]}, {"dt": "2018-07-10_19:00", "vals": [19, 0, 46, 718, null]}, {"dt": "2018-07-11_01:00", "vals": [14, 0, 77, 718, null]}, {"dt": "2018-07-11_07:00", "vals": [13, 0, 77, 717, 286]}, {"dt": "2018-07-11_13:00", "vals": [16, 0, 72, 716, null]}, {"dt": "2018-07-11_19:00", "vals": [13, 0, 92, 715, null]}, {"dt": "2018-07-12_01:00", "vals": [13, 0, 93, 714, null]}, {"dt": "2018-07-12_07:00", "vals": [14, 0, 83, 714, 289]}, {"dt": "2018-07-12_13:00", "vals": [21, 1, 53, 713, 304]}, {"dt": "2018-07-12_19:00", "vals": [16, 0, 86, 714, 312]}, {"dt": "2018-07-13_01:00", "vals": [15, 0, 87, 714, null]}, {"dt": "2018-07-13_07:00", "vals": [16, 1, 81, 714, 310]}, {"dt": "2018-07-13_13:00", "vals": [24, 1, 56, 714, 309]}, {"dt": "2018-07-13_19:00", "vals": [22, 0, 59, 713, null]}, {"dt": "2018-07-14_01:00", "vals": [15, 0, 91, 714, null]}, {"dt": "2018-07-14_07:00", "vals": [13, 0, 94, 714, null]}, {"dt": "2018-07-14_13:00", "vals": [27, 0, 39, 712, null]}, {"dt": "2018-07-14_19:00", "vals": [27, 0, 40, 712, null]}], "siRange": "08.07.2018 - 14.07.2018", "meteoRange": "08.07.2018 - 14.07.2018", "maxSiWeek": [{"dt": "08.07.2018", "val": 0.1, "name": "Оксид углерода"}, {"dt": "09.07.2018", "val": 0.2, "name": "Оксид азота"}, {"dt": "10.07.2018", "val": 0.2, "name": "Диоксид азота"}, {"dt": "11.07.2018", "val": 0.5, "name": "Сероводород"}, {"dt": "12.07.2018", "val": 0.2, "name": "Оксид углерода"}, {"dt": "13.07.2018", "val": 0.2, "name": "Оксид азота"}, {"dt": "14.07.2018", "val": 0.4, "name": "Оксид азота"}], "primsSS": [{"dt": "2018-07-08_00:00", "vals": [null, 0.001, 0.2, 0.011, 0.016, 0, null, null]}, {"dt": "2018-07-09_00:00", "vals": [null, 0.007, 0.3, 0.015, 0.041, 0.001, null, null]}, {"dt": "2018-07-10_00:00", "vals": [null, 0.018, 0.4, 0.026, 0.02, 0.001, null, null]}, {"dt": "2018-07-11_00:00", "vals": [null, 0.021, 0.5, 0.022, 0.045, 0.002, null, null]}, {"dt": "2018-07-12_00:00", "vals": [null, 0.004, 0.5, 0.009, 0.037, 0.001, null, null]}, {"dt": "2018-07-13_00:00", "vals": [null, 0.005, 0.5, 0.018, 0.039, 0.001, null, null]}, {"dt": "2018-07-14_00:00", "vals": [null, 0.001, 0.5, 0.013, 0.055, 0.002, null, null]}], "mpcAD": [{"name": "Взвешенные в-ва", "val": 0.15}, {"name": "Диоксид серы", "val": 0.05}, {"name": "Оксид углерода", "val": 3}, {"name": "Диоксид азота", "val": 0.1}, {"name": "Оксид азота", "val": null}, {"name": "Сероводород", "val": null}, {"name": "Формальдегид", "val": 0.01}, {"name": "Частицы 2.5 мкм (сут.)", "val": 0.035}], "ispel": 0}, {"ind": "38020108", "name": "Иркутск", "nom": "4", "place": "ул.Партизанская, д.76", "label": "Иркутск, ул.Партизанская, д.76", "lng": "104.307889", "lat": "52.272306", "date": "14.07.2018", "si": [{"name": "Взвешенные в-ва", "val": -32768}, {"name": "Диоксид серы", "val": 0}, {"name": "Оксид углерода", "val": 0.1}, {"name": "Диоксид азота", "val": 0.1}, {"name": "Оксид азота", "val": 0.1}, {"name": "Озон", "val": 0.5}, {"name": "Частицы 10 мкм (сут.)", "val": -32768}], "maxSi": 0.5, "meteoParamsNames": ["\"Температура\"", "\"Скорость ветра\"", "\"Влажность отн.\"", "\"Давление\"", "\"Направление ветра\""], "meteoParamsValues": [{"dt": "2018-07-08_01:00", "vals": [null, null, null, null, null]}, {"dt": "2018-07-08_07:00", "vals": [null, null, null, null, null]}, {"dt": "2018-07-08_13:00", "vals": [null, null, null, null, null]}, {"dt": "2018-07-08_19:00", "vals": [null, null, null, null, null]}, {"dt": "2018-07-09_01:00", "vals": [null, null, null, null, null]}, {"dt": "2018-07-09_07:00", "vals": [null, null, null, null, null]}, {"dt": "2018-07-09_13:00", "vals": [null, null, null, null, null]}, {"dt": "2018-07-09_19:00", "vals": [null, null, null, null, null]}, {"dt": "2018-07-10_01:00", "vals": [null, null, null, null, null]}, {"dt": "2018-07-10_07:00", "vals": [null, null, null, null, null]}, {"dt": "2018-07-10_13:00", "vals": [null, null, null, null, null]}, {"dt": "2018-07-10_19:00", "vals": [null, null, null, null, null]}, {"dt": "2018-07-11_01:00", "vals": [null, null, null, null, null]}, {"dt": "2018-07-11_07:00", "vals": [null, null, null, null, null]}, {"dt": "2018-07-11_13:00", "vals": [null, null, null, null, null]}, {"dt": "2018-07-11_19:00", "vals": [null, null, null, null, null]}, {"dt": "2018-07-12_01:00", "vals": [null, null, null, null, null]}, {"dt": "2018-07-12_07:00", "vals": [null, null, null, null, null]}, {"dt": "2018-07-12_13:00", "vals": [null, null, null, null, null]}, {"dt": "2018-07-12_19:00", "vals": [null, null, null, null, null]}, {"dt": "2018-07-13_01:00", "vals": [null, null, null, null, null]}, {"dt": "2018-07-13_07:00", "vals": [null, null, null, null, null]}, {"dt": "2018-07-13_13:00", "vals": [null, null, null, null, null]}, {"dt": "2018-07-13_19:00", "vals": [null, null, null, null, null]}, {"dt": "2018-07-14_01:00", "vals": [null, null, null, null, null]}, {"dt": "2018-07-14_07:00", "vals": [null, null, null, null, null]}, {"dt": "2018-07-14_13:00", "vals": [null, null, null, null, null]}, {"dt": "2018-07-14_19:00", "vals": [null, null, null, null, null]}], "siRange": "08.07.2018 - 14.07.2018", "meteoRange": "08.07.2018 - 14.07.2018", "maxSiWeek": [{"dt": "08.07.2018", "val": 0.2, "name": "Озон"}, {"dt": "09.07.2018", "val": 0.3, "name": "Озон"}, {"dt": "10.07.2018", "val": 0.4, "name": "Озон"}, {"dt": "11.07.2018", "val": 0.1, "name": "Диоксид серы"}, {"dt": "12.07.2018", "val": 0.2, "name": "Озон"}, {"dt": "13.07.2018", "val": 0.2, "name": "Озон"}, {"dt": "14.07.2018", "val": 0.5, "name": "Озон"}], "primsSS": [{"dt": "2018-07-08_00:00", "vals": [null, 0.008, 0.1, 0.007, 0.004, 0.029, null]}, {"dt": "2018-07-09_00:00", "vals": [null, 0.029, 0.2, 0.008, 0.009, 0.027, null]}, {"dt": "2018-07-10_00:00", "vals": [null, 0.016, 0.2, 0.01, 0.008, 0.034, null]}, {"dt": "2018-07-11_00:00", "vals": [null, 0.029, 0.3, 0.011, 0.016, 0.015, null]}, {"dt": "2018-07-12_00:00", "vals": [null, 0.004, 0.2, 0.005, 0.012, 0.016, null]}, {"dt": "2018-07-13_00:00", "vals": [null, 0.003, 0.3, 0.01, 0.007, 0.024, null]}, {"dt": "2018-07-14_00:00", "vals": [null, 0.005, 0.2, 0.004, 0.01, 0.041, null]}], "mpcAD": [{"name": "Взвешенные в-ва", "val": 0.15}, {"name": "Диоксид серы", "val": 0.05}, {"name": "Оксид углерода", "val": 3}, {"name": "Диоксид азота", "val": 0.1}, {"name": "Оксид азота", "val": null}, {"name": "Озон", "val": 0.1}, {"name": "Частицы 10 мкм (сут.)", "val": 0.06}], "ispel": 0}, {"ind": "75020102", "name": "Чита", "nom": "4", "place": "ул.Лазо, д.30", "label": "Чита, №4, ул.Лазо, д.30", "lng": "113.5", "lat": "52.019444", "date": "14.07.2018", "si": [{"name": "Взвешенные в-ва", "val": -32768}, {"name": "Диоксид серы", "val": -32768}, {"name": "Оксид углерода", "val": -32768}, {"name": "Диоксид азота", "val": -32768}, {"name": "Оксид азота", "val": -32768}, {"name": "Сероводород", "val": -32768}, {"name": "Фенол", "val": -32768}, {"name": "Сажа", "val": -32768}, {"name": "Аммиак", "val": -32768}], "maxSi": -32768, "meteoParamsNames": ["\"Температура\"", "\"Скорость ветра\"", "\"Влажность отн.\"", "\"Давление\"", "\"Направление ветра\""], "meteoParamsValues": [{"dt": "2018-07-08_01:00", "vals": [13, 0, 94, 698, 249]}, {"dt": "2018-07-08_07:00", "vals": [12, 1, 93, 697, 245]}, {"dt": "2018-07-08_13:00", "vals": [15, 3, 81, 696, 295]}, {"dt": "2018-07-08_19:00", "vals": [13, 1, 92, 696, 291]}, {"dt": "2018-07-09_01:00", "vals": [10, 1, 92, 696, 215]}, {"dt": "2018-07-09_07:00", "vals": [11, 1, 87, 697, 183]}, {"dt": "2018-07-09_13:00", "vals": [13, 2, 73, 699, 220]}, {"dt": "2018-07-09_19:00", "vals": [13, 2, 75, 701, 256]}, {"dt": "2018-07-10_01:00", "vals": [11, 1, 79, 703, 231]}, {"dt": "2018-07-10_07:00", "vals": [9, 0, 89, 705, null]}], "siRange": "08.07.2018 - 14.07.2018", "meteoRange": "08.07.2018 - 10.07.2018", "maxSiWeek": [{"dt": "08.07.2018", "val": 0.4, "name": "Сероводород"}, {"dt": "09.07.2018", "val": 0.8, "name": "Сероводород"}, {"dt": "10.07.2018", "val": 0.6, "name": "Сероводород"}, {"dt": "11.07.2018", "val": -32768, "name": ""}, {"dt": "12.07.2018", "val": -32768, "name": ""}, {"dt": "13.07.2018", "val": -32768, "name": ""}, {"dt": "14.07.2018", "val": -32768, "name": ""}], "primsSS": [{"dt": "2018-07-08_00:00", "vals": [null, 0.003, 0.6, 0.006, 0.001, 0.002, null, null, 0]}, {"dt": "2018-07-09_00:00", "vals": [null, 0.008, 0.6, 0.006, 0.007, 0.005, null, null, 0]}, {"dt": "2018-07-10_00:00", "vals": [null, 0.004, 0.5, 0.006, 0.01, 0.004, null, null, 0]}], "mpcAD": [{"name": "Взвешенные в-ва", "val": 0.15}, {"name": "Диоксид серы", "val": 0.05}, {"name": "Оксид углерода", "val": 3}, {"name": "Диоксид азота", "val": 0.1}, {"name": "Оксид азота", "val": null}, {"name": "Сероводород", "val": null}, {"name": "Фенол", "val": 0.006}, {"name": "Сажа", "val": 0.05}, {"name": "Аммиак", "val": 0.1}], "ispel": 0}, {"ind": "38020105", "name": "Усолье-Сибирское", "nom": "4", "place": "Комсомольский пр., д.33", "label": "Усолье-Сибирское, Комсомольский пр., д.33", "lng": "103.638619", "lat": "52.758317", "date": "14.07.2018", "si": [{"name": "Взвешенные в-ва", "val": -32768}, {"name": "Диоксид серы", "val": 0}, {"name": "Оксид углерода", "val": 0.1}, {"name": "Диоксид азота", "val": 0}, {"name": "Оксид азота", "val": 0}, {"name": "Сероводород", "val": 0.4}, {"name": "Хлор", "val": -32768}, {"name": "Хлорид водорода", "val": -32768}, {"name": "Частицы 10 мкм (сут.)", "val": -32768}], "maxSi": 0.4, "meteoParamsNames": ["\"Температура\"", "\"Скорость ветра\"", "\"Влажность отн.\"", "\"Давление\"", "\"Направление ветра\""], "meteoParamsValues": [{"dt": "2018-07-08_01:00", "vals": [13, 2, 88, 722, 285]}, {"dt": "2018-07-08_13:00", "vals": [16, 3, 73, 721, 301]}, {"dt": "2018-07-08_19:00", "vals": [16, 2, 70, 721, 270]}, {"dt": "2018-07-09_13:00", "vals": [18, 2, 48, 720, 296]}, {"dt": "2018-07-09_19:00", "vals": [16, 2, 58, 721, 315]}, {"dt": "2018-07-10_07:00", "vals": [11, 0, 82, 722, 286]}, {"dt": "2018-07-10_13:00", "vals": [18, 1, 50, 720, 164]}, {"dt": "2018-07-11_01:00", "vals": [11, 1, 81, 720, 276]}, {"dt": "2018-07-11_07:00", "vals": [11, 1, 85, 719, 289]}, {"dt": "2018-07-11_13:00", "vals": [19, 2, 48, 717, 325]}, {"dt": "2018-07-11_19:00", "vals": [15, 1, 90, 717, 268]}, {"dt": "2018-07-12_01:00", "vals": [15, 2, 79, 716, 282]}, {"dt": "2018-07-12_07:00", "vals": [14, 1, 80, 716, 280]}, {"dt": "2018-07-12_19:00", "vals": [15, 2, 92, 716, 278]}, {"dt": "2018-07-13_01:00", "vals": [14, 0, 95, 716, 278]}, {"dt": "2018-07-13_07:00", "vals": [15, 1, 90, 716, 289]}, {"dt": "2018-07-13_13:00", "vals": [24, 2, 56, 715, 291]}, {"dt": "2018-07-13_19:00", "vals": [25, 1, 45, 715, 238]}, {"dt": "2018-07-14_01:00", "vals": [15, 0, 86, 715, null]}, {"dt": "2018-07-14_07:00", "vals": [15, 1, 92, 715, 154]}, {"dt": "2018-07-14_13:00", "vals": [27, 1, 37, 714, 129]}, {"dt": "2018-07-14_19:00", "vals": [28, 2, 37, 713, 159]}], "siRange": "08.07.2018 - 14.07.2018", "meteoRange": "08.07.2018 - 14.07.2018", "maxSiWeek": [{"dt": "08.07.2018", "val": 0.5, "name": "Сероводород"}, {"dt": "09.07.2018", "val": 0.2, "name": "Сероводород"}, {"dt": "10.07.2018", "val": 0.4, "name": "Сероводород"}, {"dt": "11.07.2018", "val": 0.6, "name": "Сероводород"}, {"dt": "12.07.2018", "val": 0.4, "name": "Сероводород"}, {"dt": "13.07.2018", "val": 0.4, "name": "Сероводород"}, {"dt": "14.07.2018", "val": 0.4, "name": "Сероводород"}], "primsSS": [{"dt": "2018-07-08_00:00", "vals": [null, 0.005, 0.1, 0, 0.001, 0.003, null, null, null]}, {"dt": "2018-07-09_00:00", "vals": [null, 0.003, 0.2, 0, 0.001, 0.001, null, null, null]}, {"dt": "2018-07-10_00:00", "vals": [null, 0.002, 0.3, 0, 0.001, 0.003, null, null, null]}, {"dt": "2018-07-11_00:00", "vals": [null, 0.001, 0.3, 0.002, 0.004, 0.003, null, null, null]}, {"dt": "2018-07-12_00:00", "vals": [null, 0.005, 0.3, 0, 0.001, 0.003, null, null, null]}, {"dt": "2018-07-13_00:00", "vals": [null, 0.003, 0.2, 0, 0.001, 0.002, null, null, null]}, {"dt": "2018-07-14_00:00", "vals": [null, 0.001, 0.3, 0.002, 0.004, 0.002, null, null, null]}], "mpcAD": [{"name": "Взвешенные в-ва", "val": 0.15}, {"name": "Диоксид серы", "val": 0.05}, {"name": "Оксид углерода", "val": 3}, {"name": "Диоксид азота", "val": 0.1}, {"name": "Оксид азота", "val": null}, {"name": "Сероводород", "val": null}, {"name": "Хлор", "val": 0.03}, {"name": "Хлорид водорода", "val": 0.1}, {"name": "Частицы 10 мкм (сут.)", "val": 0.06}], "ispel": 0}, {"ind": "3020106", "name": "Улан-Удэ", "nom": "4", "place": " ул.Революции 1905 г., участок № 74", "label": "Улан-Удэ, №4,  ул.Революции 1905 г., участок № 74", "lng": "107.579117", "lat": "51.844186", "date": "14.07.2018", "si": [{"name": "Взвешенные в-ва", "val": -32768}, {"name": "Диоксид серы", "val": 0}, {"name": "Оксид углерода", "val": 0.1}, {"name": "Диоксид азота", "val": 0.2}, {"name": "Оксид азота", "val": 0.1}, {"name": "Сероводород", "val": 0.2}, {"name": "Фенол", "val": -32768}, {"name": "Сажа", "val": -32768}, {"name": "Частицы 10 мкм", "val": -32768}, {"name": "Частицы 2.5 мкм", "val": -32768}], "maxSi": 0.2, "meteoParamsNames": ["\"Температура\"", "\"Скорость ветра\"", "\"Влажность отн.\"", "\"Давление\"", "\"Направление ветра\""], "meteoParamsValues": [{"dt": "2018-07-08_01:00", "vals": [14, 1, 59, 710, 253]}, {"dt": "2018-07-08_07:00", "vals": [13, 1, 67, 709, 296]}, {"dt": "2018-07-08_13:00", "vals": [19, 2, 38, 708, 121]}, {"dt": "2018-07-08_19:00", "vals": [17, 2, 58, 709, 290]}, {"dt": "2018-07-09_01:00", "vals": [13, 1, 73, 709, 204]}, {"dt": "2018-07-09_07:00", "vals": [13, 2, 63, 709, 310]}, {"dt": "2018-07-09_13:00", "vals": [16, 2, 53, 710, 320]}, {"dt": "2018-07-09_19:00", "vals": [18, 1, 47, 711, 341]}, {"dt": "2018-07-10_01:00", "vals": [12, 1, 76, 712, 190]}, {"dt": "2018-07-10_07:00", "vals": [12, 0, 74, 712, 73]}, {"dt": "2018-07-10_13:00", "vals": [19, 1, 49, 710, 118]}, {"dt": "2018-07-10_19:00", "vals": [18, 1, 48, 710, 245]}, {"dt": "2018-07-11_01:00", "vals": [15, 1, 60, 708, 235]}, {"dt": "2018-07-11_07:00", "vals": [13, 1, 78, 706, 345]}, {"dt": "2018-07-11_13:00", "vals": [14, 1, 79, 705, 229]}, {"dt": "2018-07-11_19:00", "vals": [13, 1, 95, 705, 271]}, {"dt": "2018-07-12_01:00", "vals": [13, 1, 87, 704, 183]}, {"dt": "2018-07-12_07:00", "vals": [13, 1, 94, 704, 223]}, {"dt": "2018-07-12_13:00", "vals": [18, 2, 62, 704, 283]}, {"dt": "2018-07-12_19:00", "vals": [18, 1, 66, 704, 288]}, {"dt": "2018-07-13_01:00", "vals": [16, 1, 71, 704, 277]}, {"dt": "2018-07-13_07:00", "vals": [15, 0, 90, 704, 216]}, {"dt": "2018-07-13_13:00", "vals": [19, 1, 74, 705, 211]}, {"dt": "2018-07-13_19:00", "vals": [22, 1, 61, 705, 200]}, {"dt": "2018-07-14_01:00", "vals": [16, 1, 83, 706, 54]}, {"dt": "2018-07-14_07:00", "vals": [15, 0, 85, 706, 195]}, {"dt": "2018-07-14_13:00", "vals": [26, 2, 34, 705, 227]}, {"dt": "2018-07-14_19:00", "vals": [26, 1, 33, 705, 154]}], "siRange": "08.07.2018 - 14.07.2018", "meteoRange": "08.07.2018 - 14.07.2018", "maxSiWeek": [{"dt": "08.07.2018", "val": 0.1, "name": "Диоксид азота"}, {"dt": "09.07.2018", "val": 0.1, "name": "Диоксид азота"}, {"dt": "10.07.2018", "val": 0.2, "name": "Диоксид азота"}, {"dt": "11.07.2018", "val": 0.2, "name": "Диоксид азота"}, {"dt": "12.07.2018", "val": 0.1, "name": "Оксид углерода"}, {"dt": "13.07.2018", "val": 0.2, "name": "Диоксид азота"}, {"dt": "14.07.2018", "val": 0.2, "name": "Диоксид азота"}], "primsSS": [{"dt": "2018-07-08_00:00", "vals": [null, 0.004, 0.1, 0.016, 0.004, 0, null, null, null, null]}, {"dt": "2018-07-09_00:00", "vals": [null, 0, 0.1, 0.015, 0.004, 0, null, null, null, null]}, {"dt": "2018-07-10_00:00", "vals": [null, 0.004, 0.2, 0.026, 0.01, 0.001, null, null, null, null]}, {"dt": "2018-07-11_00:00", "vals": [null, 0.002, 0.1, 0.014, 0.01, 0.001, null, null, null, null]}, {"dt": "2018-07-12_00:00", "vals": [null, 0.003, 0.2, 0.022, 0.012, 0, null, null, null, null]}, {"dt": "2018-07-13_00:00", "vals": [null, 0.005, 0.4, 0.025, 0.01, 0.001, null, null, null, null]}, {"dt": "2018-07-14_00:00", "vals": [null, 0.001, 0.2, 0.025, 0.012, 0.001, null, null, null, null]}], "mpcAD": [{"name": "Взвешенные в-ва", "val": 0.15}, {"name": "Диоксид серы", "val": 0.05}, {"name": "Оксид углерода", "val": 3}, {"name": "Диоксид азота", "val": 0.1}, {"name": "Оксид азота", "val": null}, {"name": "Сероводород", "val": null}, {"name": "Фенол", "val": 0.006}, {"name": "Сажа", "val": 0.05}, {"name": "Частицы 10 мкм", "val": 0.06}, {"name": "Частицы 2.5 мкм", "val": 0.035}], "ispel": 0}, {"ind": "38020114", "name": "Усолье-Сибирское", "nom": "5", "place": "ул.Интернациональная, д.52", "label": "Усолье-Сибирское, ул.Интернациональная, д.52", "lng": "103.663736", "lat": "52.749422", "date": "14.07.2018", "si": [{"name": "Взвешенные в-ва", "val": -32768}, {"name": "Диоксид серы", "val": -32768}, {"name": "Оксид углерода", "val": 0.1}, {"name": "Диоксид азота", "val": 0.2}, {"name": "Оксид азота", "val": 0}, {"name": "Сероводород", "val": -32768}, {"name": "Хлор", "val": -32768}, {"name": "Формальдегид", "val": -32768}], "maxSi": 0.2, "meteoParamsNames": ["\"Температура\"", "\"Скорость ветра\"", "\"Влажность отн.\"", "\"Давление\"", "\"Направление ветра\""], "meteoParamsValues": [{"dt": "2018-07-08_01:00", "vals": [13, 0, 90, 723, null]}, {"dt": "2018-07-08_13:00", "vals": [16, 1, 74, 722, 333]}, {"dt": "2018-07-08_19:00", "vals": [16, 0, 66, 722, 161]}, {"dt": "2018-07-09_01:00", "vals": [13, 0, 77, 722, null]}, {"dt": "2018-07-09_07:00", "vals": [13, 1, 70, 722, 345]}, {"dt": "2018-07-09_13:00", "vals": [18, 1, 48, 721, 338]}, {"dt": "2018-07-09_19:00", "vals": [16, 1, 59, 722, 338]}, {"dt": "2018-07-10_01:00", "vals": [10, 0, 84, 723, null]}, {"dt": "2018-07-10_07:00", "vals": [10, 0, 88, 723, 44]}, {"dt": "2018-07-10_13:00", "vals": [18, 1, 49, 722, 161]}, {"dt": "2018-07-10_19:00", "vals": [18, 0, 49, 721, null]}, {"dt": "2018-07-11_01:00", "vals": [11, 0, 82, 721, null]}, {"dt": "2018-07-11_07:00", "vals": [12, 0, 88, 720, 342]}, {"dt": "2018-07-11_13:00", "vals": [19, 1, 48, 718, 339]}, {"dt": "2018-07-11_19:00", "vals": [15, 0, 97, 718, 164]}, {"dt": "2018-07-12_01:00", "vals": [15, 0, 84, 717, null]}, {"dt": "2018-07-12_07:00", "vals": [14, 0, 84, 717, null]}, {"dt": "2018-07-12_13:00", "vals": [19, 1, 64, 716, 342]}, {"dt": "2018-07-12_19:00", "vals": [16, 0, 96, 717, null]}, {"dt": "2018-07-13_01:00", "vals": [14, 0, 99, 717, null]}, {"dt": "2018-07-13_07:00", "vals": [15, 0, 96, 717, null]}, {"dt": "2018-07-14_01:00", "vals": [15, 0, 85, 716, null]}, {"dt": "2018-07-14_19:00", "vals": [27, 1, 38, 715, 146]}], "siRange": "08.07.2018 - 14.07.2018", "meteoRange": "08.07.2018 - 14.07.2018", "maxSiWeek": [{"dt": "08.07.2018", "val": 0.2, "name": "Оксид углерода"}, {"dt": "09.07.2018", "val": 0.2, "name": "Оксид углерода"}, {"dt": "10.07.2018", "val": 0.2, "name": "Оксид углерода"}, {"dt": "11.07.2018", "val": 0.2, "name": "Оксид углерода"}, {"dt": "12.07.2018", "val": 0.2, "name": "Оксид углерода"}, {"dt": "13.07.2018", "val": 0.3, "name": "Оксид углерода"}, {"dt": "14.07.2018", "val": 0.2, "name": "Диоксид азота"}], "primsSS": [{"dt": "2018-07-08_00:00", "vals": [null, null, 0.9, 0.012, 0.002, null, null, null]}, {"dt": "2018-07-09_00:00", "vals": [null, null, 0.9, 0.013, 0.004, null, null, null]}, {"dt": "2018-07-10_00:00", "vals": [null, null, 0.9, 0.012, 0.003, null, null, null]}, {"dt": "2018-07-11_00:00", "vals": [null, null, 0.9, 0.023, 0.008, null, null, null]}, {"dt": "2018-07-12_00:00", "vals": [null, null, 0.9, 0.015, 0.004, null, null, null]}, {"dt": "2018-07-13_00:00", "vals": [null, null, 1.3, 0.013, 0.004, null, null, null]}, {"dt": "2018-07-14_00:00", "vals": [null, null, 0.6, 0.028, 0.006, null, null, null]}], "mpcAD": [{"name": "Взвешенные в-ва", "val": 0.15}, {"name": "Диоксид серы", "val": 0.05}, {"name": "Оксид углерода", "val": 3}, {"name": "Диоксид азота", "val": 0.1}, {"name": "Оксид азота", "val": null}, {"name": "Сероводород", "val": null}, {"name": "Хлор", "val": 0.03}, {"name": "Формальдегид", "val": 0.01}], "ispel": 0}, {"ind": "75020101", "name": "Чита", "nom": "6", "place": "ул.Красной Звезды, д.75, МС", "label": "Чита, №6, ул.Красной Звезды, д.75, МС", "lng": "113.478333", "lat": "52.078889", "date": "14.07.2018", "si": [{"name": "Диоксид серы", "val": 0}, {"name": "Оксид углерода", "val": 0.1}, {"name": "Диоксид азота", "val": 0.1}, {"name": "Оксид азота", "val": 0}, {"name": "Озон", "val": 0.1}, {"name": "Сероводород", "val": 0.7}, {"name": "Аммиак", "val": 0}, {"name": "Частицы 10 мкм (сут.)", "val": -32768}, {"name": "Частицы 2.5 мкм (сут.)", "val": -32768}], "maxSi": 0.7, "meteoParamsNames": ["\"Температура\"", "\"Скорость ветра\"", "\"Влажность отн.\"", "\"Давление\"", "\"Направление ветра\""], "meteoParamsValues": [{"dt": "2018-07-09_13:00", "vals": [12, 3, 77, 697, 205]}, {"dt": "2018-07-09_19:00", "vals": [12, 3, 79, 699, 199]}, {"dt": "2018-07-10_01:00", "vals": [11, 2, 80, 701, 203]}, {"dt": "2018-07-10_07:00", "vals": [9, 2, 85, 702, 193]}, {"dt": "2018-07-10_13:00", "vals": [17, 2, 54, 701, 230]}, {"dt": "2018-07-10_19:00", "vals": [20, 1, 54, 700, 74]}, {"dt": "2018-07-11_01:00", "vals": [15, 1, 90, 699, 145]}, {"dt": "2018-07-11_07:00", "vals": [13, 2, 96, 697, 122]}, {"dt": "2018-07-11_13:00", "vals": [14, 2, 96, 692, 234]}, {"dt": "2018-07-11_19:00", "vals": [15, 1, 89, 691, 275]}, {"dt": "2018-07-12_01:00", "vals": [14, 1, 87, 691, 226]}, {"dt": "2018-07-12_07:00", "vals": [14, 2, 86, 690, 210]}, {"dt": "2018-07-12_13:00", "vals": [18, 3, 65, 689, 203]}, {"dt": "2018-07-12_19:00", "vals": [17, 3, 75, 689, 232]}, {"dt": "2018-07-13_01:00", "vals": [15, 2, 77, 689, 230]}, {"dt": "2018-07-13_07:00", "vals": [14, 2, 80, 689, 213]}, {"dt": "2018-07-13_13:00", "vals": [16, 2, 87, 689, 183]}, {"dt": "2018-07-13_19:00", "vals": [18, 2, 89, 689, 219]}, {"dt": "2018-07-14_01:00", "vals": [16, 1, 86, 691, 179]}, {"dt": "2018-07-14_07:00", "vals": [16, 2, 75, 693, 216]}], "siRange": "08.07.2018 - 14.07.2018", "meteoRange": "09.07.2018 - 14.07.2018", "maxSiWeek": [{"dt": "08.07.2018", "val": -32768, "name": ""}, {"dt": "09.07.2018", "val": 0.7, "name": "Оксид углерода"}, {"dt": "10.07.2018", "val": 1.5, "name": "Сероводород"}, {"dt": "11.07.2018", "val": 1.2, "name": "Сероводород"}, {"dt": "12.07.2018", "val": 0.7, "name": "Сероводород"}, {"dt": "13.07.2018", "val": 0.7, "name": "Сероводород"}, {"dt": "14.07.2018", "val": 0.7, "name": "Сероводород"}], "primsSS": [{"dt": "2018-07-09_00:00", "vals": [0, 3.1, 0.003, 0.002, 0.012, 0, 0, null, null]}, {"dt": "2018-07-10_00:00", "vals": [0.005, 2.5, 0.004, 0.003, 0.011, 0.003, 0, null, null]}, {"dt": "2018-07-11_00:00", "vals": [0.008, 0.1, 0.006, 0.002, 0.009, 0.003, 0, null, null]}, {"dt": "2018-07-12_00:00", "vals": [0.007, 0.4, 0.005, 0.002, 0.014, 0.003, 0, null, null]}, {"dt": "2018-07-13_00:00", "vals": [0.008, 0.1, 0.008, 0.004, 0.01, 0.003, 0, null, null]}, {"dt": "2018-07-14_00:00", "vals": [0.01, 0.2, 0.008, 0.002, 0.011, 0.004, 0, null, null]}], "mpcAD": [{"name": "Диоксид серы", "val": 0.05}, {"name": "Оксид углерода", "val": 3}, {"name": "Диоксид азота", "val": 0.1}, {"name": "Оксид азота", "val": null}, {"name": "Озон", "val": 0.1}, {"name": "Сероводород", "val": null}, {"name": "Аммиак", "val": 0.1}, {"name": "Частицы 10 мкм (сут.)", "val": 0.06}, {"name": "Частицы 2.5 мкм (сут.)", "val": 0.035}], "ispel": 0}, {"ind": "38020123", "name": "Черемхово", "nom": "7", "place": "ул.Шевченко, д.72", "label": "Черемхово, ул.Шевченко, д.72", "lng": "103.157164", "lat": "53.114119", "date": "14.07.2018", "si": [{"name": "Взвешенные в-ва", "val": -32768}, {"name": "Диоксид серы", "val": 0}, {"name": "Оксид углерода", "val": 0.1}, {"name": "Диоксид азота", "val": 0.2}, {"name": "Оксид азота", "val": 0}, {"name": "Сероводород", "val": 0.6}], "maxSi": 0.6, "meteoParamsNames": ["\"Температура\"", "\"Скорость ветра\"", "\"Влажность отн.\"", "\"Давление\"", "\"Направление ветра\""], "meteoParamsValues": [{"dt": "2018-07-08_01:00", "vals": [12, 1, 88, 712, 23]}, {"dt": "2018-07-08_07:00", "vals": [12, 2, 87, 712, 22]}, {"dt": "2018-07-08_13:00", "vals": [17, 2, 60, 712, 51]}, {"dt": "2018-07-08_19:00", "vals": [19, 2, 48, 711, 25]}, {"dt": "2018-07-09_01:00", "vals": [12, 1, 80, 711, 32]}, {"dt": "2018-07-09_07:00", "vals": [12, 1, 76, 711, 47]}, {"dt": "2018-07-09_13:00", "vals": [14, 1, 79, 711, 46]}, {"dt": "2018-07-09_19:00", "vals": [14, 2, 63, 712, 44]}, {"dt": "2018-07-10_01:00", "vals": [9, 1, 89, 712, 18]}, {"dt": "2018-07-10_07:00", "vals": [10, 0, 82, 712, 22]}, {"dt": "2018-07-10_13:00", "vals": [15, 0, 61, 711, 25]}, {"dt": "2018-07-10_19:00", "vals": [18, 0, 51, 710, 141]}, {"dt": "2018-07-11_01:00", "vals": [10, 0, 86, 710, null]}, {"dt": "2018-07-11_07:00", "vals": [11, 1, 88, 709, 97]}, {"dt": "2018-07-11_13:00", "vals": [18, 1, 57, 708, 91]}, {"dt": "2018-07-11_19:00", "vals": [18, 1, 55, 707, 33]}, {"dt": "2018-07-12_01:00", "vals": [13, 1, 76, 707, 19]}, {"dt": "2018-07-12_07:00", "vals": [14, 1, 80, 706, 23]}, {"dt": "2018-07-12_13:00", "vals": [17, 1, 76, 706, 58]}, {"dt": "2018-07-12_19:00", "vals": [17, 1, 79, 706, 19]}, {"dt": "2018-07-13_01:00", "vals": [15, 1, 93, 706, 18]}, {"dt": "2018-07-13_07:00", "vals": [16, 2, 91, 707, 18]}, {"dt": "2018-07-13_13:00", "vals": [24, 2, 49, 706, 45]}, {"dt": "2018-07-13_19:00", "vals": [24, 1, 47, 706, 147]}, {"dt": "2018-07-14_01:00", "vals": [16, 0, 80, 706, null]}, {"dt": "2018-07-14_07:00", "vals": [16, 0, 78, 705, null]}, {"dt": "2018-07-14_13:00", "vals": [26, 1, 39, 705, 98]}, {"dt": "2018-07-14_19:00", "vals": [28, 0, 31, 704, 150]}], "siRange": "08.07.2018 - 14.07.2018", "meteoRange": "08.07.2018 - 14.07.2018", "maxSiWeek": [{"dt": "08.07.2018", "val": 0.1, "name": "Диоксид азота"}, {"dt": "09.07.2018", "val": 0.2, "name": "Оксид углерода"}, {"dt": "10.07.2018", "val": 0.9, "name": "Оксид углерода"}, {"dt": "11.07.2018", "val": 0.2, "name": "Оксид углерода"}, {"dt": "12.07.2018", "val": 0.1, "name": "Оксид углерода"}, {"dt": "13.07.2018", "val": 0.2, "name": "Оксид углерода"}, {"dt": "14.07.2018", "val": 0.6, "name": "Сероводород"}], "primsSS": [{"dt": "2018-07-08_00:00", "vals": [null, 0.011, 0.2, 0.017, 0.002, 0]}, {"dt": "2018-07-09_00:00", "vals": [null, 0.013, 0.5, 0.025, 0.005, 0.001]}, {"dt": "2018-07-10_00:00", "vals": [null, 0.005, 2.4, 0.021, 0.006, 0.003]}, {"dt": "2018-07-11_00:00", "vals": [null, 0.002, 0.6, 0.021, 0.004, 0]}, {"dt": "2018-07-12_00:00", "vals": [null, 0.006, 0.4, 0.02, 0.005, 0.001]}, {"dt": "2018-07-13_00:00", "vals": [null, 0.004, 0.6, 0.017, 0.004, 0.001]}, {"dt": "2018-07-14_00:00", "vals": [null, 0.004, 0.5, 0.025, 0.004, 0.002]}], "mpcAD": [{"name": "Взвешенные в-ва", "val": 0.15}, {"name": "Диоксид серы", "val": 0.05}, {"name": "Оксид углерода", "val": 3}, {"name": "Диоксид азота", "val": 0.1}, {"name": "Оксид азота", "val": null}, {"name": "Сероводород", "val": null}], "ispel": 0}, {"ind": "38020109", "name": "Иркутск", "nom": "20", "place": "ул.Мира, д.101", "label": "Иркутск, ул.Мира, д.101", "lng": "104.210861", "lat": "52.350167", "date": "14.07.2018", "si": [{"name": "Взвешенные в-ва", "val": -32768}, {"name": "Диоксид серы", "val": 0}, {"name": "Оксид углерода", "val": 0.1}, {"name": "Диоксид азота", "val": -32768}, {"name": "Оксид азота", "val": -32768}, {"name": "Сероводород", "val": 0.2}, {"name": "Аммиак", "val": -32768}, {"name": "Бензол", "val": -32768}, {"name": "Ксилол", "val": -32768}, {"name": "Стирол", "val": -32768}, {"name": "Толуол", "val": -32768}, {"name": "Хлорбензол", "val": -32768}, {"name": "Этилбензол", "val": -32768}, {"name": "Кумол", "val": -32768}], "maxSi": 0.2, "meteoParamsNames": ["\"Температура\"", "\"Скорость ветра\"", "\"Влажность отн.\"", "\"Давление\"", "\"Направление ветра\""], "meteoParamsValues": [{"dt": "2018-07-08_01:00", "vals": [13, 1, 81, 722, 309]}, {"dt": "2018-07-08_07:00", "vals": [14, 1, 82, 722, 307]}, {"dt": "2018-07-08_13:00", "vals": [18, 2, 62, 721, 296]}, {"dt": "2018-07-08_19:00", "vals": [16, 0, 67, 721, 295]}, {"dt": "2018-07-09_01:00", "vals": [12, 0, 84, 721, null]}, {"dt": "2018-07-09_19:00", "vals": [16, 1, 64, 722, 349]}, {"dt": "2018-07-10_19:00", "vals": [19, 0, 48, 720, null]}, {"dt": "2018-07-12_07:00", "vals": [14, 1, 81, 716, 283]}, {"dt": "2018-07-13_01:00", "vals": [15, 0, 91, 716, null]}, {"dt": "2018-07-14_01:00", "vals": [0, 1, 95, 716, 164]}, {"dt": "2018-07-14_19:00", "vals": [27, 0, 38, 714, null]}], "siRange": "08.07.2018 - 14.07.2018", "meteoRange": "08.07.2018 - 14.07.2018", "maxSiWeek": [{"dt": "08.07.2018", "val": 0.2, "name": "Сероводород"}, {"dt": "09.07.2018", "val": 0.6, "name": "Сероводород"}, {"dt": "10.07.2018", "val": 0.9, "name": "Оксид углерода"}, {"dt": "11.07.2018", "val": -32768, "name": ""}, {"dt": "12.07.2018", "val": 0.4, "name": "Сероводород"}, {"dt": "13.07.2018", "val": 0.3, "name": "Сероводород"}, {"dt": "14.07.2018", "val": 0.2, "name": "Сероводород"}], "primsSS": [{"dt": "2018-07-08_00:00", "vals": [null, 0.011, 0.3, null, null, 0.001, null, null, null, null, null, null, null, null]}, {"dt": "2018-07-09_00:00", "vals": [null, 0.038, 0.2, null, null, 0.005, null, null, null, null, null, null, null, null]}, {"dt": "2018-07-10_00:00", "vals": [null, 0.053, 4.5, null, null, 0.005, null, null, null, null, null, null, null, null]}, {"dt": "2018-07-12_00:00", "vals": [null, 0.037, 0.4, null, null, 0.004, null, null, null, null, null, null, null, null]}, {"dt": "2018-07-13_00:00", "vals": [null, 0.015, 0.3, null, null, 0.002, null, null, null, null, null, null, null, null]}, {"dt": "2018-07-14_00:00", "vals": [null, 0.01, 0.4, null, null, 0.002, null, null, null, null, null, null, null, null]}], "mpcAD": [{"name": "Взвешенные в-ва", "val": 0.15}, {"name": "Диоксид серы", "val": 0.05}, {"name": "Оксид углерода", "val": 3}, {"name": "Диоксид азота", "val": 0.1}, {"name": "Оксид азота", "val": null}, {"name": "Сероводород", "val": null}, {"name": "Аммиак", "val": 0.1}, {"name": "Бензол", "val": 0.06}, {"name": "Ксилол", "val": null}, {"name": "Стирол", "val": null}, {"name": "Толуол", "val": null}, {"name": "Хлорбензол", "val": null}, {"name": "Этилбензол", "val": null}, {"name": "Кумол", "val": null}], "ispel": 0}, {"ind": "38020101", "name": "Иркутск", "nom": "23", "place": "ул.Севастопольская, д.239а", "label": "Иркутск, ул.Севастопольская, д.239а", "lng": "104.162517", "lat": "52.351467", "date": "14.07.2018", "si": [{"name": "Взвешенные в-ва", "val": -32768}, {"name": "Диоксид серы", "val": 0}, {"name": "Оксид углерода", "val": 0.1}, {"name": "Диоксид азота", "val": 0}, {"name": "Оксид азота", "val": 0}, {"name": "Озон", "val": 0.4}, {"name": "Сероводород", "val": 0.7}, {"name": "Сумма углеводородов", "val": 0}, {"name": "Аммиак", "val": 0}, {"name": "Формальдегид", "val": -32768}, {"name": "Метан", "val": -32768}, {"name": "Частицы 10 мкм (сут.)", "val": -32768}, {"name": "Частицы 2.5 мкм (сут.)", "val": -32768}], "maxSi": 0.7, "meteoParamsNames": ["\"Температура\"", "\"Скорость ветра\"", "\"Влажность отн.\"", "\"Давление\"", "\"Направление ветра\""], "meteoParamsValues": [{"dt": "2018-07-08_01:00", "vals": [13, 2, 83, 718, 28]}, {"dt": "2018-07-08_19:00", "vals": [16, 1, 65, 717, 28]}, {"dt": "2018-07-09_01:00", "vals": [12, 1, 79, 716, 28]}, {"dt": "2018-07-09_19:00", "vals": [15, 0, 63, 717, 30]}, {"dt": "2018-07-10_13:00", "vals": [16, 0, 58, 717, 26]}, {"dt": "2018-07-11_07:00", "vals": [11, 1, 84, 715, 30]}, {"dt": "2018-07-12_07:00", "vals": [14, 2, 82, 712, 28]}, {"dt": "2018-07-13_01:00", "vals": [15, 1, 87, 712, 28]}, {"dt": "2018-07-13_19:00", "vals": [21, 0, 67, 711, 9]}, {"dt": "2018-07-14_01:00", "vals": [16, 0, 96, 712, null]}, {"dt": "2018-07-14_19:00", "vals": [27, 0, 36, 710, 10]}], "siRange": "08.07.2018 - 14.07.2018", "meteoRange": "08.07.2018 - 14.07.2018", "maxSiWeek": [{"dt": "08.07.2018", "val": 0.2, "name": "Озон"}, {"dt": "09.07.2018", "val": 0.2, "name": "Озон"}, {"dt": "10.07.2018", "val": 0.2, "name": "Озон"}, {"dt": "11.07.2018", "val": 0.1, "name": "Диоксид серы"}, {"dt": "12.07.2018", "val": 0.1, "name": "Озон"}, {"dt": "13.07.2018", "val": 0.4, "name": "Сероводород"}, {"dt": "14.07.2018", "val": 0.7, "name": "Сероводород"}], "primsSS": [{"dt": "2018-07-08_00:00", "vals": [null, 0.001, 0.2, 0.005, 0, 0.029, 0, 0, 0, null, 0, null, null]}, {"dt": "2018-07-09_00:00", "vals": [null, 0.007, 0.2, 0.007, 0.001, 0.034, 0, 0, 0, null, 0, null, null]}, {"dt": "2018-07-10_00:00", "vals": [null, 0.052, 0.2, 0.011, 0.001, 0.031, 0, 0, 0, null, 0, null, null]}, {"dt": "2018-07-11_00:00", "vals": [null, 0.026, 0.3, 0.006, 0.001, 0.013, 0.001, 0, 0, null, 0, null, null]}, {"dt": "2018-07-12_00:00", "vals": [null, 0.004, 0.2, 0.001, 0.001, 0.016, 0, 0, 0, null, 0, null, null]}, {"dt": "2018-07-13_00:00", "vals": [null, 0.007, 0.4, 0.005, 0, 0.027, 0.002, 0, 0, null, 0, null, null]}, {"dt": "2018-07-14_00:00", "vals": [null, 0.009, 0.4, 0.005, 0.009, 0.033, 0.003, 0, 0, null, 0, null, null]}], "mpcAD": [{"name": "Взвешенные в-ва", "val": 0.15}, {"name": "Диоксид серы", "val": 0.05}, {"name": "Оксид углерода", "val": 3}, {"name": "Диоксид азота", "val": 0.1}, {"name": "Оксид азота", "val": null}, {"name": "Озон", "val": 0.1}, {"name": "Сероводород", "val": null}, {"name": "Сумма углеводородов", "val": 5}, {"name": "Аммиак", "val": 0.1}, {"name": "Формальдегид", "val": 0.01}, {"name": "Метан", "val": null}, {"name": "Частицы 10 мкм (сут.)", "val": 0.06}, {"name": "Частицы 2.5 мкм (сут.)", "val": 0.035}], "ispel": 0}, {"ind": "38020103", "name": "Ангарск", "nom": "25", "place": "ул.Ворошилова, д.49", "label": "Ангарск, ул.Ворошилова, д.49", "lng": "103.882727", "lat": "52.530861", "date": "14.07.2018", "si": [{"name": "Взвешенные в-ва", "val": -32768}, {"name": "Диоксид серы", "val": 0.1}, {"name": "Оксид углерода", "val": 0.2}, {"name": "Диоксид азота", "val": 0.3}, {"name": "Оксид азота", "val": 0.2}, {"name": "Сероводород", "val": 0.3}, {"name": "Аммиак", "val": 0}, {"name": "Формальдегид", "val": -32768}], "maxSi": 0.3, "meteoParamsNames": ["\"Температура\"", "\"Скорость ветра\"", "\"Влажность отн.\"", "\"Давление\"", "\"Направление ветра\""], "meteoParamsValues": [{"dt": "2018-07-08_01:00", "vals": [13, 2, 83, 722, 299]}, {"dt": "2018-07-08_07:00", "vals": [14, 2, 80, 722, 289]}, {"dt": "2018-07-08_13:00", "vals": [17, 2, 74, 722, 329]}, {"dt": "2018-07-08_19:00", "vals": [15, 1, 79, 721, 271]}, {"dt": "2018-07-09_01:00", "vals": [12, 1, 83, 721, 285]}, {"dt": "2018-07-09_07:00", "vals": [12, 1, 80, 721, 300]}, {"dt": "2018-07-09_13:00", "vals": [18, 1, 74, 720, 319]}, {"dt": "2018-07-09_19:00", "vals": [16, 1, 74, 722, 330]}, {"dt": "2018-07-10_01:00", "vals": [12, 1, 75, 723, 317]}, {"dt": "2018-07-10_07:00", "vals": [10, 1, 80, 723, 288]}, {"dt": "2018-07-10_19:00", "vals": [19, 0, 73, 720, 204]}, {"dt": "2018-07-11_01:00", "vals": [12, 0, 77, 720, 324]}, {"dt": "2018-07-11_07:00", "vals": [11, 1, 82, 719, 298]}, {"dt": "2018-07-11_13:00", "vals": [19, 2, 74, 718, 329]}, {"dt": "2018-07-12_01:00", "vals": [13, 2, 89, 717, 276]}, {"dt": "2018-07-12_07:00", "vals": [14, 1, 82, 716, 280]}, {"dt": "2018-07-12_13:00", "vals": [21, 2, 73, 715, 290]}, {"dt": "2018-07-12_19:00", "vals": [16, 2, 85, 716, 279]}, {"dt": "2018-07-13_01:00", "vals": [14, 0, 88, 716, null]}, {"dt": "2018-07-13_07:00", "vals": [15, 2, 85, 717, 274]}, {"dt": "2018-07-13_13:00", "vals": [23, 2, 73, 716, 321]}, {"dt": "2018-07-13_19:00", "vals": [24, 1, 73, 715, 196]}, {"dt": "2018-07-14_01:00", "vals": [16, 0, 88, 716, null]}, {"dt": "2018-07-14_07:00", "vals": [14, 1, 91, 716, 196]}, {"dt": "2018-07-14_13:00", "vals": [27, 2, 72, 715, 200]}, {"dt": "2018-07-14_19:00", "vals": [27, 2, 72, 714, 200]}], "siRange": "08.07.2018 - 14.07.2018", "meteoRange": "08.07.2018 - 14.07.2018", "maxSiWeek": [{"dt": "08.07.2018", "val": 0.2, "name": "Диоксид азота"}, {"dt": "09.07.2018", "val": 0.4, "name": "Диоксид азота"}, {"dt": "10.07.2018", "val": 0.3, "name": "Диоксид азота"}, {"dt": "11.07.2018", "val": 0.2, "name": "Диоксид азота"}, {"dt": "12.07.2018", "val": 0.2, "name": "Диоксид азота"}, {"dt": "13.07.2018", "val": 0.3, "name": "Диоксид азота"}, {"dt": "14.07.2018", "val": 0.3, "name": "Диоксид азота"}], "primsSS": [{"dt": "2018-07-08_00:00", "vals": [null, 0, 0.2, 0.021, 0.012, 0, 0, null]}, {"dt": "2018-07-09_00:00", "vals": [null, 0, 0.5, 0.041, 0.043, 0.001, 0, null]}, {"dt": "2018-07-10_00:00", "vals": [null, 0.021, 0.3, 0.035, 0.02, 0.001, 0, null]}, {"dt": "2018-07-11_00:00", "vals": [null, 0.001, 0.6, 0.039, 0.032, 0, 0, null]}, {"dt": "2018-07-12_00:00", "vals": [null, 0, 0.3, 0.025, 0.021, 0.001, 0, null]}, {"dt": "2018-07-13_00:00", "vals": [null, 0.008, 0.4, 0.037, 0.024, 0.001, 0, null]}, {"dt": "2018-07-14_00:00", "vals": [null, 0.018, 0.5, 0.04, 0.031, 0.001, 0, null]}], "mpcAD": [{"name": "Взвешенные в-ва", "val": 0.15}, {"name": "Диоксид серы", "val": 0.05}, {"name": "Оксид углерода", "val": 3}, {"name": "Диоксид азота", "val": 0.1}, {"name": "Оксид азота", "val": null}, {"name": "Сероводород", "val": null}, {"name": "Аммиак", "val": 0.1}, {"name": "Формальдегид", "val": 0.01}], "ispel": 0}, {"ind": "38020104", "name": "Ангарск", "nom": "41", "place": "ул.Московская, п.о.30", "label": "Ангарск, ул.Московская, п.о.30", "lng": "103.881717", "lat": "52.541858", "date": "14.07.2018", "si": [{"name": "Взвешенные в-ва", "val": -32768}, {"name": "Диоксид серы", "val": 0.2}, {"name": "Оксид углерода", "val": 0.2}, {"name": "Диоксид азота", "val": -32768}, {"name": "Оксид азота", "val": -32768}, {"name": "Озон", "val": 0.5}, {"name": "Сероводород", "val": 0.1}, {"name": "Фторид водорода", "val": -32768}, {"name": "Формальдегид", "val": -32768}, {"name": "Частицы 10 мкм (сут.)", "val": -32768}], "maxSi": 0.5, "meteoParamsNames": ["\"Температура\"", "\"Скорость ветра\"", "\"Влажность отн.\"", "\"Давление\"", "\"Направление ветра\""], "meteoParamsValues": [{"dt": "2018-07-08_01:00", "vals": [13, 0, 89, 723, 222]}, {"dt": "2018-07-08_07:00", "vals": [13, 0, 84, 723, 221]}, {"dt": "2018-07-08_13:00", "vals": [17, 1, 66, 722, 249]}, {"dt": "2018-07-08_19:00", "vals": [15, 0, 81, 722, 188]}, {"dt": "2018-07-09_01:00", "vals": [12, 0, 93, 722, null]}, {"dt": "2018-07-09_07:00", "vals": [11, 0, 87, 722, 224]}, {"dt": "2018-07-09_13:00", "vals": [18, 0, 48, 721, 225]}, {"dt": "2018-07-09_19:00", "vals": [16, 0, 65, 722, null]}, {"dt": "2018-07-10_01:00", "vals": [11, 0, 77, 723, null]}, {"dt": "2018-07-10_19:00", "vals": [19, 0, 48, 721, null]}, {"dt": "2018-07-11_01:00", "vals": [11, 0, 86, 720, null]}, {"dt": "2018-07-11_07:00", "vals": [10, 0, 90, 720, null]}, {"dt": "2018-07-11_13:00", "vals": [19, 1, 52, 718, 254]}, {"dt": "2018-07-11_19:00", "vals": [14, 0, 97, 718, null]}, {"dt": "2018-07-12_01:00", "vals": [13, 0, 99, 717, null]}, {"dt": "2018-07-12_07:00", "vals": [13, 0, 90, 717, null]}, {"dt": "2018-07-12_13:00", "vals": [21, 1, 54, 716, 228]}, {"dt": "2018-07-12_19:00", "vals": [15, 0, 95, 717, 206]}, {"dt": "2018-07-13_01:00", "vals": [13, 0, 98, 717, null]}, {"dt": "2018-07-13_07:00", "vals": [15, 0, 94, 717, null]}, {"dt": "2018-07-13_13:00", "vals": [23, 0, 59, 716, 239]}, {"dt": "2018-07-13_19:00", "vals": [24, 1, 54, 716, 39]}, {"dt": "2018-07-14_01:00", "vals": [15, 0, 97, 716, null]}, {"dt": "2018-07-14_07:00", "vals": [14, 0, 99, 716, 29]}, {"dt": "2018-07-14_13:00", "vals": [29, 1, 35, 715, 39]}, {"dt": "2018-07-14_19:00", "vals": [27, 1, 32, 715, 35]}], "siRange": "08.07.2018 - 14.07.2018", "meteoRange": "08.07.2018 - 14.07.2018", "maxSiWeek": [{"dt": "08.07.2018", "val": 0.3, "name": "Озон"}, {"dt": "09.07.2018", "val": 0.3, "name": "Озон"}, {"dt": "10.07.2018", "val": 0.4, "name": "Озон"}, {"dt": "11.07.2018", "val": 0.3, "name": "Озон"}, {"dt": "12.07.2018", "val": 0.2, "name": "Озон"}, {"dt": "13.07.2018", "val": 0.3, "name": "Озон"}, {"dt": "14.07.2018", "val": 0.5, "name": "Озон"}], "primsSS": [{"dt": "2018-07-08_00:00", "vals": [null, 0.002, 0.3, null, null, 0.039, 0, null, null, null]}, {"dt": "2018-07-09_00:00", "vals": [null, 0.001, 0.3, null, null, 0.038, 0.001, null, null, null]}, {"dt": "2018-07-10_00:00", "vals": [null, 0.029, 0.4, null, null, 0.054, 0.001, null, null, null]}, {"dt": "2018-07-11_00:00", "vals": [null, 0.002, 0.5, null, null, 0.027, 0.001, null, null, null]}, {"dt": "2018-07-12_00:00", "vals": [null, 0.001, 0.4, null, null, 0.028, 0, null, null, null]}, {"dt": "2018-07-13_00:00", "vals": [null, 0.017, 0.4, null, null, 0.034, 0.001, null, null, null]}, {"dt": "2018-07-14_00:00", "vals": [null, 0.029, 0.6, null, null, 0.042, 0.001, null, null, null]}], "mpcAD": [{"name": "Взвешенные в-ва", "val": 0.15}, {"name": "Диоксид серы", "val": 0.05}, {"name": "Оксид углерода", "val": 3}, {"name": "Диоксид азота", "val": 0.1}, {"name": "Оксид азота", "val": null}, {"name": "Озон", "val": 0.1}, {"name": "Сероводород", "val": null}, {"name": "Фторид водорода", "val": 0.014}, {"name": "Формальдегид", "val": 0.01}, {"name": "Частицы 10 мкм (сут.)", "val": 0.06}], "ispel": 0}, {"ind": "38020102", "name": "Байкальск", "nom": "47", "place": "Промбаза, МС", "label": "Байкальск, Промбаза, МС", "lng": "104.174733", "lat": "51.51615", "date": "14.07.2018", "si": [{"name": "Взвешенные в-ва", "val": -32768}, {"name": "Диоксид серы", "val": 0}, {"name": "Оксид углерода", "val": -32768}, {"name": "Диоксид азота", "val": -32768}, {"name": "Оксид азота", "val": -32768}, {"name": "Озон", "val": 0.4}, {"name": "Сероводород", "val": 0.4}, {"name": "Сумма углеводородов", "val": 0}, {"name": "Аммиак", "val": -32768}, {"name": "Частицы 10 мкм", "val": 0.1}, {"name": "Метан", "val": -32768}, {"name": "Частицы 2.5 мкм", "val": 0}, {"name": "Частицы 10 мкм (сут.)", "val": -32768}, {"name": "Частицы 2.5 мкм (сут.)", "val": -32768}], "maxSi": 0.4, "meteoParamsNames": ["\"Температура\"", "\"Скорость ветра\"", "\"Влажность отн.\"", "\"Давление\"", "\"Направление ветра\""], "meteoParamsValues": [{"dt": "2018-07-08_01:00", "vals": [13, 0, 99, 719, null]}, {"dt": "2018-07-08_07:00", "vals": [13, 0, 99, 719, 269]}, {"dt": "2018-07-08_13:00", "vals": [16, 2, 75, 719, 298]}, {"dt": "2018-07-08_19:00", "vals": [14, 1, 82, 718, 183]}, {"dt": "2018-07-09_01:00", "vals": [12, 0, 99, 717, 256]}, {"dt": "2018-07-09_07:00", "vals": [13, 0, 99, 718, 253]}, {"dt": "2018-07-09_13:00", "vals": [18, 2, 56, 717, 154]}, {"dt": "2018-07-09_19:00", "vals": [15, 1, 76, 718, 279]}, {"dt": "2018-07-10_01:00", "vals": [11, 0, 99, 719, null]}, {"dt": "2018-07-10_07:00", "vals": [12, 1, 98, 718, 47]}, {"dt": "2018-07-10_13:00", "vals": [14, 1, 69, 718, 44]}, {"dt": "2018-07-10_19:00", "vals": [13, 0, 99, 717, 34]}, {"dt": "2018-07-11_01:00", "vals": [11, 0, null, 716, null]}, {"dt": "2018-07-11_07:00", "vals": [11, 0, null, 715, null]}, {"dt": "2018-07-11_13:00", "vals": [13, 0, null, 715, 204]}, {"dt": "2018-07-11_19:00", "vals": [12, 0, null, 714, 235]}, {"dt": "2018-07-12_01:00", "vals": [12, 1, null, 713, 282]}, {"dt": "2018-07-12_07:00", "vals": [13, 0, null, 713, 280]}, {"dt": "2018-07-12_13:00", "vals": [20, 1, 60, 712, 275]}, {"dt": "2018-07-12_19:00", "vals": [16, 0, 99, 712, null]}, {"dt": "2018-07-13_01:00", "vals": [14, 0, null, 713, null]}, {"dt": "2018-07-13_07:00", "vals": [16, 0, 99, 713, 251]}, {"dt": "2018-07-13_13:00", "vals": [24, 1, 52, 713, 61]}, {"dt": "2018-07-13_19:00", "vals": [20, 0, 74, 712, 50]}, {"dt": "2018-07-14_01:00", "vals": [13, 0, 99, 712, null]}, {"dt": "2018-07-14_07:00", "vals": [17, 0, 89, 712, null]}, {"dt": "2018-07-14_13:00", "vals": [20, 2, 66, 711, 46]}, {"dt": "2018-07-14_19:00", "vals": [18, 0, 72, 712, 106]}], "siRange": "08.07.2018 - 14.07.2018", "meteoRange": "08.07.2018 - 14.07.2018", "maxSiWeek": [{"dt": "08.07.2018", "val": 0.3, "name": "Озон"}, {"dt": "09.07.2018", "val": 0.4, "name": "Сероводород"}, {"dt": "10.07.2018", "val": 0.4, "name": "Озон"}, {"dt": "11.07.2018", "val": 0.3, "name": "Озон"}, {"dt": "12.07.2018", "val": 0.3, "name": "Озон"}, {"dt": "13.07.2018", "val": 0.7, "name": "Сероводород"}, {"dt": "14.07.2018", "val": 0.4, "name": "Озон"}], "primsSS": [{"dt": "2018-07-08_00:00", "vals": [null, 0.002, null, null, null, 0.045, 0.002, 0, null, 0.01, 0, 0, null, null]}, {"dt": "2018-07-09_00:00", "vals": [null, 0.002, null, null, null, 0.041, 0.002, 0, null, 0.008, 0, 0, null, null]}, {"dt": "2018-07-10_00:00", "vals": [null, 0.007, null, null, null, 0.047, 0.001, 0, null, 0.017, 0, 0, null, null]}, {"dt": "2018-07-11_00:00", "vals": [null, 0.003, null, null, null, 0.028, 0.001, 0, null, 0.024, 0, 0, null, null]}, {"dt": "2018-07-12_00:00", "vals": [null, 0.006, null, null, null, 0.037, 0.002, 0, null, 0.014, 0, 0, null, null]}, {"dt": "2018-07-13_00:00", "vals": [null, 0.007, null, null, null, 0.038, 0.002, 0, null, 0.015, 0, 0, null, null]}, {"dt": "2018-07-14_00:00", "vals": [null, 0.006, null, null, null, 0.04, 0.002, 0, null, 0.021, 0, 0, null, null]}], "mpcAD": [{"name": "Взвешенные в-ва", "val": 0.15}, {"name": "Диоксид серы", "val": 0.05}, {"name": "Оксид углерода", "val": 3}, {"name": "Диоксид азота", "val": 0.1}, {"name": "Оксид азота", "val": null}, {"name": "Озон", "val": 0.1}, {"name": "Сероводород", "val": null}, {"name": "Сумма углеводородов", "val": 5}, {"name": "Аммиак", "val": 0.1}, {"name": "Частицы 10 мкм", "val": 0.06}, {"name": "Метан", "val": null}, {"name": "Частицы 2.5 мкм", "val": 0.035}, {"name": "Частицы 10 мкм (сут.)", "val": 0.06}, {"name": "Частицы 2.5 мкм (сут.)", "val": 0.035}], "ispel": 0}]}, {"type": 1, "stations": [{"ind": "24050201", "name": "Красноярск(ТСН)", "nom": "1", "place": "ул.Мате Залки, д.4", "label": "Красноярск(ТСН), №1, ул.Мате Залки, д.4", "lng": "92.941833", "lat": "56.067389", "date": "14.07.2018", "si": [{"name": "Диоксид серы", "val": 0}, {"name": "Оксид углерода", "val": 0.2}, {"name": "Диоксид азота", "val": 1.1}, {"name": "Оксид азота", "val": 0}, {"name": "Сероводород", "val": 0}, {"name": "Фенол", "val": -32768}, {"name": "Свинец", "val": -32768}, {"name": "Аммиак", "val": -32768}, {"name": "Бензол", "val": -32768}, {"name": "Стирол", "val": -32768}, {"name": "Толуол", "val": -32768}, {"name": "Хлорбензол", "val": -32768}, {"name": "Этилбензол", "val": -32768}, {"name": "Частицы 2.5 мкм", "val": -32768}, {"name": "МП-ксилол", "val": -32768}, {"name": "О-ксилол", "val": -32768}], "maxSi": 1.1, "meteoParamsNames": ["\"Температура\"", "\"Скорость ветра\"", "\"Влажность отн.\"", "\"Давление\"", "\"Направление ветра\""], "meteoParamsValues": [{"dt": "2018-07-08_01:00", "vals": [13, 0, 77, 746, 0]}, {"dt": "2018-07-08_07:00", "vals": [15, 0, 74, 746, 0]}, {"dt": "2018-07-08_13:00", "vals": [20, 1, 46, 746, 37]}, {"dt": "2018-07-08_19:00", "vals": [18, 0, 54, 746, 26]}, {"dt": "2018-07-09_01:00", "vals": [13, 0, 77, 746, 0]}, {"dt": "2018-07-09_07:00", "vals": [null, null, null, null, null]}, {"dt": "2018-07-09_13:00", "vals": [22, 1, 47, 745, 40]}, {"dt": "2018-07-09_19:00", "vals": [23, 0, 39, 744, 0]}, {"dt": "2018-07-10_01:00", "vals": [null, null, null, null, null]}, {"dt": "2018-07-10_07:00", "vals": [15, 0, 66, 743, 0]}, {"dt": "2018-07-10_13:00", "vals": [25, 0, 39, 741, 28]}, {"dt": "2018-07-10_19:00", "vals": [25, 0, 44, 741, 27]}, {"dt": "2018-07-11_01:00", "vals": [19, 0, 72, 741, 0]}, {"dt": "2018-07-11_07:00", "vals": [18, 0, 78, 740, 0]}, {"dt": "2018-07-11_13:00", "vals": [24, 0, 52, 739, 0]}, {"dt": "2018-07-11_19:00", "vals": [25, 0, 53, 738, 0]}, {"dt": "2018-07-12_01:00", "vals": [19, 0, 75, 738, 0]}, {"dt": "2018-07-12_07:00", "vals": [18, 0, 78, 737, 0]}, {"dt": "2018-07-12_13:00", "vals": [29, 0, 44, 736, 0]}, {"dt": "2018-07-12_19:00", "vals": [28, 0, 45, 736, 26]}, {"dt": "2018-07-13_01:00", "vals": [21, 0, 73, 736, 0]}, {"dt": "2018-07-13_07:00", "vals": [21, 0, 75, 736, 0]}, {"dt": "2018-07-13_13:00", "vals": [27, 0, 57, 735, 0]}, {"dt": "2018-07-13_19:00", "vals": [28, 0, 47, 734, 0]}, {"dt": "2018-07-14_01:00", "vals": [20, 0, 75, 734, 0]}, {"dt": "2018-07-14_07:00", "vals": [20, 0, 76, 734, 0]}, {"dt": "2018-07-14_13:00", "vals": [29, 0, 44, 734, 0]}, {"dt": "2018-07-14_19:00", "vals": [27, 0, 59, 735, 0]}], "siRange": "08.07.2018 - 14.07.2018", "meteoRange": "08.07.2018 - 14.07.2018", "maxSiWeek": [{"dt": "08.07.2018", "val": 0.1, "name": "Диоксид серы"}, {"dt": "09.07.2018", "val": 0, "name": "Диоксид серы"}, {"dt": "10.07.2018", "val": 0, "name": "Диоксид серы"}, {"dt": "11.07.2018", "val": 0, "name": "Диоксид серы"}, {"dt": "12.07.2018", "val": 0.2, "name": "Оксид углерода"}, {"dt": "13.07.2018", "val": 0.6, "name": "Диоксид азота"}, {"dt": "14.07.2018", "val": 1.1, "name": "Диоксид азота"}], "primsSS": [{"dt": "2018-07-08_00:00", "vals": [0.009, 0, 0.002, 0, 0, null, null, 0, null, null, null, null, null, null, null, null]}, {"dt": "2018-07-09_00:00", "vals": [0.002, 0, 0, 0.002, 0, null, null, 0, null, null, null, null, null, null, null, null]}, {"dt": "2018-07-10_00:00", "vals": [0.001, 0, 0, 0, 0, null, null, 0, null, null, null, null, null, null, null, null]}, {"dt": "2018-07-11_00:00", "vals": [0.004, 0, 0, 0, 0, null, null, 0, null, null, null, null, null, null, null, null]}, {"dt": "2018-07-12_00:00", "vals": [0.006, 0.3, null, null, 0, null, null, null, null, null, null, null, null, null, null, null]}, {"dt": "2018-07-13_00:00", "vals": [0, 0, 0.08, 0, 0, null, null, null, null, null, null, null, null, null, null, null]}, {"dt": "2018-07-14_00:00", "vals": [0.003, 0.5, 0.1, 0.004, 0, null, null, null, null, null, null, null, null, null, null, null]}], "mpcAD": [{"name": "Диоксид серы", "val": 0.05}, {"name": "Оксид углерода", "val": 3}, {"name": "Диоксид азота", "val": 0.1}, {"name": "Оксид азота", "val": null}, {"name": "Сероводород", "val": null}, {"name": "Фенол", "val": 0.006}, {"name": "Свинец", "val": 0.0003}, {"name": "Аммиак", "val": 0.1}, {"name": "Бензол", "val": 0.06}, {"name": "Стирол", "val": null}, {"name": "Толуол", "val": null}, {"name": "Хлорбензол", "val": null}, {"name": "Этилбензол", "val": null}, {"name": "Частицы 2.5 мкм", "val": 0.035}, {"name": "МП-ксилол", "val": 0.04}, {"name": "О-ксилол", "val": null}], "ispel": 0}, {"ind": "24050202", "name": "Красноярск(ТСН)", "nom": "2", "place": "бул.Солнечный, д.2", "label": "Красноярск(ТСН), №2, бул.Солнечный, д.2", "lng": "92.937278", "lat": "56.117167", "date": "14.07.2018", "si": [{"name": "Диоксид серы", "val": 0.2}, {"name": "Оксид углерода", "val": 0.4}, {"name": "Диоксид азота", "val": 0.4}, {"name": "Оксид азота", "val": 0}, {"name": "Сероводород", "val": 0}, {"name": "Фенол", "val": -32768}, {"name": "Бензол", "val": -32768}, {"name": "Стирол", "val": -32768}, {"name": "Толуол", "val": -32768}, {"name": "Хлорбензол", "val": -32768}, {"name": "Этилбензол", "val": -32768}, {"name": "МП-ксилол", "val": -32768}, {"name": "О-ксилол", "val": -32768}], "maxSi": 0.4, "meteoParamsNames": ["\"Температура\"", "\"Скорость ветра\"", "\"Влажность отн.\"", "\"Давление\"", "\"Направление ветра\""], "meteoParamsValues": [{"dt": "2018-07-08_01:00", "vals": [13, 0, 75, 734, 0]}, {"dt": "2018-07-08_07:00", "vals": [12, 1, 85, 734, 294]}, {"dt": "2018-07-08_13:00", "vals": [17, 3, 54, 734, 300]}, {"dt": "2018-07-08_19:00", "vals": [16, 0, 60, 734, 10]}, {"dt": "2018-07-09_01:00", "vals": [14, 0, 75, 734, 0]}, {"dt": "2018-07-09_07:00", "vals": [12, 0, 85, 734, 0]}, {"dt": "2018-07-09_13:00", "vals": [21, 3, 45, 733, 58]}, {"dt": "2018-07-09_19:00", "vals": [21, 1, 41, 732, 40]}, {"dt": "2018-07-10_01:00", "vals": [18, 0, 47, 731, 91]}, {"dt": "2018-07-10_07:00", "vals": [15, 1, 62, 731, 174]}, {"dt": "2018-07-10_13:00", "vals": [23, 3, 42, 730, 53]}, {"dt": "2018-07-10_19:00", "vals": [23, 3, 49, 729, 66]}, {"dt": "2018-07-11_01:00", "vals": [18, 0, 71, 729, 34]}, {"dt": "2018-07-11_07:00", "vals": [17, 0, 81, 729, 0]}, {"dt": "2018-07-11_13:00", "vals": [23, 2, 56, 728, 67]}, {"dt": "2018-07-11_19:00", "vals": [24, 0, 53, 727, 64]}, {"dt": "2018-07-12_01:00", "vals": [20, 0, 69, 726, 0]}, {"dt": "2018-07-12_07:00", "vals": [20, 0, 69, 726, 77]}, {"dt": "2018-07-12_13:00", "vals": [27, 2, 47, 725, 100]}, {"dt": "2018-07-12_19:00", "vals": [27, 2, 50, 725, 87]}, {"dt": "2018-07-13_01:00", "vals": [22, 0, 64, 725, 0]}, {"dt": "2018-07-13_07:00", "vals": [20, 0, 76, 725, 0]}, {"dt": "2018-07-13_13:00", "vals": [26, 3, 57, 724, 78]}, {"dt": "2018-07-13_19:00", "vals": [26, 1, 50, 723, 66]}, {"dt": "2018-07-14_01:00", "vals": [22, 0, 64, 723, 0]}, {"dt": "2018-07-14_07:00", "vals": [22, 0, 75, 723, 0]}, {"dt": "2018-07-14_13:00", "vals": [26, 2, 50, 723, 50]}, {"dt": "2018-07-14_19:00", "vals": [25, 2, 61, 724, 48]}], "siRange": "08.07.2018 - 14.07.2018", "meteoRange": "08.07.2018 - 14.07.2018", "maxSiWeek": [{"dt": "08.07.2018", "val": 0.2, "name": "Диоксид азота"}, {"dt": "09.07.2018", "val": 0.1, "name": "Диоксид азота"}, {"dt": "10.07.2018", "val": 0.2, "name": "Диоксид азота"}, {"dt": "11.07.2018", "val": 0.4, "name": "Диоксид азота"}, {"dt": "12.07.2018", "val": 0.5, "name": "Диоксид азота"}, {"dt": "13.07.2018", "val": 0.4, "name": "Диоксид азота"}, {"dt": "14.07.2018", "val": 0.4, "name": "Оксид углерода"}], "primsSS": [{"dt": "2018-07-08_00:00", "vals": [0, 0, 0.015, 0, 0, null, null, null, null, null, null, null, null]}, {"dt": "2018-07-09_00:00", "vals": [0, 0, 0.013, 0, 0, null, null, null, null, null, null, null, null]}, {"dt": "2018-07-10_00:00", "vals": [0, 0, 0.024, 0, 0, null, null, null, null, null, null, null, null]}, {"dt": "2018-07-11_00:00", "vals": [0.013, 0.2, 0.047, 0.004, 0, null, null, null, null, null, null, null, null]}, {"dt": "2018-07-12_00:00", "vals": [0.005, 0, 0.05, 0, 0, null, null, null, null, null, null, null, null]}, {"dt": "2018-07-13_00:00", "vals": [0.01, 0, 0.03, 0, 0, null, null, null, null, null, null, null, null]}, {"dt": "2018-07-14_00:00", "vals": [0.035, 0.5, 0.053, 0, 0, null, null, null, null, null, null, null, null]}], "mpcAD": [{"name": "Диоксид серы", "val": 0.05}, {"name": "Оксид углерода", "val": 3}, {"name": "Диоксид азота", "val": 0.1}, {"name": "Оксид азота", "val": null}, {"name": "Сероводород", "val": null}, {"name": "Фенол", "val": 0.006}, {"name": "Бензол", "val": 0.06}, {"name": "Стирол", "val": null}, {"name": "Толуол", "val": null}, {"name": "Хлорбензол", "val": null}, {"name": "Этилбензол", "val": null}, {"name": "МП-ксилол", "val": 0.04}, {"name": "О-ксилол", "val": null}], "ispel": 0}, {"ind": "24050204", "name": "Ачинск(ТСН)", "nom": "4", "place": "ЮВ район, д.14", "label": "Ачинск(ТСН), №4, ЮВ район, д.14", "lng": "90.499444", "lat": "56.252333", "date": "14.07.2018", "si": [{"name": "Диоксид серы", "val": 0}, {"name": "Оксид углерода", "val": 0}, {"name": "Диоксид азота", "val": 0}, {"name": "Оксид азота", "val": 0}, {"name": "Сероводород", "val": 0}, {"name": "Фенол", "val": -32768}, {"name": "Аммиак", "val": 0}, {"name": "Бензол", "val": -32768}, {"name": "Стирол", "val": -32768}, {"name": "Толуол", "val": -32768}, {"name": "Хлорбензол", "val": -32768}, {"name": "Этилбензол", "val": -32768}, {"name": "Частицы 10 мкм", "val": 0.3}, {"name": "Частицы 2.5 мкм", "val": -32768}, {"name": "МП-ксилол", "val": -32768}, {"name": "О-ксилол", "val": -32768}], "maxSi": 0.3, "meteoParamsNames": ["\"Температура\"", "\"Скорость ветра\"", "\"Влажность отн.\"", "\"Давление\"", "\"Направление ветра\""], "meteoParamsValues": [{"dt": "2018-07-08_01:00", "vals": [12, 0, 79, 742, 0]}, {"dt": "2018-07-08_07:00", "vals": [13, 0, 75, 742, 0]}, {"dt": "2018-07-08_13:00", "vals": [19, 2, 49, 742, 48]}, {"dt": "2018-07-08_19:00", "vals": [19, 2, 48, 742, 46]}, {"dt": "2018-07-09_01:00", "vals": [11, 0, 78, 742, 0]}, {"dt": "2018-07-09_07:00", "vals": [15, 0, 69, 742, 0]}, {"dt": "2018-07-09_13:00", "vals": [22, 2, 48, 741, 56]}, {"dt": "2018-07-09_19:00", "vals": [23, 1, 44, 740, 43]}, {"dt": "2018-07-10_01:00", "vals": [12, 0, 77, 740, 0]}, {"dt": "2018-07-10_07:00", "vals": [15, 0, 71, 740, 0]}, {"dt": "2018-07-10_13:00", "vals": [25, 2, 40, 738, 27]}, {"dt": "2018-07-10_19:00", "vals": [25, 2, 40, 737, 40]}, {"dt": "2018-07-11_01:00", "vals": [14, 0, 73, 736, 0]}, {"dt": "2018-07-11_07:00", "vals": [13, 0, 78, 736, 0]}, {"dt": "2018-07-11_13:00", "vals": [26, 0, 48, 735, 0]}, {"dt": "2018-07-11_19:00", "vals": [27, 1, 46, 733, 12]}, {"dt": "2018-07-12_01:00", "vals": [16, 0, 78, 733, 0]}, {"dt": "2018-07-12_07:00", "vals": [17, 0, 77, 733, 0]}, {"dt": "2018-07-12_13:00", "vals": [28, 1, 42, 732, 20]}, {"dt": "2018-07-12_19:00", "vals": [29, 2, 50, 731, 43]}, {"dt": "2018-07-13_01:00", "vals": [21, 0, 72, 731, 0]}, {"dt": "2018-07-13_07:00", "vals": [21, 0, 72, 731, 0]}, {"dt": "2018-07-13_13:00", "vals": [29, 2, 41, 730, 52]}, {"dt": "2018-07-13_19:00", "vals": [29, 1, 43, 729, 46]}, {"dt": "2018-07-14_01:00", "vals": [19, 0, 75, 729, 0]}, {"dt": "2018-07-14_07:00", "vals": [19, 0, 76, 729, 0]}, {"dt": "2018-07-14_13:00", "vals": [22, 0, 76, 730, 0]}, {"dt": "2018-07-14_19:00", "vals": [26, 1, 57, 731, 125]}], "siRange": "08.07.2018 - 14.07.2018", "meteoRange": "08.07.2018 - 14.07.2018", "maxSiWeek": [{"dt": "08.07.2018", "val": 0, "name": "Диоксид серы"}, {"dt": "09.07.2018", "val": 0.1, "name": "Оксид азота"}, {"dt": "10.07.2018", "val": 0.4, "name": "Частицы 10 мкм"}, {"dt": "11.07.2018", "val": 0.2, "name": "Частицы 10 мкм"}, {"dt": "12.07.2018", "val": 0.2, "name": "Диоксид азота"}, {"dt": "13.07.2018", "val": 0.1, "name": "Диоксид азота"}, {"dt": "14.07.2018", "val": 0.3, "name": "Частицы 10 мкм"}], "primsSS": [{"dt": "2018-07-08_00:00", "vals": [0, 0, 0, 0.005, 0, null, 0, null, null, null, null, null, 0, null, null, null]}, {"dt": "2018-07-09_00:00", "vals": [0.002, 0, 0, 0.014, 0, null, 0, null, null, null, null, null, 0, null, null, null]}, {"dt": "2018-07-10_00:00", "vals": [0, 0, 0.008, 0.011, 0, null, 0, null, null, null, null, null, 0.032, null, null, null]}, {"dt": "2018-07-11_00:00", "vals": [0, 0, 0.007, 0, 0, null, 0, null, null, null, null, null, 0.015, null, null, null]}, {"dt": "2018-07-12_00:00", "vals": [0.007, 0, 0.01, 0.012, 0, null, 0, null, null, null, null, null, 0.017, null, null, null]}, {"dt": "2018-07-13_00:00", "vals": [0, 0, 0.005, 0, 0, null, 0, null, null, null, null, null, 0, null, null, null]}, {"dt": "2018-07-14_00:00", "vals": [0, 0, 0.002, 0, 0, null, 0, null, null, null, null, null, 0.031, null, null, null]}], "mpcAD": [{"name": "Диоксид серы", "val": 0.05}, {"name": "Оксид углерода", "val": 3}, {"name": "Диоксид азота", "val": 0.1}, {"name": "Оксид азота", "val": null}, {"name": "Сероводород", "val": null}, {"name": "Фенол", "val": 0.006}, {"name": "Аммиак", "val": 0.1}, {"name": "Бензол", "val": 0.06}, {"name": "Стирол", "val": null}, {"name": "Толуол", "val": null}, {"name": "Хлорбензол", "val": null}, {"name": "Этилбензол", "val": null}, {"name": "Частицы 10 мкм", "val": 0.06}, {"name": "Частицы 2.5 мкм", "val": 0.035}, {"name": "МП-ксилол", "val": 0.04}, {"name": "О-ксилол", "val": null}], "ispel": 0}, {"ind": "24050205", "name": "Красноярск(ТСН)", "nom": "5", "place": "д.Кубеково,ул.Новая, д.6", "label": "Красноярск(ТСН), №5, д.Кубеково,ул.Новая, д.6", "lng": "93.113667", "lat": "56.143472", "date": "14.07.2018", "si": [{"name": "Диоксид серы", "val": 0}, {"name": "Оксид углерода", "val": 0}, {"name": "Диоксид азота", "val": 0}, {"name": "Оксид азота", "val": 0}, {"name": "Частицы 2.5 мкм", "val": -32768}], "maxSi": 0, "meteoParamsNames": ["\"Температура\"", "\"Скорость ветра\"", "\"Влажность отн.\"", "\"Давление\"", "\"Направление ветра\""], "meteoParamsValues": [{"dt": "2018-07-08_01:00", "vals": [10, 0, 87, 752, 0]}, {"dt": "2018-07-08_07:00", "vals": [12, 0, 87, 753, 0]}, {"dt": "2018-07-08_13:00", "vals": [19, 2, 53, 752, 326]}, {"dt": "2018-07-08_19:00", "vals": [17, 2, 68, 752, 270]}, {"dt": "2018-07-09_01:00", "vals": [10, 0, 88, 752, 0]}, {"dt": "2018-07-09_07:00", "vals": [10, 0, 91, 752, 0]}, {"dt": "2018-07-09_13:00", "vals": [23, 2, 48, 751, 297]}, {"dt": "2018-07-09_19:00", "vals": [23, 1, 43, 750, 207]}, {"dt": "2018-07-10_01:00", "vals": [14, 1, 72, 749, 200]}, {"dt": "2018-07-10_07:00", "vals": [15, 0, 81, 749, 0]}, {"dt": "2018-07-10_19:00", "vals": [23, 2, 50, 745, 121]}, {"dt": "2018-07-11_01:00", "vals": [17, 0, 80, 745, 0]}, {"dt": "2018-07-11_07:00", "vals": [16, 0, 81, 745, 0]}, {"dt": "2018-07-11_13:00", "vals": [24, 0, 57, 744, 0]}, {"dt": "2018-07-11_19:00", "vals": [25, 0, 55, 743, 0]}, {"dt": "2018-07-12_01:00", "vals": [16, 0, 82, 742, 0]}, {"dt": "2018-07-12_07:00", "vals": [16, 0, 83, 742, 0]}, {"dt": "2018-07-12_13:00", "vals": [28, 0, 50, 741, 52]}, {"dt": "2018-07-12_19:00", "vals": [27, 0, 53, 740, 0]}, {"dt": "2018-07-13_01:00", "vals": [17, 0, 81, 741, 0]}, {"dt": "2018-07-13_07:00", "vals": [18, 0, 82, 741, 0]}, {"dt": "2018-07-13_13:00", "vals": [27, 1, 57, 740, 123]}, {"dt": "2018-07-13_19:00", "vals": [28, 0, 54, 739, 0]}, {"dt": "2018-07-14_01:00", "vals": [17, 0, 82, 739, 0]}, {"dt": "2018-07-14_07:00", "vals": [17, 0, 83, 739, 0]}, {"dt": "2018-07-14_13:00", "vals": [28, 1, 47, 739, 28]}, {"dt": "2018-07-14_19:00", "vals": [26, 0, 62, 739, 0]}], "siRange": "08.07.2018 - 14.07.2018", "meteoRange": "08.07.2018 - 14.07.2018", "maxSiWeek": [{"dt": "08.07.2018", "val": 0, "name": "Диоксид серы"}, {"dt": "09.07.2018", "val": 0, "name": "Диоксид серы"}, {"dt": "10.07.2018", "val": 0, "name": "Диоксид серы"}, {"dt": "11.07.2018", "val": 0, "name": "Диоксид серы"}, {"dt": "12.07.2018", "val": 0, "name": "Диоксид серы"}, {"dt": "13.07.2018", "val": 0, "name": "Диоксид серы"}, {"dt": "14.07.2018", "val": 0, "name": "Диоксид серы"}], "primsSS": [{"dt": "2018-07-08_00:00", "vals": [0, 0, 0, 0, null]}, {"dt": "2018-07-09_00:00", "vals": [0, 0, 0, 0, null]}, {"dt": "2018-07-10_00:00", "vals": [0, 0, 0, 0, null]}, {"dt": "2018-07-11_00:00", "vals": [0, 0, 0, 0, null]}, {"dt": "2018-07-12_00:00", "vals": [0.003, 0, 0, 0, null]}, {"dt": "2018-07-13_00:00", "vals": [0, 0, 0, 0, null]}, {"dt": "2018-07-14_00:00", "vals": [0.006, 0, 0, 0, null]}], "mpcAD": [{"name": "Диоксид серы", "val": 0.05}, {"name": "Оксид углерода", "val": 3}, {"name": "Диоксид азота", "val": 0.1}, {"name": "Оксид азота", "val": null}, {"name": "Частицы 2.5 мкм", "val": 0.035}], "ispel": 0}, {"ind": "24050206", "name": "Красноярск(ТСН)", "nom": "6", "place": "д.Березовка,ул.Береговая, д.40", "label": "Красноярск(ТСН), №6, д.Березовка,ул.Береговая, д.40", "lng": "93.137306", "lat": "56.04675", "date": "14.07.2018", "si": [{"name": "Диоксид серы", "val": 0}, {"name": "Оксид углерода", "val": 0.2}, {"name": "Диоксид азота", "val": 0.2}, {"name": "Оксид азота", "val": 0}, {"name": "Частицы 2.5 мкм", "val": -32768}], "maxSi": 0.2, "meteoParamsNames": ["\"Температура\"", "\"Скорость ветра\"", "\"Влажность отн.\"", "\"Давление\"", "\"Направление ветра\""], "meteoParamsValues": [{"dt": "2018-07-08_01:00", "vals": [12, 0, 84, 749, 0]}, {"dt": "2018-07-08_07:00", "vals": [13, 0, 82, 750, 0]}, {"dt": "2018-07-08_13:00", "vals": [18, 2, 59, 749, 13]}, {"dt": "2018-07-08_19:00", "vals": [18, 0, 62, 749, 0]}, {"dt": "2018-07-09_01:00", "vals": [12, 0, 85, 749, 0]}, {"dt": "2018-07-09_07:00", "vals": [11, 0, 87, 750, 60]}, {"dt": "2018-07-09_13:00", "vals": [22, 0, 56, 748, 0]}, {"dt": "2018-07-09_19:00", "vals": [23, 0, 45, 747, 0]}, {"dt": "2018-07-10_01:00", "vals": [14, 1, 75, 747, 97]}, {"dt": "2018-07-10_07:00", "vals": [16, 1, 68, 746, 68]}, {"dt": "2018-07-10_13:00", "vals": [24, 1, 48, 745, 128]}, {"dt": "2018-07-10_19:00", "vals": [24, 2, 51, 744, 60]}, {"dt": "2018-07-11_01:00", "vals": [17, 0, 80, 744, 0]}, {"dt": "2018-07-11_07:00", "vals": [16, 0, 84, 744, 0]}, {"dt": "2018-07-11_13:00", "vals": [23, 0, 65, 743, 9]}, {"dt": "2018-07-11_19:00", "vals": [26, 0, 55, 742, 0]}, {"dt": "2018-07-12_01:00", "vals": [18, 0, 83, 741, 0]}, {"dt": "2018-07-12_07:00", "vals": [18, 0, 83, 741, 59]}, {"dt": "2018-07-12_13:00", "vals": [28, 0, 52, 740, 12]}, {"dt": "2018-07-12_19:00", "vals": [28, 1, 53, 739, 117]}, {"dt": "2018-07-13_01:00", "vals": [19, 0, 84, 740, 0]}, {"dt": "2018-07-13_07:00", "vals": [18, 0, 85, 740, 0]}, {"dt": "2018-07-13_13:00", "vals": [27, 0, 59, 739, 8]}, {"dt": "2018-07-13_19:00", "vals": [28, 0, 53, 738, 0]}, {"dt": "2018-07-14_01:00", "vals": [19, 0, 82, 738, 0]}, {"dt": "2018-07-14_07:00", "vals": [null, null, null, null, null]}, {"dt": "2018-07-14_13:00", "vals": [null, null, null, null, null]}, {"dt": "2018-07-14_19:00", "vals": [null, null, null, null, null]}], "siRange": "08.07.2018 - 14.07.2018", "meteoRange": "08.07.2018 - 14.07.2018", "maxSiWeek": [{"dt": "08.07.2018", "val": 0.3, "name": "Диоксид азота"}, {"dt": "09.07.2018", "val": 0.3, "name": "Диоксид азота"}, {"dt": "10.07.2018", "val": 0.3, "name": "Диоксид азота"}, {"dt": "11.07.2018", "val": 0.3, "name": "Диоксид азота"}, {"dt": "12.07.2018", "val": 0.2, "name": "Диоксид азота"}, {"dt": "13.07.2018", "val": 0.3, "name": "Диоксид азота"}, {"dt": "14.07.2018", "val": 0.2, "name": "Оксид углерода"}], "primsSS": [{"dt": "2018-07-08_00:00", "vals": [0, 0.4, 0.037, 0.01, null]}, {"dt": "2018-07-09_00:00", "vals": [0, 0, 0.028, 0.004, null]}, {"dt": "2018-07-10_00:00", "vals": [0, 0, 0.051, 0, null]}, {"dt": "2018-07-11_00:00", "vals": [0, 0.2, 0.04, 0.013, null]}, {"dt": "2018-07-12_00:00", "vals": [0, 0.1, 0.023, 0, null]}, {"dt": "2018-07-13_00:00", "vals": [0, 0.4, 0.039, 0.012, null]}, {"dt": "2018-07-14_00:00", "vals": [0, 0.4, 0.013, 0, null]}], "mpcAD": [{"name": "Диоксид серы", "val": 0.05}, {"name": "Оксид углерода", "val": 3}, {"name": "Диоксид азота", "val": 0.1}, {"name": "Оксид азота", "val": null}, {"name": "Частицы 2.5 мкм", "val": 0.035}], "ispel": 0}]}]}