{"status": 1, "date": "21.09.2019", "data": [{"type": 0, "stations": [{"ind": "3020103", "name": "Селенгинск", "nom": "1", "place": "Южный мкр.", "label": "Селенгинск, №1, Южный мкр.", "lng": "106.86742", "lat": "52.00384", "date": "21.09.2019", "si": [{"name": "Взвешенные в-ва", "val": -32768}, {"name": "Диоксид серы", "val": 0}, {"name": "Оксид углерода", "val": 0.3}, {"name": "Диоксид азота", "val": 0.2}, {"name": "Оксид азота", "val": 0}, {"name": "Озон", "val": 0.4}, {"name": "Сероводород", "val": 0.2}, {"name": "Фенол", "val": -32768}, {"name": "Формальдегид", "val": -32768}, {"name": "Частицы 10 мкм (сут.)", "val": -32768}], "maxSi": 0.4, "meteoParamsNames": ["\"Температура\"", "\"Скорость ветра\"", "\"Влажность отн.\"", "\"Давление\"", "\"Направление ветра\""], "meteoParamsValues": [{"dt": "2019-09-15_01:00", "vals": [1, 1, 70, 724, 191]}, {"dt": "2019-09-15_07:00", "vals": [-1, 1, 82, 723, 8]}, {"dt": "2019-09-15_13:00", "vals": [11, 2, 42, 720, 159]}, {"dt": "2019-09-15_19:00", "vals": [10, 1, 69, 719, 202]}, {"dt": "2019-09-16_01:00", "vals": [6, 1, 89, 718, 204]}, {"dt": "2019-09-16_07:00", "vals": [4, 0, 94, 718, 10]}, {"dt": "2019-09-16_13:00", "vals": [13, 1, 61, 719, 284]}, {"dt": "2019-09-16_19:00", "vals": [9, 1, 59, 722, 245]}, {"dt": "2019-09-17_01:00", "vals": [3, 1, 83, 726, 210]}, {"dt": "2019-09-17_07:00", "vals": [1, 1, 85, 728, 139]}, {"dt": "2019-09-17_13:00", "vals": [12, 1, 40, 728, 118]}, {"dt": "2019-09-17_19:00", "vals": [9, 1, 66, 726, 215]}, {"dt": "2019-09-18_01:00", "vals": [1, 1, 90, 725, 207]}, {"dt": "2019-09-18_07:00", "vals": [1, 1, 91, 723, 208]}, {"dt": "2019-09-18_13:00", "vals": [14, 1, 57, 723, 336]}, {"dt": "2019-09-18_19:00", "vals": [11, 1, 79, 722, 210]}, {"dt": "2019-09-19_01:00", "vals": [4, 0, 91, 723, 144]}, {"dt": "2019-09-19_07:00", "vals": [6, 1, 94, 724, 214]}, {"dt": "2019-09-19_13:00", "vals": [14, 1, 75, 725, 269]}, {"dt": "2019-09-19_19:00", "vals": [11, 1, 83, 725, 206]}, {"dt": "2019-09-20_01:00", "vals": [4, 1, 94, 726, 235]}, {"dt": "2019-09-20_07:00", "vals": [2, 1, 96, 726, 14]}, {"dt": "2019-09-20_13:00", "vals": [19, 2, 43, 725, 123]}, {"dt": "2019-09-20_19:00", "vals": [14, 1, 69, 723, 137]}, {"dt": "2019-09-21_01:00", "vals": [9, 1, 83, 723, 350]}, {"dt": "2019-09-21_07:00", "vals": [6, 1, 91, 722, 174]}, {"dt": "2019-09-21_13:00", "vals": [22, 1, 41, 722, 163]}, {"dt": "2019-09-21_19:00", "vals": [16, 1, 78, 721, 62]}], "siRange": "15.09.2019 - 21.09.2019", "meteoRange": "15.09.2019 - 21.09.2019", "maxSiWeek": [{"dt": "15.09.2019", "val": 0.3, "name": "Сероводород"}, {"dt": "16.09.2019", "val": 0.3, "name": "Озон"}, {"dt": "17.09.2019", "val": 0.3, "name": "Озон"}, {"dt": "18.09.2019", "val": 0.2, "name": "Оксид углерода"}, {"dt": "19.09.2019", "val": 0.3, "name": "Озон"}, {"dt": "20.09.2019", "val": 0.3, "name": "Озон"}, {"dt": "21.09.2019", "val": 0.4, "name": "Озон"}], "primsSS": [{"dt": "2019-09-15_00:00", "vals": [null, 0.009, 0.4, 0.013, 0.006, 0.026, 0.002, null, null, null]}, {"dt": "2019-09-16_00:00", "vals": [null, 0.001, 0.4, 0.011, 0.012, 0.027, 0.002, null, null, null]}, {"dt": "2019-09-17_00:00", "vals": [null, 0.002, 0.5, 0.013, 0.007, 0.027, 0, null, null, null]}, {"dt": "2019-09-18_00:00", "vals": [null, 0.003, 0.5, 0.016, 0.008, 0.014, 0.001, null, null, null]}, {"dt": "2019-09-19_00:00", "vals": [null, 0.001, 0.5, 0.014, 0.005, 0.018, 0, null, null, null]}, {"dt": "2019-09-20_00:00", "vals": [null, 0.001, 0.7, 0.018, 0.014, 0.021, 0, null, null, null]}, {"dt": "2019-09-21_00:00", "vals": [null, 0.007, 0.8, 0.02, 0.009, 0.027, 0.001, null, null, null]}], "mpcAD": [{"name": "Взвешенные в-ва", "val": 0.15}, {"name": "Диоксид серы", "val": 0.05}, {"name": "Оксид углерода", "val": 3}, {"name": "Диоксид азота", "val": 0.1}, {"name": "Оксид азота", "val": null}, {"name": "Озон", "val": 0.1}, {"name": "Сероводород", "val": null}, {"name": "Фенол", "val": 0.006}, {"name": "Формальдегид", "val": 0.01}, {"name": "Частицы 10 мкм (сут.)", "val": 0.06}], "ispel": 0}, {"ind": "38020112", "name": "Свирск", "nom": "1", "place": "ул.Ангарская, д.2", "label": "Свирск, ул.Ангарская, д.2", "lng": "103.343486", "lat": "53.083278", "date": "21.09.2019", "si": [{"name": "Взвешенные в-ва", "val": -32768}, {"name": "Диоксид серы", "val": 0}, {"name": "Оксид углерода", "val": 0}, {"name": "Диоксид азота", "val": 0.3}, {"name": "Оксид азота", "val": 0}, {"name": "Сероводород", "val": 0}, {"name": "Формальдегид", "val": -32768}], "maxSi": 0.3, "meteoParamsNames": ["\"Температура\"", "\"Скорость ветра\"", "\"Влажность отн.\"", "\"Давление\"", "\"Направление ветра\""], "meteoParamsValues": [{"dt": "2019-09-15_13:00", "vals": [null, 3, 50, 725, 158]}, {"dt": "2019-09-15_19:00", "vals": [null, 1, 73, 724, 39]}, {"dt": "2019-09-16_01:00", "vals": [null, 0, 99, 724, null]}, {"dt": "2019-09-16_07:00", "vals": [null, 1, 93, 724, 178]}, {"dt": "2019-09-16_13:00", "vals": [null, 3, 72, 727, 329]}, {"dt": "2019-09-16_19:00", "vals": [null, 2, 62, 729, 305]}, {"dt": "2019-09-17_01:00", "vals": [null, 0, 97, 732, null]}, {"dt": "2019-09-17_07:00", "vals": [null, 0, 99, 733, 180]}, {"dt": "2019-09-17_13:00", "vals": [null, 2, 53, 732, 159]}, {"dt": "2019-09-17_19:00", "vals": [null, 0, 67, 729, 196]}, {"dt": "2019-09-18_01:00", "vals": [null, 0, 99, 729, null]}, {"dt": "2019-09-18_07:00", "vals": [null, 0, 98, 728, null]}, {"dt": "2019-09-18_13:00", "vals": [null, 1, 57, 728, 119]}, {"dt": "2019-09-18_19:00", "vals": [null, 0, 98, 727, null]}, {"dt": "2019-09-19_07:00", "vals": [null, 0, 99, 731, null]}, {"dt": "2019-09-19_13:00", "vals": [null, 1, 58, 730, 113]}, {"dt": "2019-09-19_19:00", "vals": [null, 0, 80, 730, null]}, {"dt": "2019-09-20_01:00", "vals": [null, 0, 99, 731, null]}, {"dt": "2019-09-20_07:00", "vals": [null, 0, 99, 730, null]}, {"dt": "2019-09-20_13:00", "vals": [null, 2, 50, 728, 182]}, {"dt": "2019-09-21_13:00", "vals": [null, 1, 50, 726, 119]}], "siRange": "15.09.2019 - 21.09.2019", "meteoRange": "15.09.2019 - 21.09.2019", "maxSiWeek": [{"dt": "15.09.2019", "val": 0.1, "name": "Диоксид серы"}, {"dt": "16.09.2019", "val": 0.2, "name": "Диоксид азота"}, {"dt": "17.09.2019", "val": 0.8, "name": "Диоксид азота"}, {"dt": "18.09.2019", "val": 0.5, "name": "Диоксид азота"}, {"dt": "19.09.2019", "val": 0.6, "name": "Диоксид азота"}, {"dt": "20.09.2019", "val": 0.3, "name": "Диоксид азота"}, {"dt": "21.09.2019", "val": 0.3, "name": "Диоксид азота"}], "primsSS": [{"dt": "2019-09-15_00:00", "vals": [null, 0.019, 0.1, 0.022, 0.006, 0.001, null]}, {"dt": "2019-09-16_00:00", "vals": [null, 0.004, 0.3, 0.028, 0.007, 0.001, null]}, {"dt": "2019-09-17_00:00", "vals": [null, 0.006, 0.4, 0.067, 0.027, 0.001, null]}, {"dt": "2019-09-18_00:00", "vals": [null, 0.001, 0.5, 0.066, 0.027, 0, null]}, {"dt": "2019-09-19_00:00", "vals": [null, 0, 0.7, 0.066, 0.029, 0, null]}, {"dt": "2019-09-20_00:00", "vals": [null, 0.013, 0.3, 0.046, 0.015, 0, null]}, {"dt": "2019-09-21_00:00", "vals": [null, 0.015, 0.2, 0.054, 0.013, 0, null]}], "mpcAD": [{"name": "Взвешенные в-ва", "val": 0.15}, {"name": "Диоксид серы", "val": 0.05}, {"name": "Оксид углерода", "val": 3}, {"name": "Диоксид азота", "val": 0.1}, {"name": "Оксид азота", "val": null}, {"name": "Сероводород", "val": null}, {"name": "Формальдегид", "val": 0.01}], "ispel": 0}, {"ind": "40010301", "name": "Обнинск", "nom": "1", "place": "Метеомачта", "label": "Обнинск, №1, Метеомачта", "lng": "36.598", "lat": "55.111", "date": "21.09.2019", "si": [{"name": "Диоксид серы", "val": 0}, {"name": "Оксид углерода", "val": 0}, {"name": "Диоксид азота", "val": 0}, {"name": "Оксид азота", "val": 0}, {"name": "Сероводород", "val": 0.3}, {"name": "Сумма углеводородов", "val": 0}, {"name": "Аммиак", "val": 0}, {"name": "Бензол", "val": -32768}, {"name": "Толуол", "val": -32768}, {"name": "Этилбензол", "val": -32768}, {"name": "Метан", "val": -32768}, {"name": "МП-ксилол", "val": -32768}, {"name": "О-ксилол", "val": -32768}, {"name": "Частицы 2.5 мкм (сут.)", "val": -32768}], "maxSi": 0.3, "meteoParamsNames": ["\"Температура\"", "\"Скорость ветра\"", "\"Влажность отн.\"", "\"Давление\"", "\"Направление ветра\""], "meteoParamsValues": [{"dt": "2019-09-15_01:00", "vals": [8, 1, 79, 746, 249]}, {"dt": "2019-09-15_07:00", "vals": [7, 2, 92, 747, 229]}, {"dt": "2019-09-15_13:00", "vals": [13, 3, 50, 746, 248]}, {"dt": "2019-09-15_19:00", "vals": [10, 2, 82, 741, 220]}, {"dt": "2019-09-16_01:00", "vals": [10, 3, 85, 736, 220]}, {"dt": "2019-09-16_07:00", "vals": [10, 3, 93, 734, 228]}, {"dt": "2019-09-16_13:00", "vals": [14, 3, 66, 733, 239]}, {"dt": "2019-09-16_19:00", "vals": [11, 2, 82, 734, 221]}, {"dt": "2019-09-17_01:00", "vals": [9, 2, 89, 733, 225]}, {"dt": "2019-09-17_07:00", "vals": [9, 3, 87, 732, 231]}, {"dt": "2019-09-17_13:00", "vals": [11, 3, 71, 733, 252]}, {"dt": "2019-09-17_19:00", "vals": [10, 2, 70, 733, 230]}, {"dt": "2019-09-18_01:00", "vals": [8, 1, 90, 733, 216]}, {"dt": "2019-09-18_07:00", "vals": [6, 2, 95, 733, 228]}, {"dt": "2019-09-18_13:00", "vals": [11, 1, 74, 732, 114]}, {"dt": "2019-09-18_19:00", "vals": [7, 0, 97, 733, null]}, {"dt": "2019-09-19_01:00", "vals": [6, 1, 97, 735, 276]}, {"dt": "2019-09-19_07:00", "vals": [7, 2, 97, 738, 267]}, {"dt": "2019-09-19_13:00", "vals": [11, 3, 73, 741, 234]}, {"dt": "2019-09-19_19:00", "vals": [8, 1, 70, 743, 310]}, {"dt": "2019-09-20_01:00", "vals": [4, 0, 97, 743, null]}, {"dt": "2019-09-20_07:00", "vals": [4, 0, 99, 743, 57]}, {"dt": "2019-09-20_13:00", "vals": [8, 1, 86, 743, 104]}, {"dt": "2019-09-20_19:00", "vals": [6, 1, 86, 744, 284]}, {"dt": "2019-09-21_01:00", "vals": [5, 1, 93, 744, 346]}, {"dt": "2019-09-21_07:00", "vals": [2, 1, 99, 745, 291]}, {"dt": "2019-09-21_13:00", "vals": [9, 2, 51, 744, 263]}, {"dt": "2019-09-21_19:00", "vals": [6, 2, 73, 742, 225]}], "siRange": "15.09.2019 - 21.09.2019", "meteoRange": "15.09.2019 - 21.09.2019", "maxSiWeek": [{"dt": "15.09.2019", "val": 0.2, "name": "Сероводород"}, {"dt": "16.09.2019", "val": 0.2, "name": "Сероводород"}, {"dt": "17.09.2019", "val": 0.4, "name": "Сероводород"}, {"dt": "18.09.2019", "val": 0.3, "name": "Сероводород"}, {"dt": "19.09.2019", "val": 0.3, "name": "Сероводород"}, {"dt": "20.09.2019", "val": 0.2, "name": "Сероводород"}, {"dt": "21.09.2019", "val": 0.3, "name": "Сероводород"}], "primsSS": [{"dt": "2019-09-15_00:00", "vals": [0.003, 0, 0.009, 0, 0.001, 1.4, 0.01, null, null, null, 1.33, null, null, null]}, {"dt": "2019-09-16_00:00", "vals": [0.001, 0.1, 0.005, 0, 0.001, 1.4, 0.01, null, null, null, 1.327, null, null, null]}, {"dt": "2019-09-17_00:00", "vals": [0, 0, 0.004, 0, 0.003, 1.4, 0.01, null, null, null, 1.328, null, null, null]}, {"dt": "2019-09-18_00:00", "vals": [0, 0.1, 0.007, 0, 0.002, 1.4, 0.01, null, null, null, 1.358, null, null, null]}, {"dt": "2019-09-19_00:00", "vals": [0, 0, 0.006, 0, 0.002, 1.4, 0.01, null, null, null, 1.387, null, null, null]}, {"dt": "2019-09-20_00:00", "vals": [0.001, 0, 0.01, 0, 0.001, 1.6, 0.01, null, null, null, 1.506, null, null, null]}, {"dt": "2019-09-21_00:00", "vals": [0, 0, 0.006, 0, 0.002, 1.4, 0.01, null, null, null, 1.365, null, null, null]}], "mpcAD": [{"name": "Диоксид серы", "val": 0.05}, {"name": "Оксид углерода", "val": 3}, {"name": "Диоксид азота", "val": 0.1}, {"name": "Оксид азота", "val": null}, {"name": "Сероводород", "val": null}, {"name": "Сумма углеводородов", "val": 5}, {"name": "Аммиак", "val": 0.1}, {"name": "Бензол", "val": 0.06}, {"name": "Толуол", "val": null}, {"name": "Этилбензол", "val": null}, {"name": "Метан", "val": null}, {"name": "МП-ксилол", "val": 0.04}, {"name": "О-ксилол", "val": null}, {"name": "Частицы 2.5 мкм (сут.)", "val": 0.035}], "ispel": 0}, {"ind": "75020103", "name": "Петровск-Забайкальский", "nom": "1", "place": "ул.Маяковского, д.25а, МС", "label": "Петровск-Забайкальский, №1, ул.Маяковского, д.25а, МС", "lng": "108.870057", "lat": "51.312577", "date": "21.09.2019", "si": [{"name": "Взвешенные в-ва", "val": -32768}, {"name": "Диоксид серы", "val": 0}, {"name": "Оксид углерода", "val": 0}, {"name": "Диоксид азота", "val": 0}, {"name": "Оксид азота", "val": 0}, {"name": "Сероводород", "val": 0.3}, {"name": "Аммиак", "val": 0}], "maxSi": 0.3, "meteoParamsNames": ["\"Температура\"", "\"Скорость ветра\"", "\"Влажность отн.\"", "\"Давление\"", "\"Направление ветра\""], "meteoParamsValues": [{"dt": "2019-09-15_01:00", "vals": [3, 2, 47, 693, 300]}, {"dt": "2019-09-15_07:00", "vals": [-5, 1, 75, 695, 173]}, {"dt": "2019-09-15_13:00", "vals": [8, 4, 43, 693, 243]}, {"dt": "2019-09-15_19:00", "vals": [9, 2, 49, 692, 214]}, {"dt": "2019-09-16_01:00", "vals": [3, 0, 86, 691, 311]}, {"dt": "2019-09-16_07:00", "vals": [0, 0, 95, 690, 28]}, {"dt": "2019-09-16_13:00", "vals": [12, 3, 53, 690, 259]}, {"dt": "2019-09-16_19:00", "vals": [9, 1, 72, 691, 237]}, {"dt": "2019-09-17_01:00", "vals": [1, 1, 92, 696, 230]}, {"dt": "2019-09-17_07:00", "vals": [-1, 2, 79, 699, 241]}, {"dt": "2019-09-17_19:00", "vals": [10, 1, 45, 698, 278]}, {"dt": "2019-09-18_01:00", "vals": [-2, 0, 90, 699, 39]}, {"dt": "2019-09-18_07:00", "vals": [-5, 0, 94, 697, null]}, {"dt": "2019-09-18_13:00", "vals": [16, 1, 42, 695, 165]}, {"dt": "2019-09-18_19:00", "vals": [15, 1, 47, 694, 267]}, {"dt": "2019-09-19_01:00", "vals": [1, 1, 94, 695, 21]}, {"dt": "2019-09-19_07:00", "vals": [-3, 0, 97, 696, null]}, {"dt": "2019-09-19_13:00", "vals": [13, 2, 61, 696, 225]}, {"dt": "2019-09-19_19:00", "vals": [13, 1, 54, 696, 246]}, {"dt": "2019-09-20_13:00", "vals": [16, 2, 42, 698, 204]}, {"dt": "2019-09-20_19:00", "vals": [13, 1, 46, 697, 276]}, {"dt": "2019-09-21_01:00", "vals": [1, 0, 90, 698, 14]}, {"dt": "2019-09-21_07:00", "vals": [-4, 0, 95, 697, null]}, {"dt": "2019-09-21_13:00", "vals": [20, 2, 37, 696, 195]}, {"dt": "2019-09-21_19:00", "vals": [20, 2, 39, 694, 265]}], "siRange": "15.09.2019 - 21.09.2019", "meteoRange": "15.09.2019 - 21.09.2019", "maxSiWeek": [{"dt": "15.09.2019", "val": 0.1, "name": "Диоксид азота"}, {"dt": "16.09.2019", "val": 0.2, "name": "Сероводород"}, {"dt": "17.09.2019", "val": 0.1, "name": "Диоксид азота"}, {"dt": "18.09.2019", "val": 0.1, "name": "Сероводород"}, {"dt": "19.09.2019", "val": 0.1, "name": "Диоксид азота"}, {"dt": "20.09.2019", "val": 0, "name": "Диоксид серы"}, {"dt": "21.09.2019", "val": 0.3, "name": "Сероводород"}], "primsSS": [{"dt": "2019-09-15_00:00", "vals": [null, 0.002, 0.1, 0.006, 0, 0, 0]}, {"dt": "2019-09-16_00:00", "vals": [null, 0.005, 0.2, 0.004, 0, 0.001, 0]}, {"dt": "2019-09-17_00:00", "vals": [null, 0.001, 0.1, 0.009, 0, 0.001, 0]}, {"dt": "2019-09-18_00:00", "vals": [null, 0.008, 0.2, 0.002, 0, 0, 0]}, {"dt": "2019-09-19_00:00", "vals": [null, 0.003, 0.1, 0.005, 0.001, 0.001, 0]}, {"dt": "2019-09-20_00:00", "vals": [null, 0.006, 0.1, 0.003, 0, 0, 0]}, {"dt": "2019-09-21_00:00", "vals": [null, 0.006, 0.1, 0.003, 0, 0.002, 0]}], "mpcAD": [{"name": "Взвешенные в-ва", "val": 0.15}, {"name": "Диоксид серы", "val": 0.05}, {"name": "Оксид углерода", "val": 3}, {"name": "Диоксид азота", "val": 0.1}, {"name": "Оксид азота", "val": null}, {"name": "Сероводород", "val": null}, {"name": "Аммиак", "val": 0.1}], "ispel": 0}, {"ind": "3020101", "name": "Улан-Удэ", "nom": "1", "place": "пр.50 лет Октября, д.15", "label": "Улан-Удэ, №1, пр.50 лет Октября, д.15", "lng": "107.597501", "lat": "51.838996", "date": "21.09.2019", "si": [{"name": "Взвешенные в-ва", "val": -32768}, {"name": "Диоксид серы", "val": 0}, {"name": "Оксид углерода", "val": 0.2}, {"name": "Диоксид азота", "val": 0.4}, {"name": "Оксид азота", "val": 0.1}, {"name": "Озон", "val": 0.4}, {"name": "Сероводород", "val": 0.1}, {"name": "Фенол", "val": -32768}, {"name": "Аммиак", "val": 0}, {"name": "Формальдегид", "val": -32768}], "maxSi": 0.4, "meteoParamsNames": ["\"Температура\"", "\"Скорость ветра\"", "\"Влажность отн.\"", "\"Давление\"", "\"Направление ветра\""], "meteoParamsValues": [{"dt": "2019-09-15_01:00", "vals": [3, 1, 47, 716, 133]}, {"dt": "2019-09-15_07:00", "vals": [1, 0, 64, 716, 147]}, {"dt": "2019-09-15_13:00", "vals": [11, 2, 47, 713, 170]}, {"dt": "2019-09-15_19:00", "vals": [12, 1, 51, 711, 160]}, {"dt": "2019-09-16_01:00", "vals": [8, 0, 73, 711, 110]}, {"dt": "2019-09-16_07:00", "vals": [6, 1, 83, 711, 187]}, {"dt": "2019-09-16_13:00", "vals": [13, 2, 57, 711, 174]}, {"dt": "2019-09-16_19:00", "vals": [9, 1, 57, 713, 136]}, {"dt": "2019-09-17_01:00", "vals": [5, 1, 63, 718, 140]}, {"dt": "2019-09-17_07:00", "vals": [2, 0, 80, 721, 179]}, {"dt": "2019-09-17_13:00", "vals": [12, 1, 38, 720, 159]}, {"dt": "2019-09-17_19:00", "vals": [12, 0, 46, 719, 89]}, {"dt": "2019-09-18_01:00", "vals": [5, 1, 72, 718, 152]}, {"dt": "2019-09-18_07:00", "vals": [1, 1, 73, 717, 201]}, {"dt": "2019-09-18_13:00", "vals": [13, 1, 47, 715, 157]}, {"dt": "2019-09-18_19:00", "vals": [14, 1, 58, 715, 195]}, {"dt": "2019-09-19_01:00", "vals": [9, 0, 84, 715, 124]}, {"dt": "2019-09-19_07:00", "vals": [7, 1, 90, 717, 180]}, {"dt": "2019-09-19_13:00", "vals": [14, 1, 63, 717, 173]}, {"dt": "2019-09-19_19:00", "vals": [13, 0, 66, 717, 119]}, {"dt": "2019-09-20_01:00", "vals": [7, 0, 87, 718, 154]}, {"dt": "2019-09-20_07:00", "vals": [5, 0, 91, 719, 130]}, {"dt": "2019-09-20_13:00", "vals": [18, 1, 42, 718, 179]}, {"dt": "2019-09-20_19:00", "vals": [16, 1, 53, 717, 146]}, {"dt": "2019-09-21_01:00", "vals": [8, 1, 77, 717, 175]}, {"dt": "2019-09-21_07:00", "vals": [5, 2, 81, 717, 189]}, {"dt": "2019-09-21_13:00", "vals": [19, 1, 45, 715, 170]}, {"dt": "2019-09-21_19:00", "vals": [19, 0, 52, 715, 168]}], "siRange": "15.09.2019 - 21.09.2019", "meteoRange": "15.09.2019 - 21.09.2019", "maxSiWeek": [{"dt": "15.09.2019", "val": 0.3, "name": "Озон"}, {"dt": "16.09.2019", "val": 0.3, "name": "Озон"}, {"dt": "17.09.2019", "val": 0.3, "name": "Диоксид азота"}, {"dt": "18.09.2019", "val": 0.4, "name": "Диоксид азота"}, {"dt": "19.09.2019", "val": 0.6, "name": "Оксид углерода"}, {"dt": "20.09.2019", "val": 0.4, "name": "Озон"}, {"dt": "21.09.2019", "val": 0.4, "name": "Диоксид азота"}], "primsSS": [{"dt": "2019-09-15_00:00", "vals": [null, 0.002, 0.3, 0.021, 0.004, 0.031, 0, null, 0, null]}, {"dt": "2019-09-16_00:00", "vals": [null, 0.002, 0.3, 0.022, 0.005, 0.033, 0, null, 0, null]}, {"dt": "2019-09-17_00:00", "vals": [null, 0.002, 0.4, 0.03, 0.011, 0.027, 0, null, 0, null]}, {"dt": "2019-09-18_00:00", "vals": [null, 0.022, 0.6, 0.05, 0.028, 0.014, 0.001, null, 0, null]}, {"dt": "2019-09-19_00:00", "vals": [null, 0.003, 1.1, 0.037, 0.017, 0.02, 0.001, null, 0, null]}, {"dt": "2019-09-20_00:00", "vals": [null, 0.004, 0.3, 0.037, 0.009, 0.023, 0.001, null, 0, null]}, {"dt": "2019-09-21_00:00", "vals": [null, 0.013, 0.5, 0.041, 0.016, 0.023, 0.001, null, 0, null]}], "mpcAD": [{"name": "Взвешенные в-ва", "val": 0.15}, {"name": "Диоксид серы", "val": 0.05}, {"name": "Оксид углерода", "val": 3}, {"name": "Диоксид азота", "val": 0.1}, {"name": "Оксид азота", "val": null}, {"name": "Озон", "val": 0.1}, {"name": "Сероводород", "val": null}, {"name": "Фенол", "val": 0.006}, {"name": "Аммиак", "val": 0.1}, {"name": "Формальдегид", "val": 0.01}], "ispel": 0}, {"ind": "3020105", "name": "Гусиноозерск", "nom": "1", "place": "ул.Ленина, д.24", "label": "Гусиноозерск, №1, ул.Ленина, д.24", "lng": "106.53054", "lat": "51.28585", "date": "21.09.2019", "si": [{"name": "Взвешенные в-ва", "val": -32768}, {"name": "Диоксид серы", "val": 0}, {"name": "Оксид углерода", "val": 0.2}, {"name": "Диоксид азота", "val": 0.3}, {"name": "Оксид азота", "val": 0.1}, {"name": "Озон", "val": 0.4}, {"name": "Сероводород", "val": 0.1}, {"name": "Аммиак", "val": 0}, {"name": "Частицы 10 мкм (сут.)", "val": -32768}, {"name": "Частицы 2.5 мкм (сут.)", "val": -32768}], "maxSi": 0.4, "meteoParamsNames": ["\"Температура\"", "\"Скорость ветра\"", "\"Влажность отн.\"", "\"Давление\"", "\"Направление ветра\""], "meteoParamsValues": [{"dt": "2019-09-15_01:00", "vals": [5, 1, 46, 711, 38]}, {"dt": "2019-09-15_07:00", "vals": [3, 1, 61, 711, 126]}, {"dt": "2019-09-15_13:00", "vals": [10, 4, 51, 708, 218]}, {"dt": "2019-09-15_19:00", "vals": [12, 1, 47, 706, 166]}, {"dt": "2019-09-16_01:00", "vals": [6, 1, 74, 706, 37]}, {"dt": "2019-09-16_07:00", "vals": [6, 1, 74, 706, 31]}, {"dt": "2019-09-16_13:00", "vals": [13, 2, 55, 706, 153]}, {"dt": "2019-09-16_19:00", "vals": [10, 1, 56, 709, 108]}, {"dt": "2019-09-17_01:00", "vals": [6, 1, 54, 713, 24]}, {"dt": "2019-09-17_07:00", "vals": [6, 1, 62, 715, 33]}, {"dt": "2019-09-17_13:00", "vals": [12, 4, 44, 715, 229]}, {"dt": "2019-09-17_19:00", "vals": [13, 0, 54, 713, 19]}, {"dt": "2019-09-18_01:00", "vals": [6, 2, 76, 713, 35]}, {"dt": "2019-09-18_07:00", "vals": [4, 1, 81, 712, 33]}, {"dt": "2019-09-18_13:00", "vals": [14, 2, 60, 710, 235]}, {"dt": "2019-09-18_19:00", "vals": [15, 1, 60, 710, 173]}, {"dt": "2019-09-19_01:00", "vals": [11, 0, 73, 710, 78]}, {"dt": "2019-09-19_07:00", "vals": [9, 1, 75, 711, 9]}, {"dt": "2019-09-19_13:00", "vals": [16, 2, 56, 712, 135]}, {"dt": "2019-09-19_19:00", "vals": [13, 1, 57, 712, 44]}, {"dt": "2019-09-20_01:00", "vals": [9, 1, 73, 713, 39]}, {"dt": "2019-09-20_07:00", "vals": [7, 1, 79, 714, 31]}, {"dt": "2019-09-20_13:00", "vals": [15, 2, 61, 713, 247]}, {"dt": "2019-09-20_19:00", "vals": [15, 1, 59, 712, 47]}, {"dt": "2019-09-21_01:00", "vals": [10, 1, 73, 712, 36]}, {"dt": "2019-09-21_07:00", "vals": [8, 1, 80, 711, 37]}, {"dt": "2019-09-21_13:00", "vals": [17, 2, 54, 710, 240]}, {"dt": "2019-09-21_19:00", "vals": [17, 1, 55, 710, 22]}], "siRange": "15.09.2019 - 21.09.2019", "meteoRange": "15.09.2019 - 21.09.2019", "maxSiWeek": [{"dt": "15.09.2019", "val": 0.3, "name": "Озон"}, {"dt": "16.09.2019", "val": 0.3, "name": "Озон"}, {"dt": "17.09.2019", "val": 0.3, "name": "Диоксид азота"}, {"dt": "18.09.2019", "val": 0.3, "name": "Озон"}, {"dt": "19.09.2019", "val": 0.3, "name": "Диоксид азота"}, {"dt": "20.09.2019", "val": 0.3, "name": "Диоксид азота"}, {"dt": "21.09.2019", "val": 0.4, "name": "Озон"}], "primsSS": [{"dt": "2019-09-15_00:00", "vals": [null, 0.002, 0.2, 0.019, 0.011, 0.038, 0, 0, null, null]}, {"dt": "2019-09-16_00:00", "vals": [null, 0.005, 0.4, 0.028, 0.021, 0.032, 0.001, 0, null, null]}, {"dt": "2019-09-17_00:00", "vals": [null, 0.002, 0.4, 0.03, 0.025, 0.036, 0.001, 0, null, null]}, {"dt": "2019-09-18_00:00", "vals": [null, 0.002, 0.3, 0.029, 0.016, 0.026, 0, 0, null, null]}, {"dt": "2019-09-19_00:00", "vals": [null, 0.004, 0.5, 0.036, 0.023, 0.032, 0, 0, null, null]}, {"dt": "2019-09-20_00:00", "vals": [null, 0.001, 0.6, 0.034, 0.032, 0.028, 0, 0, null, null]}, {"dt": "2019-09-21_00:00", "vals": [null, 0.002, 0.5, 0.033, 0.017, 0.031, 0.001, 0, null, null]}], "mpcAD": [{"name": "Взвешенные в-ва", "val": 0.15}, {"name": "Диоксид серы", "val": 0.05}, {"name": "Оксид углерода", "val": 3}, {"name": "Диоксид азота", "val": 0.1}, {"name": "Оксид азота", "val": null}, {"name": "Озон", "val": 0.1}, {"name": "Сероводород", "val": null}, {"name": "Аммиак", "val": 0.1}, {"name": "Частицы 10 мкм (сут.)", "val": 0.06}, {"name": "Частицы 2.5 мкм (сут.)", "val": 0.035}], "ispel": 0}, {"ind": "38020110", "name": "Иркутск", "nom": "2", "place": "ул.Сухэ-Батора, д.5", "label": "Иркутск, ул.Сухэ-Батора, д.5", "lng": "104.282", "lat": "52.288917", "date": "21.09.2019", "si": [{"name": "Взвешенные в-ва", "val": -32768}, {"name": "Диоксид серы", "val": 0.1}, {"name": "Оксид углерода", "val": 0.3}, {"name": "Диоксид азота", "val": 0.7}, {"name": "Оксид азота", "val": 0.9}, {"name": "Формальдегид", "val": -32768}], "maxSi": 0.9, "meteoParamsNames": ["\"Температура\"", "\"Скорость ветра\"", "\"Влажность отн.\"", "\"Давление\"", "\"Направление ветра\""], "meteoParamsValues": [{"dt": "2019-09-15_01:00", "vals": [5, 1, 63, 725, 38]}, {"dt": "2019-09-15_07:00", "vals": [0, 1, 83, 722, 122]}, {"dt": "2019-09-15_13:00", "vals": [11, 1, 49, 721, 113]}, {"dt": "2019-09-15_19:00", "vals": [12, 0, 51, 720, 165]}, {"dt": "2019-09-16_01:00", "vals": [9, 0, 69, 720, 152]}, {"dt": "2019-09-16_07:00", "vals": [7, 0, 82, 720, null]}, {"dt": "2019-09-16_13:00", "vals": [10, 3, 83, 722, 21]}, {"dt": "2019-09-16_19:00", "vals": [10, 3, 68, 725, 18]}, {"dt": "2019-09-17_01:00", "vals": [6, 1, 85, 728, 22]}, {"dt": "2019-09-17_07:00", "vals": [4, 1, 88, 728, 134]}, {"dt": "2019-09-17_13:00", "vals": [14, 1, 48, 728, 70]}, {"dt": "2019-09-18_01:00", "vals": [6, 1, 86, 725, 120]}, {"dt": "2019-09-18_07:00", "vals": [5, 1, 87, 723, 148]}, {"dt": "2019-09-18_13:00", "vals": [18, 1, 50, 724, 71]}, {"dt": "2019-09-18_19:00", "vals": [17, 0, 53, 725, 16]}, {"dt": "2019-09-19_01:00", "vals": [10, 0, 91, 725, 26]}, {"dt": "2019-09-19_07:00", "vals": [11, 1, 82, 727, 64]}, {"dt": "2019-09-19_13:00", "vals": [14, 1, 64, 727, 30]}, {"dt": "2019-09-19_19:00", "vals": [16, 0, 59, 727, null]}, {"dt": "2019-09-20_01:00", "vals": [8, 1, 86, 727, 163]}, {"dt": "2019-09-20_07:00", "vals": [6, 1, 88, 726, 131]}, {"dt": "2019-09-20_13:00", "vals": [20, 2, 48, 725, 167]}, {"dt": "2019-09-20_19:00", "vals": [18, 1, 45, 725, 170]}, {"dt": "2019-09-21_01:00", "vals": [10, 0, 82, 723, null]}, {"dt": "2019-09-21_07:00", "vals": [10, 1, 81, 722, 156]}, {"dt": "2019-09-21_13:00", "vals": [22, 1, 43, 723, 110]}, {"dt": "2019-09-21_19:00", "vals": [20, 0, 51, 724, null]}], "siRange": "15.09.2019 - 21.09.2019", "meteoRange": "15.09.2019 - 21.09.2019", "maxSiWeek": [{"dt": "15.09.2019", "val": 0.2, "name": "Диоксид азота"}, {"dt": "16.09.2019", "val": 0.3, "name": "Диоксид азота"}, {"dt": "17.09.2019", "val": 0.2, "name": "Диоксид азота"}, {"dt": "18.09.2019", "val": 0.5, "name": "Диоксид азота"}, {"dt": "19.09.2019", "val": 1, "name": "Оксид азота"}, {"dt": "20.09.2019", "val": 0.4, "name": "Диоксид азота"}, {"dt": "21.09.2019", "val": 0.9, "name": "Оксид азота"}], "primsSS": [{"dt": "2019-09-15_00:00", "vals": [null, 0.021, 0.3, 0.028, 0.022, null]}, {"dt": "2019-09-16_00:00", "vals": [null, 0.011, 0.6, 0.044, 0.074, null]}, {"dt": "2019-09-17_00:00", "vals": [null, 0.005, 0.4, 0.019, 0.021, null]}, {"dt": "2019-09-18_00:00", "vals": [null, 0.005, 0.6, 0.051, 0.058, null]}, {"dt": "2019-09-19_00:00", "vals": [null, 0.023, 0.9, 0.083, 0.16, null]}, {"dt": "2019-09-20_00:00", "vals": [null, 0.006, 0.5, 0.031, 0.021, null]}, {"dt": "2019-09-21_00:00", "vals": [null, 0.013, 0.8, 0.069, 0.114, null]}], "mpcAD": [{"name": "Взвешенные в-ва", "val": 0.15}, {"name": "Диоксид серы", "val": 0.05}, {"name": "Оксид углерода", "val": 3}, {"name": "Диоксид азота", "val": 0.1}, {"name": "Оксид азота", "val": null}, {"name": "Формальдегид", "val": 0.01}], "ispel": 0}, {"ind": "3020104", "name": "Селенгинск", "nom": "2", "place": "с.Брянск, ул.Новая, д.19", "label": "Селенгинск, №2, с.Брянск, ул.Новая, д.19", "lng": "106.83843", "lat": "52.02293", "date": "21.09.2019", "si": [{"name": "Взвешенные в-ва", "val": -32768}, {"name": "Диоксид серы", "val": 0}, {"name": "Сульфаты растворимые", "val": -32768}, {"name": "Оксид углерода", "val": 0.1}, {"name": "Диоксид азота", "val": 0.2}, {"name": "Оксид азота", "val": 0.1}, {"name": "Сероводород", "val": 1}, {"name": "Фенол", "val": -32768}, {"name": "Аммиак", "val": 0}, {"name": "Формальдегид", "val": -32768}, {"name": "Частицы 10 мкм (сут.)", "val": -32768}, {"name": "Частицы 2.5 мкм (сут.)", "val": -32768}], "maxSi": 1, "meteoParamsNames": ["\"Температура\"", "\"Скорость ветра\"", "\"Влажность отн.\"", "\"Давление\"", "\"Направление ветра\""], "meteoParamsValues": [{"dt": "2019-09-15_01:00", "vals": [1, 1, 67, 723, 99]}, {"dt": "2019-09-15_07:00", "vals": [-1, 2, 83, 723, 327]}, {"dt": "2019-09-15_13:00", "vals": [12, 2, 46, 720, 253]}, {"dt": "2019-09-15_19:00", "vals": [11, 1, 64, 719, 68]}, {"dt": "2019-09-16_01:00", "vals": [6, 1, 86, 718, 106]}, {"dt": "2019-09-16_07:00", "vals": [4, 1, 94, 718, 332]}, {"dt": "2019-09-16_13:00", "vals": [13, 4, 64, 719, 178]}, {"dt": "2019-09-16_19:00", "vals": [9, 3, 63, 722, 175]}, {"dt": "2019-09-17_01:00", "vals": [4, 1, 69, 726, 178]}, {"dt": "2019-09-17_07:00", "vals": [1, 1, 84, 728, 118]}, {"dt": "2019-09-17_13:00", "vals": [12, 2, 45, 728, 239]}, {"dt": "2019-09-17_19:00", "vals": [10, 1, 61, 726, 50]}, {"dt": "2019-09-18_01:00", "vals": [4, 3, 79, 725, 211]}, {"dt": "2019-09-18_13:00", "vals": [14, 2, 62, 723, 214]}, {"dt": "2019-09-18_19:00", "vals": [12, 1, 76, 722, 71]}, {"dt": "2019-09-19_01:00", "vals": [6, 1, 93, 723, 237]}, {"dt": "2019-09-19_07:00", "vals": [6, 1, 94, 724, 164]}, {"dt": "2019-09-19_19:00", "vals": [12, 1, 81, 725, 127]}, {"dt": "2019-09-20_01:00", "vals": [4, 1, 96, 726, 334]}, {"dt": "2019-09-20_07:00", "vals": [4, 2, 97, 726, 338]}, {"dt": "2019-09-20_13:00", "vals": [19, 3, 43, 725, 300]}, {"dt": "2019-09-20_19:00", "vals": [15, 1, 66, 723, 235]}, {"dt": "2019-09-21_01:00", "vals": [9, 4, 83, 723, 332]}, {"dt": "2019-09-21_07:00", "vals": [9, 3, 81, 722, 343]}, {"dt": "2019-09-21_13:00", "vals": [22, 2, 44, 722, 299]}, {"dt": "2019-09-21_19:00", "vals": [16, 0, 77, 721, 133]}], "siRange": "15.09.2019 - 21.09.2019", "meteoRange": "15.09.2019 - 21.09.2019", "maxSiWeek": [{"dt": "15.09.2019", "val": 1, "name": "Сероводород"}, {"dt": "16.09.2019", "val": 0.2, "name": "Сероводород"}, {"dt": "17.09.2019", "val": 0.3, "name": "Сероводород"}, {"dt": "18.09.2019", "val": 0.4, "name": "Оксид углерода"}, {"dt": "19.09.2019", "val": 1.1, "name": "Сероводород"}, {"dt": "20.09.2019", "val": 0.5, "name": "Сероводород"}, {"dt": "21.09.2019", "val": 1, "name": "Сероводород"}], "primsSS": [{"dt": "2019-09-15_00:00", "vals": [null, 0.017, null, 0.4, 0.012, 0.011, 0.003, null, 0, null, null, null]}, {"dt": "2019-09-16_00:00", "vals": [null, 0.006, null, 0.1, 0.003, 0.005, 0.001, null, 0, null, null, null]}, {"dt": "2019-09-17_00:00", "vals": [null, 0.006, null, 0.2, 0.014, 0.008, 0.001, null, 0, null, null, null]}, {"dt": "2019-09-18_00:00", "vals": [null, 0.002, null, 1.3, 0.016, 0.019, 0, null, 0, null, null, null]}, {"dt": "2019-09-19_00:00", "vals": [null, 0.003, null, 0.9, 0.012, 0.013, 0.003, null, 0, null, null, null]}, {"dt": "2019-09-20_00:00", "vals": [null, 0.004, null, 0.2, 0.016, 0.01, 0.002, null, 0, null, null, null]}, {"dt": "2019-09-21_00:00", "vals": [null, 0.011, null, 0.2, 0.014, 0.012, 0.003, null, 0, null, null, null]}], "mpcAD": [{"name": "Взвешенные в-ва", "val": 0.15}, {"name": "Диоксид серы", "val": 0.05}, {"name": "Сульфаты растворимые", "val": null}, {"name": "Оксид углерода", "val": 3}, {"name": "Диоксид азота", "val": 0.1}, {"name": "Оксид азота", "val": null}, {"name": "Сероводород", "val": null}, {"name": "Фенол", "val": 0.006}, {"name": "Аммиак", "val": 0.1}, {"name": "Формальдегид", "val": 0.01}, {"name": "Частицы 10 мкм (сут.)", "val": 0.06}, {"name": "Частицы 2.5 мкм (сут.)", "val": 0.035}], "ispel": 0}, {"ind": "3020102", "name": "Улан-Удэ", "nom": "2", "place": "ул.Бабушкина, участок № 16", "label": "Улан-Удэ, №2, ул.Бабушкина, участок № 16", "lng": "107.594363", "lat": "51.815382", "date": "21.09.2019", "si": [{"name": "Взвешенные в-ва", "val": -32768}, {"name": "Диоксид серы", "val": 0}, {"name": "Оксид углерода", "val": 0.2}, {"name": "Диоксид азота", "val": 0.6}, {"name": "Оксид азота", "val": 0.4}, {"name": "Сероводород", "val": 0.1}, {"name": "Фенол", "val": -32768}, {"name": "Аммиак", "val": 0.2}], "maxSi": 0.6, "meteoParamsNames": ["\"Температура\"", "\"Скорость ветра\"", "\"Влажность отн.\"", "\"Давление\"", "\"Направление ветра\""], "meteoParamsValues": [{"dt": "2019-09-15_01:00", "vals": [4, 1, 49, 720, 250]}, {"dt": "2019-09-15_07:00", "vals": [1, 1, 75, 720, 247]}, {"dt": "2019-09-15_13:00", "vals": [11, 3, 48, 717, 176]}, {"dt": "2019-09-15_19:00", "vals": [13, 1, 57, 716, 259]}, {"dt": "2019-09-16_01:00", "vals": [9, 1, 74, 715, 156]}, {"dt": "2019-09-16_07:00", "vals": [7, 2, 86, 715, 267]}, {"dt": "2019-09-16_13:00", "vals": [14, 4, 59, 715, 263]}, {"dt": "2019-09-16_19:00", "vals": [11, 2, 57, 718, 257]}, {"dt": "2019-09-17_01:00", "vals": [6, 1, 66, 722, 258]}, {"dt": "2019-09-17_07:00", "vals": [2, 1, 85, 725, 253]}, {"dt": "2019-09-17_13:00", "vals": [13, 1, 38, 724, 302]}, {"dt": "2019-09-17_19:00", "vals": [13, 0, 46, 723, 220]}, {"dt": "2019-09-18_01:00", "vals": [5, 1, 74, 723, 76]}, {"dt": "2019-09-18_07:00", "vals": [4, 3, 67, 721, 112]}, {"dt": "2019-09-18_13:00", "vals": [13, 1, 47, 719, 86]}, {"dt": "2019-09-18_19:00", "vals": [16, 1, 53, 719, 238]}, {"dt": "2019-09-19_01:00", "vals": [9, 1, 88, 720, 241]}, {"dt": "2019-09-19_07:00", "vals": [7, 1, 92, 721, 265]}, {"dt": "2019-09-19_13:00", "vals": [15, 2, 64, 721, 271]}, {"dt": "2019-09-19_19:00", "vals": [14, 1, 66, 721, 253]}, {"dt": "2019-09-20_01:00", "vals": [7, 1, 88, 723, 251]}, {"dt": "2019-09-20_07:00", "vals": [4, 1, 97, 724, 175]}, {"dt": "2019-09-20_13:00", "vals": [19, 2, 43, 722, 266]}, {"dt": "2019-09-20_19:00", "vals": [18, 1, 51, 721, 139]}, {"dt": "2019-09-21_01:00", "vals": [null, null, null, null, null]}, {"dt": "2019-09-21_07:00", "vals": [null, null, null, null, null]}, {"dt": "2019-09-21_13:00", "vals": [20, 1, 46, 719, 133]}, {"dt": "2019-09-21_19:00", "vals": [20, 1, 51, 719, 120]}], "siRange": "15.09.2019 - 21.09.2019", "meteoRange": "15.09.2019 - 21.09.2019", "maxSiWeek": [{"dt": "15.09.2019", "val": 0.2, "name": "Диоксид азота"}, {"dt": "16.09.2019", "val": 0.2, "name": "Диоксид азота"}, {"dt": "17.09.2019", "val": 0.4, "name": "Диоксид азота"}, {"dt": "18.09.2019", "val": 0.4, "name": "Диоксид азота"}, {"dt": "19.09.2019", "val": 0.2, "name": "Диоксид азота"}, {"dt": "20.09.2019", "val": 0.7, "name": "Диоксид азота"}, {"dt": "21.09.2019", "val": 0.6, "name": "Диоксид азота"}], "primsSS": [{"dt": "2019-09-15_00:00", "vals": [null, 0.005, 0.2, 0.019, 0.006, 0.001, null, 0]}, {"dt": "2019-09-16_00:00", "vals": [null, 0.007, 0, 0.023, 0.006, 0.001, null, 0]}, {"dt": "2019-09-17_00:00", "vals": [null, 0.005, 0.3, 0.031, 0.02, 0.001, null, 0]}, {"dt": "2019-09-18_00:00", "vals": [null, 0.01, 0.3, 0.049, 0.029, 0.001, null, 0.01]}, {"dt": "2019-09-19_00:00", "vals": [null, 0.006, 0.2, 0.026, 0.007, 0, null, 0]}, {"dt": "2019-09-20_00:00", "vals": [null, 0.007, 0.2, 0.046, 0.05, 0.001, null, 0.01]}, {"dt": "2019-09-21_00:00", "vals": [null, 0.008, 0.3, 0.058, 0.052, 0, null, 0.01]}], "mpcAD": [{"name": "Взвешенные в-ва", "val": 0.15}, {"name": "Диоксид серы", "val": 0.05}, {"name": "Оксид углерода", "val": 3}, {"name": "Диоксид азота", "val": 0.1}, {"name": "Оксид азота", "val": null}, {"name": "Сероводород", "val": null}, {"name": "Фенол", "val": 0.006}, {"name": "Аммиак", "val": 0.1}], "ispel": 0}, {"ind": "38020107", "name": "Иркутск", "nom": "3", "place": "ул.Лермонтова, д.317", "label": "Иркутск, ул.Лермонтова, д.317", "lng": "104.272667", "lat": "52.242567", "date": "21.09.2019", "si": [{"name": "Взвешенные в-ва", "val": -32768}, {"name": "Диоксид серы", "val": 0}, {"name": "Оксид углерода", "val": 0.3}, {"name": "Диоксид азота", "val": 1.7}, {"name": "Оксид азота", "val": 0.9}, {"name": "Сероводород", "val": 0.4}, {"name": "Формальдегид", "val": -32768}, {"name": "Частицы 2.5 мкм (сут.)", "val": 0}], "maxSi": 1.7, "meteoParamsNames": ["\"Температура\"", "\"Скорость ветра\"", "\"Влажность отн.\"", "\"Давление\"", "\"Направление ветра\""], "meteoParamsValues": [{"dt": "2019-09-15_01:00", "vals": [4, 0, 69, 725, null]}, {"dt": "2019-09-15_07:00", "vals": [2, 0, 92, 723, null]}, {"dt": "2019-09-15_13:00", "vals": [11, 1, 56, 721, 162]}, {"dt": "2019-09-15_19:00", "vals": [11, 0, 66, 720, null]}, {"dt": "2019-09-16_01:00", "vals": [8, 0, 83, 719, null]}, {"dt": "2019-09-16_07:00", "vals": [7, 0, 88, 720, null]}, {"dt": "2019-09-16_13:00", "vals": [10, 1, 86, 722, 131]}, {"dt": "2019-09-16_19:00", "vals": [9, 1, 72, 725, 141]}, {"dt": "2019-09-17_01:00", "vals": [5, 0, 91, 728, null]}, {"dt": "2019-09-17_07:00", "vals": [6, 0, 93, 729, null]}, {"dt": "2019-09-17_13:00", "vals": [14, 0, 53, 728, 188]}, {"dt": "2019-09-17_19:00", "vals": [11, 0, 75, 726, null]}, {"dt": "2019-09-18_01:00", "vals": [6, 0, 94, 725, null]}, {"dt": "2019-09-18_07:00", "vals": [7, 0, 95, 724, null]}, {"dt": "2019-09-18_13:00", "vals": [17, 0, 54, 724, 181]}, {"dt": "2019-09-18_19:00", "vals": [15, 0, 67, 723, null]}, {"dt": "2019-09-19_01:00", "vals": [10, 0, 97, 724, 146]}, {"dt": "2019-09-19_07:00", "vals": [11, 0, 91, 726, null]}, {"dt": "2019-09-19_13:00", "vals": [15, 1, 65, 727, 216]}, {"dt": "2019-09-19_19:00", "vals": [14, 0, 76, 726, null]}, {"dt": "2019-09-20_01:00", "vals": [8, 0, 96, 727, null]}, {"dt": "2019-09-20_07:00", "vals": [8, 0, 98, 726, null]}, {"dt": "2019-09-20_13:00", "vals": [21, 1, 48, 724, 248]}, {"dt": "2019-09-20_19:00", "vals": [16, 1, 54, 723, 332]}, {"dt": "2019-09-21_01:00", "vals": [9, 0, 89, 722, null]}, {"dt": "2019-09-21_07:00", "vals": [9, 0, 93, 722, null]}, {"dt": "2019-09-21_13:00", "vals": [22, 1, 46, 722, 163]}, {"dt": "2019-09-21_19:00", "vals": [16, 0, 63, 721, null]}], "siRange": "15.09.2019 - 21.09.2019", "meteoRange": "15.09.2019 - 21.09.2019", "maxSiWeek": [{"dt": "15.09.2019", "val": 0.5, "name": "Оксид азота"}, {"dt": "16.09.2019", "val": 0.2, "name": "Оксид углерода"}, {"dt": "17.09.2019", "val": 0.9, "name": "Оксид азота"}, {"dt": "18.09.2019", "val": 0.9, "name": "Оксид азота"}, {"dt": "19.09.2019", "val": 1.4, "name": "Диоксид азота"}, {"dt": "20.09.2019", "val": 0.9, "name": "Диоксид азота"}, {"dt": "21.09.2019", "val": 1.7, "name": "Диоксид азота"}], "primsSS": [{"dt": "2019-09-15_00:00", "vals": [null, 0, 0.5, 0.003, 0.072, 0, null, 0.001]}, {"dt": "2019-09-16_00:00", "vals": [null, 0.001, 0.6, 0.003, 0.058, 0.001, null, 0.001]}, {"dt": "2019-09-17_00:00", "vals": [null, 0.001, 0.7, 0.002, 0.102, 0.001, null, 0.002]}, {"dt": "2019-09-18_00:00", "vals": [null, 0.001, 1, 0.003, 0.142, 0, null, 0.001]}, {"dt": "2019-09-19_00:00", "vals": [null, 0, 0.8, 0.075, 0.124, 0.001, null, 0.001]}, {"dt": "2019-09-20_00:00", "vals": [null, 0.001, 0.9, 0.11, 0.093, 0.003, null, 0.002]}, {"dt": "2019-09-21_00:00", "vals": [null, 0.002, 1.1, 0.183, 0.184, 0.002, null, 0]}], "mpcAD": [{"name": "Взвешенные в-ва", "val": 0.15}, {"name": "Диоксид серы", "val": 0.05}, {"name": "Оксид углерода", "val": 3}, {"name": "Диоксид азота", "val": 0.1}, {"name": "Оксид азота", "val": null}, {"name": "Сероводород", "val": null}, {"name": "Формальдегид", "val": 0.01}, {"name": "Частицы 2.5 мкм (сут.)", "val": 0.035}], "ispel": 0}, {"ind": "38020108", "name": "Иркутск", "nom": "4", "place": "ул.Партизанская, д.76", "label": "Иркутск, ул.Партизанская, д.76", "lng": "104.307889", "lat": "52.272306", "date": "21.09.2019", "si": [{"name": "Взвешенные в-ва", "val": -32768}, {"name": "Диоксид серы", "val": 0}, {"name": "Оксид углерода", "val": 0.1}, {"name": "Диоксид азота", "val": 0.1}, {"name": "Оксид азота", "val": 0}, {"name": "Озон", "val": 0.2}, {"name": "Частицы 10 мкм (сут.)", "val": -32768}], "maxSi": 0.2, "meteoParamsNames": ["\"Температура\"", "\"Скорость ветра\"", "\"Влажность отн.\"", "\"Давление\"", "\"Направление ветра\""], "meteoParamsValues": [{"dt": "2019-09-15_01:00", "vals": [null, null, null, null, null]}, {"dt": "2019-09-15_07:00", "vals": [null, null, null, null, null]}, {"dt": "2019-09-15_13:00", "vals": [null, null, null, null, null]}, {"dt": "2019-09-15_19:00", "vals": [null, null, null, null, null]}, {"dt": "2019-09-16_01:00", "vals": [null, null, null, null, null]}, {"dt": "2019-09-16_07:00", "vals": [null, null, null, null, null]}, {"dt": "2019-09-16_13:00", "vals": [null, null, null, null, null]}, {"dt": "2019-09-16_19:00", "vals": [null, null, null, null, null]}, {"dt": "2019-09-17_01:00", "vals": [null, null, null, null, null]}, {"dt": "2019-09-17_07:00", "vals": [null, null, null, null, null]}, {"dt": "2019-09-17_13:00", "vals": [null, null, null, null, null]}, {"dt": "2019-09-17_19:00", "vals": [null, null, null, null, null]}, {"dt": "2019-09-18_01:00", "vals": [null, null, null, null, null]}, {"dt": "2019-09-18_07:00", "vals": [null, null, null, null, null]}, {"dt": "2019-09-18_13:00", "vals": [null, null, null, null, null]}, {"dt": "2019-09-18_19:00", "vals": [null, null, null, null, null]}, {"dt": "2019-09-19_01:00", "vals": [null, null, null, null, null]}, {"dt": "2019-09-19_07:00", "vals": [null, null, null, null, null]}, {"dt": "2019-09-19_13:00", "vals": [null, null, null, null, null]}, {"dt": "2019-09-19_19:00", "vals": [null, null, null, null, null]}, {"dt": "2019-09-20_01:00", "vals": [null, null, null, null, null]}, {"dt": "2019-09-20_07:00", "vals": [null, null, null, null, null]}, {"dt": "2019-09-20_13:00", "vals": [null, null, null, null, null]}, {"dt": "2019-09-20_19:00", "vals": [null, null, null, null, null]}, {"dt": "2019-09-21_01:00", "vals": [null, null, null, null, null]}, {"dt": "2019-09-21_07:00", "vals": [null, null, null, null, null]}, {"dt": "2019-09-21_13:00", "vals": [null, null, null, null, null]}, {"dt": "2019-09-21_19:00", "vals": [null, null, null, null, null]}], "siRange": "15.09.2019 - 21.09.2019", "meteoRange": "15.09.2019 - 21.09.2019", "maxSiWeek": [{"dt": "15.09.2019", "val": 0.2, "name": "Озон"}, {"dt": "16.09.2019", "val": 0.1, "name": "Оксид углерода"}, {"dt": "17.09.2019", "val": 0.2, "name": "Оксид углерода"}, {"dt": "18.09.2019", "val": 0.3, "name": "Оксид углерода"}, {"dt": "19.09.2019", "val": 0.2, "name": "Оксид углерода"}, {"dt": "20.09.2019", "val": 0.2, "name": "Озон"}, {"dt": "21.09.2019", "val": 0.2, "name": "Озон"}], "primsSS": [{"dt": "2019-09-15_00:00", "vals": [null, 0.014, 0.4, 0.009, 0.005, 0.014, null]}, {"dt": "2019-09-16_00:00", "vals": [null, 0.009, 0.3, 0.007, 0.01, 0.011, null]}, {"dt": "2019-09-17_00:00", "vals": [null, 0.004, 0.6, 0.008, 0.012, 0.016, null]}, {"dt": "2019-09-18_00:00", "vals": [null, 0.01, 0.9, 0.007, 0.026, 0.011, null]}, {"dt": "2019-09-19_00:00", "vals": [null, 0.011, 0.6, 0.011, 0.02, 0.009, null]}, {"dt": "2019-09-20_00:00", "vals": [null, 0.002, 0.5, 0.01, 0.006, 0.017, null]}, {"dt": "2019-09-21_00:00", "vals": [null, 0.007, 0.4, 0.01, 0.005, 0.024, null]}], "mpcAD": [{"name": "Взвешенные в-ва", "val": 0.15}, {"name": "Диоксид серы", "val": 0.05}, {"name": "Оксид углерода", "val": 3}, {"name": "Диоксид азота", "val": 0.1}, {"name": "Оксид азота", "val": null}, {"name": "Озон", "val": 0.1}, {"name": "Частицы 10 мкм (сут.)", "val": 0.06}], "ispel": 0}, {"ind": "75020102", "name": "Чита", "nom": "4", "place": "ул.Лазо, д.30", "label": "Чита, №4, ул.Лазо, д.30", "lng": "113.5", "lat": "52.019444", "date": "21.09.2019", "si": [{"name": "Взвешенные в-ва", "val": -32768}, {"name": "Диоксид серы", "val": 0}, {"name": "Оксид углерода", "val": 0.1}, {"name": "Диоксид азота", "val": 0.4}, {"name": "Оксид азота", "val": 0.1}, {"name": "Сероводород", "val": 2.5}, {"name": "Фенол", "val": -32768}, {"name": "Сажа", "val": -32768}, {"name": "Аммиак", "val": 0}], "maxSi": 2.5, "meteoParamsNames": ["\"Температура\"", "\"Скорость ветра\"", "\"Влажность отн.\"", "\"Давление\"", "\"Направление ветра\""], "meteoParamsValues": [{"dt": "2019-09-15_01:00", "vals": [6, 2, 51, 702, 298]}, {"dt": "2019-09-15_07:00", "vals": [1, 2, 54, 705, 293]}, {"dt": "2019-09-15_13:00", "vals": [8, 3, 27, 705, 293]}, {"dt": "2019-09-15_19:00", "vals": [8, 3, 28, 704, 291]}, {"dt": "2019-09-16_01:00", "vals": [3, 0, 68, 704, null]}, {"dt": "2019-09-16_07:00", "vals": [3, 0, 79, 703, null]}, {"dt": "2019-09-16_13:00", "vals": [14, 1, 48, 701, 215]}, {"dt": "2019-09-16_19:00", "vals": [7, 1, 87, 701, 287]}, {"dt": "2019-09-17_01:00", "vals": [5, 1, 51, 704, 296]}, {"dt": "2019-09-17_07:00", "vals": [1, 0, 59, 708, 290]}, {"dt": "2019-09-17_13:00", "vals": [10, 3, 28, 710, 287]}, {"dt": "2019-09-17_19:00", "vals": [10, 2, 35, 709, 291]}, {"dt": "2019-09-18_01:00", "vals": [2, 0, 76, 711, null]}, {"dt": "2019-09-18_07:00", "vals": [-2, 0, 91, 711, null]}, {"dt": "2019-09-18_13:00", "vals": [15, 0, 34, 708, null]}, {"dt": "2019-09-18_19:00", "vals": [15, 0, 50, 706, 293]}, {"dt": "2019-09-19_01:00", "vals": [5, 0, 91, 706, null]}, {"dt": "2019-09-19_07:00", "vals": [1, 0, 98, 707, null]}, {"dt": "2019-09-19_13:00", "vals": [16, 3, 48, 706, 290]}, {"dt": "2019-09-19_19:00", "vals": [15, 2, 48, 706, 288]}, {"dt": "2019-09-20_01:00", "vals": [9, 1, 64, 708, 292]}, {"dt": "2019-09-20_07:00", "vals": [6, 0, 82, 710, null]}, {"dt": "2019-09-20_13:00", "vals": [16, 0, 40, 710, 291]}, {"dt": "2019-09-20_19:00", "vals": [15, 0, 41, 709, 292]}, {"dt": "2019-09-21_01:00", "vals": [5, 0, 86, 710, null]}, {"dt": "2019-09-21_07:00", "vals": [1, 0, 97, 711, null]}, {"dt": "2019-09-21_13:00", "vals": [19, 0, 40, 709, 276]}, {"dt": "2019-09-21_19:00", "vals": [18, 0, 47, 708, null]}], "siRange": "15.09.2019 - 21.09.2019", "meteoRange": "15.09.2019 - 21.09.2019", "maxSiWeek": [{"dt": "15.09.2019", "val": 2, "name": "Сероводород"}, {"dt": "16.09.2019", "val": 3.4, "name": "Сероводород"}, {"dt": "17.09.2019", "val": 1.8, "name": "Сероводород"}, {"dt": "18.09.2019", "val": 30.8, "name": "Сероводород"}, {"dt": "19.09.2019", "val": 5.4, "name": "Сероводород"}, {"dt": "20.09.2019", "val": 3.4, "name": "Сероводород"}, {"dt": "21.09.2019", "val": 2.5, "name": "Сероводород"}], "primsSS": [{"dt": "2019-09-15_00:00", "vals": [null, 0.002, 0.4, 0.008, 0.004, 0.007, null, null, 0]}, {"dt": "2019-09-16_00:00", "vals": [null, 0.002, 0.3, 0.023, 0.019, 0.016, null, null, 0]}, {"dt": "2019-09-17_00:00", "vals": [null, 0.002, 0.5, 0.023, 0.021, 0.008, null, null, 0]}, {"dt": "2019-09-18_00:00", "vals": [null, 0.007, 0.6, 0.037, 0.03, 0.076, null, null, 0]}, {"dt": "2019-09-19_00:00", "vals": [null, 0.005, 0.4, 0.028, 0.022, 0.024, null, null, 0]}, {"dt": "2019-09-20_00:00", "vals": [null, 0.004, 0.1, 0.043, 0.02, 0.012, null, null, 0]}, {"dt": "2019-09-21_00:00", "vals": [null, 0.005, 0.3, 0.035, 0.016, 0.012, null, null, 0]}], "mpcAD": [{"name": "Взвешенные в-ва", "val": 0.15}, {"name": "Диоксид серы", "val": 0.05}, {"name": "Оксид углерода", "val": 3}, {"name": "Диоксид азота", "val": 0.1}, {"name": "Оксид азота", "val": null}, {"name": "Сероводород", "val": null}, {"name": "Фенол", "val": 0.006}, {"name": "Сажа", "val": 0.05}, {"name": "Аммиак", "val": 0.1}], "ispel": 0}, {"ind": "38020105", "name": "Усолье-Сибирское", "nom": "4", "place": "Комсомольский пр., д.33", "label": "Усолье-Сибирское, Комсомольский пр., д.33", "lng": "103.638619", "lat": "52.758317", "date": "21.09.2019", "si": [{"name": "Взвешенные в-ва", "val": -32768}, {"name": "Диоксид серы", "val": 0}, {"name": "Оксид углерода", "val": 0.3}, {"name": "Диоксид азота", "val": 0.2}, {"name": "Оксид азота", "val": 0.5}, {"name": "Сероводород", "val": 0.4}, {"name": "Хлор", "val": -32768}, {"name": "Хлорид водорода", "val": -32768}, {"name": "Частицы 10 мкм (сут.)", "val": -32768}], "maxSi": 0.5, "meteoParamsNames": ["\"Температура\"", "\"Скорость ветра\"", "\"Влажность отн.\"", "\"Давление\"", "\"Направление ветра\""], "meteoParamsValues": [{"dt": "2019-09-15_01:00", "vals": [3, 0, 75, 727, 144]}, {"dt": "2019-09-15_07:00", "vals": [1, 0, 94, 725, null]}, {"dt": "2019-09-15_13:00", "vals": [10, 2, 51, 723, 147]}, {"dt": "2019-09-15_19:00", "vals": [10, 1, 61, 721, 156]}, {"dt": "2019-09-16_07:00", "vals": [6, 0, 95, 722, 136]}, {"dt": "2019-09-16_13:00", "vals": [9, 3, 77, 724, 330]}, {"dt": "2019-09-16_19:00", "vals": [9, 2, 71, 727, 298]}, {"dt": "2019-09-17_01:00", "vals": [4, 0, 97, 730, 276]}, {"dt": "2019-09-17_07:00", "vals": [5, 1, 98, 731, 130]}, {"dt": "2019-09-17_13:00", "vals": [14, 2, 57, 729, 142]}, {"dt": "2019-09-17_19:00", "vals": [13, 0, 61, 727, 161]}, {"dt": "2019-09-18_01:00", "vals": [7, 0, 87, 726, null]}, {"dt": "2019-09-18_07:00", "vals": [6, 0, 94, 726, 159]}, {"dt": "2019-09-18_13:00", "vals": [18, 2, 49, 725, 341]}, {"dt": "2019-09-18_19:00", "vals": [16, 0, 65, 725, 275]}, {"dt": "2019-09-19_01:00", "vals": [12, 2, 85, 727, 315]}, {"dt": "2019-09-19_07:00", "vals": [10, 1, 94, 728, 302]}, {"dt": "2019-09-19_13:00", "vals": [16, 1, 53, 728, 232]}, {"dt": "2019-09-19_19:00", "vals": [13, 0, 78, 728, null]}, {"dt": "2019-09-20_01:00", "vals": [7, 0, 99, 728, 162]}, {"dt": "2019-09-20_07:00", "vals": [7, 1, 97, 728, 152]}, {"dt": "2019-09-20_13:00", "vals": [18, 2, 53, 726, 146]}, {"dt": "2019-09-20_19:00", "vals": [18, 0, 50, 724, 166]}, {"dt": "2019-09-21_01:00", "vals": [11, 0, 74, 724, 164]}, {"dt": "2019-09-21_07:00", "vals": [9, 0, 91, 724, 149]}, {"dt": "2019-09-21_13:00", "vals": [23, 1, 33, 724, 69]}, {"dt": "2019-09-21_19:00", "vals": [17, 0, 65, 723, 257]}], "siRange": "15.09.2019 - 21.09.2019", "meteoRange": "15.09.2019 - 21.09.2019", "maxSiWeek": [{"dt": "15.09.2019", "val": 0.7, "name": "Сероводород"}, {"dt": "16.09.2019", "val": 0.7, "name": "Сероводород"}, {"dt": "17.09.2019", "val": 0.9, "name": "Сероводород"}, {"dt": "18.09.2019", "val": 0.6, "name": "Сероводород"}, {"dt": "19.09.2019", "val": 0.6, "name": "Оксид азота"}, {"dt": "20.09.2019", "val": 0.6, "name": "Сероводород"}, {"dt": "21.09.2019", "val": 0.5, "name": "Оксид азота"}], "primsSS": [{"dt": "2019-09-15_00:00", "vals": [null, 0.023, 0.3, 0.009, 0.008, 0.004, null, null, null]}, {"dt": "2019-09-16_00:00", "vals": [null, 0.007, 0.3, 0.007, 0.016, 0.004, null, null, null]}, {"dt": "2019-09-17_00:00", "vals": [null, 0.033, 0.3, 0.018, 0.011, 0.004, null, null, null]}, {"dt": "2019-09-18_00:00", "vals": [null, 0.011, 0.5, 0.02, 0.041, 0.003, null, null, null]}, {"dt": "2019-09-19_00:00", "vals": [null, 0.004, 0.5, 0.007, 0.061, 0.002, null, null, null]}, {"dt": "2019-09-20_00:00", "vals": [null, 0.042, 0.6, 0.031, 0.041, 0.003, null, null, null]}, {"dt": "2019-09-21_00:00", "vals": [null, 0.017, 0.6, 0.019, 0.056, 0.002, null, null, null]}], "mpcAD": [{"name": "Взвешенные в-ва", "val": 0.15}, {"name": "Диоксид серы", "val": 0.05}, {"name": "Оксид углерода", "val": 3}, {"name": "Диоксид азота", "val": 0.1}, {"name": "Оксид азота", "val": null}, {"name": "Сероводород", "val": null}, {"name": "Хлор", "val": 0.03}, {"name": "Хлорид водорода", "val": 0.1}, {"name": "Частицы 10 мкм (сут.)", "val": 0.06}], "ispel": 0}, {"ind": "3020106", "name": "Улан-Удэ", "nom": "4", "place": " ул.Революции 1905 г., участок № 74", "label": "Улан-Удэ, №4,  ул.Революции 1905 г., участок № 74", "lng": "107.579117", "lat": "51.844186", "date": "21.09.2019", "si": [{"name": "Взвешенные в-ва", "val": -32768}, {"name": "Диоксид серы", "val": 0}, {"name": "Оксид углерода", "val": 0.4}, {"name": "Диоксид азота", "val": 0.3}, {"name": "Оксид азота", "val": 0.4}, {"name": "Сероводород", "val": 0.2}, {"name": "Фенол", "val": -32768}, {"name": "Сажа", "val": -32768}, {"name": "Частицы 10 мкм", "val": -32768}, {"name": "Частицы 2.5 мкм", "val": -32768}], "maxSi": 0.4, "meteoParamsNames": ["\"Температура\"", "\"Скорость ветра\"", "\"Влажность отн.\"", "\"Давление\"", "\"Направление ветра\""], "meteoParamsValues": [{"dt": "2019-09-15_01:00", "vals": [3, 1, 49, 717, 0]}, {"dt": "2019-09-15_07:00", "vals": [1, 0, 67, 717, 73]}, {"dt": "2019-09-15_13:00", "vals": [11, 2, 48, 714, 258]}, {"dt": "2019-09-15_19:00", "vals": [12, 1, 53, 712, 188]}, {"dt": "2019-09-16_01:00", "vals": [9, 0, 77, 712, 80]}, {"dt": "2019-09-16_07:00", "vals": [6, 1, 87, 712, 249]}, {"dt": "2019-09-16_13:00", "vals": [13, 2, 59, 712, 262]}, {"dt": "2019-09-16_19:00", "vals": [10, 1, 59, 714, 0]}, {"dt": "2019-09-17_01:00", "vals": [5, 1, 68, 719, 150]}, {"dt": "2019-09-17_07:00", "vals": [2, 0, 86, 722, 0]}, {"dt": "2019-09-17_13:00", "vals": [12, 1, 40, 721, 163]}, {"dt": "2019-09-17_19:00", "vals": [12, 0, 49, 720, 83]}, {"dt": "2019-09-18_01:00", "vals": [5, 0, 83, 719, 71]}, {"dt": "2019-09-18_07:00", "vals": [2, 1, 74, 718, 15]}, {"dt": "2019-09-18_13:00", "vals": [12, 1, 49, 716, 186]}, {"dt": "2019-09-18_19:00", "vals": [15, 0, 57, 716, 47]}, {"dt": "2019-09-19_01:00", "vals": [9, 0, 88, 716, 89]}, {"dt": "2019-09-19_07:00", "vals": [7, 1, 94, 718, 248]}, {"dt": "2019-09-19_13:00", "vals": [14, 1, 65, 718, 311]}, {"dt": "2019-09-19_19:00", "vals": [13, 0, 68, 718, 31]}, {"dt": "2019-09-20_01:00", "vals": [7, 0, 88, 719, 33]}, {"dt": "2019-09-20_07:00", "vals": [5, 0, 92, 720, 0]}, {"dt": "2019-09-20_13:00", "vals": [18, 1, 46, 719, 242]}, {"dt": "2019-09-20_19:00", "vals": [17, 1, 51, 718, 54]}, {"dt": "2019-09-21_01:00", "vals": [10, 1, 73, 718, 86]}, {"dt": "2019-09-21_07:00", "vals": [5, 1, 81, 718, 191]}, {"dt": "2019-09-21_13:00", "vals": [19, 1, 47, 716, 221]}, {"dt": "2019-09-21_19:00", "vals": [20, 1, 51, 716, 50]}], "siRange": "15.09.2019 - 21.09.2019", "meteoRange": "15.09.2019 - 21.09.2019", "maxSiWeek": [{"dt": "15.09.2019", "val": 0.3, "name": "Диоксид азота"}, {"dt": "16.09.2019", "val": 0.2, "name": "Оксид углерода"}, {"dt": "17.09.2019", "val": 0.2, "name": "Оксид углерода"}, {"dt": "18.09.2019", "val": 0.3, "name": "Диоксид азота"}, {"dt": "19.09.2019", "val": 0.2, "name": "Диоксид азота"}, {"dt": "20.09.2019", "val": 0.6, "name": "Оксид азота"}, {"dt": "21.09.2019", "val": 0.4, "name": "Оксид углерода"}], "primsSS": [{"dt": "2019-09-15_00:00", "vals": [null, 0.001, 0.2, 0.019, 0.021, 0, null, null, null, null]}, {"dt": "2019-09-16_00:00", "vals": [null, 0, 0.4, 0.025, 0.03, 0, null, null, null, null]}, {"dt": "2019-09-17_00:00", "vals": [null, 0.003, 0.5, 0.024, 0.03, 0, null, null, null, null]}, {"dt": "2019-09-18_00:00", "vals": [null, 0.015, 0.6, 0.033, 0.05, 0.001, null, null, null, null]}, {"dt": "2019-09-19_00:00", "vals": [null, 0.003, 0.4, 0.027, 0.026, 0.001, null, null, null, null]}, {"dt": "2019-09-20_00:00", "vals": [null, 0.002, 0.8, 0.024, 0.085, 0.001, null, null, null, null]}, {"dt": "2019-09-21_00:00", "vals": [null, 0.006, 0.7, 0.028, 0.043, 0.001, null, null, null, null]}], "mpcAD": [{"name": "Взвешенные в-ва", "val": 0.15}, {"name": "Диоксид серы", "val": 0.05}, {"name": "Оксид углерода", "val": 3}, {"name": "Диоксид азота", "val": 0.1}, {"name": "Оксид азота", "val": null}, {"name": "Сероводород", "val": null}, {"name": "Фенол", "val": 0.006}, {"name": "Сажа", "val": 0.05}, {"name": "Частицы 10 мкм", "val": 0.06}, {"name": "Частицы 2.5 мкм", "val": 0.035}], "ispel": 0}, {"ind": "38020114", "name": "Усолье-Сибирское", "nom": "5", "place": "ул.Интернациональная, д.52", "label": "Усолье-Сибирское, ул.Интернациональная, д.52", "lng": "103.663736", "lat": "52.749422", "date": "21.09.2019", "si": [{"name": "Взвешенные в-ва", "val": -32768}, {"name": "Диоксид серы", "val": -32768}, {"name": "Оксид углерода", "val": 0.3}, {"name": "Диоксид азота", "val": 0.6}, {"name": "Оксид азота", "val": 0.3}, {"name": "Сероводород", "val": -32768}, {"name": "Хлор", "val": -32768}, {"name": "Формальдегид", "val": -32768}], "maxSi": 0.6, "meteoParamsNames": ["\"Температура\"", "\"Скорость ветра\"", "\"Влажность отн.\"", "\"Давление\"", "\"Направление ветра\""], "meteoParamsValues": [{"dt": "2019-09-15_01:00", "vals": [4, 0, 73, 728, null]}, {"dt": "2019-09-15_07:00", "vals": [2, 0, 95, 727, null]}, {"dt": "2019-09-15_13:00", "vals": [10, 1, 53, 724, 146]}, {"dt": "2019-09-15_19:00", "vals": [10, 0, 62, 723, 186]}, {"dt": "2019-09-16_01:00", "vals": [7, 0, 85, 723, null]}, {"dt": "2019-09-16_07:00", "vals": [6, 0, 98, 723, null]}, {"dt": "2019-09-16_13:00", "vals": [9, 1, 74, 725, 329]}, {"dt": "2019-09-16_19:00", "vals": [9, 0, 69, 728, null]}, {"dt": "2019-09-17_01:00", "vals": [4, 0, 98, 731, null]}, {"dt": "2019-09-17_07:00", "vals": [5, 0, 99, 732, null]}, {"dt": "2019-09-17_13:00", "vals": [14, 1, 58, 731, 136]}, {"dt": "2019-09-17_19:00", "vals": [12, 0, 67, 728, null]}, {"dt": "2019-09-18_01:00", "vals": [7, 0, 89, 728, null]}, {"dt": "2019-09-18_07:00", "vals": [6, 0, 93, 727, null]}, {"dt": "2019-09-18_13:00", "vals": [17, 0, 56, 727, 25]}, {"dt": "2019-09-18_19:00", "vals": [16, 0, 65, 726, null]}, {"dt": "2019-09-19_01:00", "vals": [12, 0, 83, 728, 336]}, {"dt": "2019-09-19_07:00", "vals": [10, 0, 96, 730, null]}, {"dt": "2019-09-19_13:00", "vals": [16, 0, 57, 729, 157]}, {"dt": "2019-09-19_19:00", "vals": [13, 0, 76, 729, null]}, {"dt": "2019-09-20_01:00", "vals": [8, 0, 99, 729, 161]}, {"dt": "2019-09-20_07:00", "vals": [7, 0, 99, 729, 157]}, {"dt": "2019-09-20_13:00", "vals": [19, 0, 56, 727, 127]}, {"dt": "2019-09-21_01:00", "vals": [11, 0, 76, 725, null]}, {"dt": "2019-09-21_07:00", "vals": [8, 0, 96, 725, null]}, {"dt": "2019-09-21_19:00", "vals": [18, 0, 65, 724, null]}], "siRange": "15.09.2019 - 21.09.2019", "meteoRange": "15.09.2019 - 21.09.2019", "maxSiWeek": [{"dt": "15.09.2019", "val": 0.2, "name": "Диоксид азота"}, {"dt": "16.09.2019", "val": 0.2, "name": "Диоксид азота"}, {"dt": "17.09.2019", "val": 0.2, "name": "Диоксид азота"}, {"dt": "18.09.2019", "val": 0.4, "name": "Диоксид азота"}, {"dt": "19.09.2019", "val": 0.5, "name": "Диоксид азота"}, {"dt": "20.09.2019", "val": 0.3, "name": "Диоксид азота"}, {"dt": "21.09.2019", "val": 0.6, "name": "Диоксид азота"}], "primsSS": [{"dt": "2019-09-15_00:00", "vals": [null, null, 0.3, 0.025, 0.008, null, null, null]}, {"dt": "2019-09-16_00:00", "vals": [null, null, 0.3, 0.025, 0.008, null, null, null]}, {"dt": "2019-09-17_00:00", "vals": [null, null, 0.4, 0.028, 0.007, null, null, null]}, {"dt": "2019-09-18_00:00", "vals": [null, null, 0.4, 0.046, 0.014, null, null, null]}, {"dt": "2019-09-19_00:00", "vals": [null, null, 0.5, 0.04, 0.043, null, null, null]}, {"dt": "2019-09-20_00:00", "vals": [null, null, 0.3, 0.046, 0.01, null, null, null]}, {"dt": "2019-09-21_00:00", "vals": [null, null, 0.7, 0.063, 0.044, null, null, null]}], "mpcAD": [{"name": "Взвешенные в-ва", "val": 0.15}, {"name": "Диоксид серы", "val": 0.05}, {"name": "Оксид углерода", "val": 3}, {"name": "Диоксид азота", "val": 0.1}, {"name": "Оксид азота", "val": null}, {"name": "Сероводород", "val": null}, {"name": "Хлор", "val": 0.03}, {"name": "Формальдегид", "val": 0.01}], "ispel": 0}, {"ind": "75020101", "name": "Чита", "nom": "6", "place": "ул.Красной Звезды, д.75, МС", "label": "Чита, №6, ул.Красной Звезды, д.75, МС", "lng": "113.478333", "lat": "52.078889", "date": "21.09.2019", "si": [{"name": "Диоксид серы", "val": 0}, {"name": "Оксид углерода", "val": 0.2}, {"name": "Диоксид азота", "val": 0.4}, {"name": "Оксид азота", "val": 0.2}, {"name": "Озон", "val": -32768}, {"name": "Сероводород", "val": 0.4}, {"name": "Аммиак", "val": 0}, {"name": "Частицы 10 мкм (сут.)", "val": -32768}, {"name": "Частицы 2.5 мкм (сут.)", "val": -32768}], "maxSi": 0.4, "meteoParamsNames": ["\"Температура\"", "\"Скорость ветра\"", "\"Влажность отн.\"", "\"Давление\"", "\"Направление ветра\""], "meteoParamsValues": [{"dt": "2019-09-15_01:00", "vals": [5, 4, 52, 699, 323]}, {"dt": "2019-09-15_07:00", "vals": [0, 3, 55, 702, 242]}, {"dt": "2019-09-15_13:00", "vals": [7, 6, 28, 701, 290]}, {"dt": "2019-09-15_19:00", "vals": [8, 4, 27, 701, 280]}, {"dt": "2019-09-16_01:00", "vals": [5, 1, 57, 701, 194]}, {"dt": "2019-09-16_07:00", "vals": [5, 1, 71, 700, 180]}, {"dt": "2019-09-16_13:00", "vals": [13, 3, 50, 698, 195]}, {"dt": "2019-09-16_19:00", "vals": [7, 2, 82, 698, 242]}, {"dt": "2019-09-17_01:00", "vals": [4, 4, 51, 701, 319]}, {"dt": "2019-09-17_07:00", "vals": [1, 2, 53, 705, 134]}, {"dt": "2019-09-17_13:00", "vals": [9, 4, 27, 707, 319]}, {"dt": "2019-09-17_19:00", "vals": [9, 3, 35, 706, 265]}, {"dt": "2019-09-18_01:00", "vals": [0, 2, 72, 708, 85]}, {"dt": "2019-09-18_07:00", "vals": [-2, 1, 85, 708, 102]}, {"dt": "2019-09-18_13:00", "vals": [13, 1, 37, 705, 193]}, {"dt": "2019-09-18_19:00", "vals": [15, 2, 43, 703, 268]}, {"dt": "2019-09-19_01:00", "vals": [7, 1, 76, 703, 142]}, {"dt": "2019-09-19_07:00", "vals": [4, 1, 88, 703, 143]}, {"dt": "2019-09-19_13:00", "vals": [16, 5, 49, 703, 278]}, {"dt": "2019-09-19_19:00", "vals": [14, 3, 46, 703, 293]}, {"dt": "2019-09-20_01:00", "vals": [9, 1, 60, 705, 135]}, {"dt": "2019-09-20_07:00", "vals": [3, 2, 90, 707, 77]}, {"dt": "2019-09-20_13:00", "vals": [15, 1, 42, 707, 168]}, {"dt": "2019-09-20_19:00", "vals": [15, 1, 39, 706, 218]}, {"dt": "2019-09-21_01:00", "vals": [6, 1, 79, 707, 100]}, {"dt": "2019-09-21_07:00", "vals": [0, 0, 94, 708, 2]}, {"dt": "2019-09-21_13:00", "vals": [17, 1, 44, 707, 232]}, {"dt": "2019-09-21_19:00", "vals": [19, 1, 37, 705, 127]}], "siRange": "15.09.2019 - 21.09.2019", "meteoRange": "15.09.2019 - 21.09.2019", "maxSiWeek": [{"dt": "15.09.2019", "val": 0.2, "name": "Сероводород"}, {"dt": "16.09.2019", "val": 0.3, "name": "Сероводород"}, {"dt": "17.09.2019", "val": 0.2, "name": "Сероводород"}, {"dt": "18.09.2019", "val": 0.3, "name": "Диоксид азота"}, {"dt": "19.09.2019", "val": 0.3, "name": "Сероводород"}, {"dt": "20.09.2019", "val": 0.5, "name": "Сероводород"}, {"dt": "21.09.2019", "val": 0.4, "name": "Диоксид азота"}], "primsSS": [{"dt": "2019-09-15_00:00", "vals": [0, 0, 0.004, 0.001, null, 0, 0, null, null]}, {"dt": "2019-09-16_00:00", "vals": [0.004, 0, 0.018, 0.005, null, 0.002, 0, null, null]}, {"dt": "2019-09-17_00:00", "vals": [null, 0.1, 0.01, 0.003, null, 0, 0, null, null]}, {"dt": "2019-09-18_00:00", "vals": [0.004, 0, 0.032, 0.018, null, 0.002, 0, null, null]}, {"dt": "2019-09-19_00:00", "vals": [0.003, 0, 0.021, 0.022, null, 0.002, 0, null, null]}, {"dt": "2019-09-20_00:00", "vals": [0.003, 0.3, 0.025, 0.033, null, 0.002, 0, null, null]}, {"dt": "2019-09-21_00:00", "vals": [0.003, 0.2, 0.037, 0.032, null, 0.002, 0, null, null]}], "mpcAD": [{"name": "Диоксид серы", "val": 0.05}, {"name": "Оксид углерода", "val": 3}, {"name": "Диоксид азота", "val": 0.1}, {"name": "Оксид азота", "val": null}, {"name": "Озон", "val": 0.1}, {"name": "Сероводород", "val": null}, {"name": "Аммиак", "val": 0.1}, {"name": "Частицы 10 мкм (сут.)", "val": 0.06}, {"name": "Частицы 2.5 мкм (сут.)", "val": 0.035}], "ispel": 0}, {"ind": "38020123", "name": "Черемхово", "nom": "7", "place": "ул.Шевченко, д.72", "label": "Черемхово, ул.Шевченко, д.72", "lng": "103.157164", "lat": "53.114119", "date": "21.09.2019", "si": [{"name": "Взвешенные в-ва", "val": -32768}, {"name": "Диоксид серы", "val": 0}, {"name": "Оксид углерода", "val": 0.2}, {"name": "Диоксид азота", "val": 0.4}, {"name": "Оксид азота", "val": 0.1}, {"name": "Сероводород", "val": 0.2}], "maxSi": 0.4, "meteoParamsNames": ["\"Температура\"", "\"Скорость ветра\"", "\"Влажность отн.\"", "\"Давление\"", "\"Направление ветра\""], "meteoParamsValues": [{"dt": "2019-09-15_01:00", "vals": [2, 0, 78, 716, null]}, {"dt": "2019-09-15_07:00", "vals": [1, 0, 80, 715, null]}, {"dt": "2019-09-15_13:00", "vals": [10, 1, 52, 712, 51]}, {"dt": "2019-09-15_19:00", "vals": [8, 0, 78, 712, 146]}, {"dt": "2019-09-16_01:00", "vals": [7, 1, 83, 712, 17]}, {"dt": "2019-09-16_07:00", "vals": [6, 1, 88, 711, 20]}, {"dt": "2019-09-16_13:00", "vals": [9, 2, 72, 714, 59]}, {"dt": "2019-09-16_19:00", "vals": [7, 0, 69, 717, 28]}, {"dt": "2019-09-17_01:00", "vals": [4, 1, 88, 720, 21]}, {"dt": "2019-09-17_07:00", "vals": [4, 0, 93, 720, null]}, {"dt": "2019-09-17_13:00", "vals": [14, 1, 56, 719, 192]}, {"dt": "2019-09-17_19:00", "vals": [12, 0, 69, 717, null]}, {"dt": "2019-09-18_01:00", "vals": [7, 0, 82, 716, null]}, {"dt": "2019-09-18_07:00", "vals": [5, 0, 93, 715, null]}, {"dt": "2019-09-18_13:00", "vals": [18, 1, 47, 716, 42]}, {"dt": "2019-09-18_19:00", "vals": [13, 0, 81, 715, null]}, {"dt": "2019-09-19_01:00", "vals": [11, 1, 77, 717, 73]}, {"dt": "2019-09-19_07:00", "vals": [9, 1, 96, 718, 20]}, {"dt": "2019-09-19_13:00", "vals": [15, 1, 61, 718, 31]}, {"dt": "2019-09-19_19:00", "vals": [13, 0, 69, 718, null]}, {"dt": "2019-09-20_01:00", "vals": [6, 0, 96, 718, null]}, {"dt": "2019-09-20_07:00", "vals": [7, 0, 99, 718, null]}, {"dt": "2019-09-20_13:00", "vals": [19, 0, 51, 716, 172]}, {"dt": "2019-09-20_19:00", "vals": [15, 0, 56, 714, null]}, {"dt": "2019-09-21_01:00", "vals": [11, 0, 73, 714, null]}, {"dt": "2019-09-21_07:00", "vals": [8, 0, 91, 714, null]}, {"dt": "2019-09-21_13:00", "vals": [22, 0, 44, 714, 152]}, {"dt": "2019-09-21_19:00", "vals": [17, 0, 62, 713, null]}], "siRange": "15.09.2019 - 21.09.2019", "meteoRange": "15.09.2019 - 21.09.2019", "maxSiWeek": [{"dt": "15.09.2019", "val": 0.3, "name": "Диоксид азота"}, {"dt": "16.09.2019", "val": 0.3, "name": "Диоксид азота"}, {"dt": "17.09.2019", "val": 0.3, "name": "Оксид углерода"}, {"dt": "18.09.2019", "val": 0.4, "name": "Оксид углерода"}, {"dt": "19.09.2019", "val": 0.3, "name": "Диоксид азота"}, {"dt": "20.09.2019", "val": 0.3, "name": "Диоксид азота"}, {"dt": "21.09.2019", "val": 0.4, "name": "Диоксид азота"}], "primsSS": [{"dt": "2019-09-15_00:00", "vals": [null, 0.01, 0.3, 0.045, 0.013, 0.001]}, {"dt": "2019-09-16_00:00", "vals": [null, 0.004, 0.5, 0.051, 0.022, 0.001]}, {"dt": "2019-09-17_00:00", "vals": [null, 0.002, 0.6, 0.047, 0.023, 0.001]}, {"dt": "2019-09-18_00:00", "vals": [null, 0.005, 0.9, 0.058, 0.063, 0.001]}, {"dt": "2019-09-19_00:00", "vals": [null, 0.002, 0.5, 0.046, 0.015, 0]}, {"dt": "2019-09-20_00:00", "vals": [null, 0.012, 0.7, 0.055, 0.033, 0.001]}, {"dt": "2019-09-21_00:00", "vals": [null, 0.015, 0.6, 0.062, 0.031, 0.001]}], "mpcAD": [{"name": "Взвешенные в-ва", "val": 0.15}, {"name": "Диоксид серы", "val": 0.05}, {"name": "Оксид углерода", "val": 3}, {"name": "Диоксид азота", "val": 0.1}, {"name": "Оксид азота", "val": null}, {"name": "Сероводород", "val": null}], "ispel": 0}, {"ind": "38020109", "name": "Иркутск", "nom": "20", "place": "ул.Мира, д.101", "label": "Иркутск, ул.Мира, д.101", "lng": "104.210861", "lat": "52.350167", "date": "21.09.2019", "si": [{"name": "Взвешенные в-ва", "val": -32768}, {"name": "Диоксид серы", "val": 0.2}, {"name": "Оксид углерода", "val": 0.4}, {"name": "Диоксид азота", "val": 0.7}, {"name": "Оксид азота", "val": 0.3}, {"name": "Сероводород", "val": 0.3}, {"name": "Аммиак", "val": 0}, {"name": "Бензол", "val": -32768}, {"name": "Ксилол", "val": -32768}, {"name": "Стирол", "val": -32768}, {"name": "Толуол", "val": -32768}, {"name": "Хлорбензол", "val": -32768}, {"name": "Этилбензол", "val": -32768}, {"name": "Кумол", "val": -32768}], "maxSi": 0.7, "meteoParamsNames": ["\"Температура\"", "\"Скорость ветра\"", "\"Влажность отн.\"", "\"Давление\"", "\"Направление ветра\""], "meteoParamsValues": [{"dt": "2019-09-15_01:00", "vals": [4, 0, 70, 727, 320]}, {"dt": "2019-09-15_07:00", "vals": [1, 1, 88, 725, 170]}, {"dt": "2019-09-15_13:00", "vals": [11, 1, 54, 723, 146]}, {"dt": "2019-09-15_19:00", "vals": [10, 0, 66, 722, 138]}, {"dt": "2019-09-16_13:00", "vals": [9, 2, 92, 724, 324]}, {"dt": "2019-09-16_19:00", "vals": [9, 1, 75, 727, 301]}, {"dt": "2019-09-17_01:00", "vals": [5, 0, 95, 730, null]}, {"dt": "2019-09-17_07:00", "vals": [5, 0, 95, 731, 170]}, {"dt": "2019-09-17_13:00", "vals": [15, 1, 48, 730, 225]}, {"dt": "2019-09-17_19:00", "vals": [13, 0, 63, 727, 160]}, {"dt": "2019-09-18_01:00", "vals": [7, 1, 94, 727, 171]}, {"dt": "2019-09-18_07:00", "vals": [7, 1, 93, 726, 162]}, {"dt": "2019-09-18_13:00", "vals": [19, 2, 45, 726, 340]}, {"dt": "2019-09-18_19:00", "vals": [16, 0, 69, 725, 148]}, {"dt": "2019-09-19_01:00", "vals": [10, 0, 98, 726, null]}, {"dt": "2019-09-19_07:00", "vals": [11, 1, 88, 728, 296]}, {"dt": "2019-09-19_13:00", "vals": [15, 1, 61, 728, 279]}, {"dt": "2019-09-19_19:00", "vals": [13, 0, 79, 728, null]}, {"dt": "2019-09-20_01:00", "vals": [7, 0, 96, 729, 177]}, {"dt": "2019-09-20_13:00", "vals": [21, 2, 49, 726, 146]}, {"dt": "2019-09-20_19:00", "vals": [17, 1, 52, 725, 172]}, {"dt": "2019-09-21_01:00", "vals": [11, 2, 85, 724, 167]}, {"dt": "2019-09-21_07:00", "vals": [9, 1, 93, 724, 165]}, {"dt": "2019-09-21_13:00", "vals": [24, 1, 38, 724, 185]}, {"dt": "2019-09-21_19:00", "vals": [18, 0, 63, 723, null]}], "siRange": "15.09.2019 - 21.09.2019", "meteoRange": "15.09.2019 - 21.09.2019", "maxSiWeek": [{"dt": "15.09.2019", "val": 0.3, "name": "Диоксид азота"}, {"dt": "16.09.2019", "val": 0.2, "name": "Диоксид серы"}, {"dt": "17.09.2019", "val": 0.5, "name": "Диоксид азота"}, {"dt": "18.09.2019", "val": 1.4, "name": "Сероводород"}, {"dt": "19.09.2019", "val": 1.1, "name": "Сероводород"}, {"dt": "20.09.2019", "val": 0.5, "name": "Диоксид азота"}, {"dt": "21.09.2019", "val": 0.7, "name": "Диоксид азота"}], "primsSS": [{"dt": "2019-09-15_00:00", "vals": [null, 0.021, 0.1, 0.032, 0.008, 0.001, 0, null, null, null, null, null, null, null]}, {"dt": "2019-09-16_00:00", "vals": [null, 0.086, 0, 0.031, 0.016, 0.001, 0, null, null, null, null, null, null, null]}, {"dt": "2019-09-17_00:00", "vals": [null, 0.015, 0.6, 0.047, 0.032, 0.001, 0, null, null, null, null, null, null, null]}, {"dt": "2019-09-18_00:00", "vals": [null, 0.053, 0.6, 0.051, 0.02, 0.004, 0, null, null, null, null, null, null, null]}, {"dt": "2019-09-19_00:00", "vals": [null, 0.037, 0.6, 0.063, 0.044, 0.003, 0, null, null, null, null, null, null, null]}, {"dt": "2019-09-20_00:00", "vals": [null, 0.006, 0.5, 0.051, 0.01, 0, 0, null, null, null, null, null, null, null]}, {"dt": "2019-09-21_00:00", "vals": [null, 0.03, 0.8, 0.072, 0.044, 0.002, 0, null, null, null, null, null, null, null]}], "mpcAD": [{"name": "Взвешенные в-ва", "val": 0.15}, {"name": "Диоксид серы", "val": 0.05}, {"name": "Оксид углерода", "val": 3}, {"name": "Диоксид азота", "val": 0.1}, {"name": "Оксид азота", "val": null}, {"name": "Сероводород", "val": null}, {"name": "Аммиак", "val": 0.1}, {"name": "Бензол", "val": 0.06}, {"name": "Ксилол", "val": null}, {"name": "Стирол", "val": null}, {"name": "Толуол", "val": null}, {"name": "Хлорбензол", "val": null}, {"name": "Этилбензол", "val": null}, {"name": "Кумол", "val": null}], "ispel": 0}, {"ind": "38020101", "name": "Иркутск", "nom": "23", "place": "ул.Севастопольская, д.239а", "label": "Иркутск, ул.Севастопольская, д.239а", "lng": "104.162517", "lat": "52.351467", "date": "21.09.2019", "si": [{"name": "Взвешенные в-ва", "val": -32768}, {"name": "Диоксид серы", "val": 0.1}, {"name": "Оксид углерода", "val": 0.2}, {"name": "Диоксид азота", "val": -32768}, {"name": "Оксид азота", "val": -32768}, {"name": "Озон", "val": -32768}, {"name": "Сероводород", "val": 0.1}, {"name": "Сумма углеводородов", "val": -32768}, {"name": "Аммиак", "val": -32768}, {"name": "Формальдегид", "val": -32768}, {"name": "Метан", "val": -32768}, {"name": "Частицы 10 мкм (сут.)", "val": 0.1}, {"name": "Частицы 2.5 мкм (сут.)", "val": 0}], "maxSi": 0.2, "meteoParamsNames": ["\"Температура\"", "\"Скорость ветра\"", "\"Влажность отн.\"", "\"Давление\"", "\"Направление ветра\""], "meteoParamsValues": [{"dt": "2019-09-15_01:00", "vals": [4, 0, 69, 723, 27]}, {"dt": "2019-09-15_07:00", "vals": [1, 0, 87, 721, null]}, {"dt": "2019-09-15_13:00", "vals": [11, 1, 52, 719, 15]}, {"dt": "2019-09-15_19:00", "vals": [10, 0, 67, 717, null]}, {"dt": "2019-09-16_01:00", "vals": [8, 0, 77, 717, null]}, {"dt": "2019-09-16_07:00", "vals": [6, 0, 87, 718, null]}, {"dt": "2019-09-16_13:00", "vals": [9, 2, 92, 720, 29]}, {"dt": "2019-09-16_19:00", "vals": [9, 1, 74, 722, 29]}, {"dt": "2019-09-17_01:00", "vals": [6, 2, 88, 726, 28]}, {"dt": "2019-09-17_07:00", "vals": [5, 0, 95, 726, 10]}, {"dt": "2019-09-17_13:00", "vals": [15, 1, 51, 725, 9]}, {"dt": "2019-09-17_19:00", "vals": [12, 0, 64, 723, null]}, {"dt": "2019-09-18_01:00", "vals": [7, 0, 93, 723, null]}, {"dt": "2019-09-18_07:00", "vals": [5, 0, 97, 721, 9]}, {"dt": "2019-09-19_13:00", "vals": [15, 1, 63, 724, 24]}, {"dt": "2019-09-19_19:00", "vals": [13, 0, 74, 724, null]}, {"dt": "2019-09-20_01:00", "vals": [8, 0, 99, 724, null]}, {"dt": "2019-09-20_07:00", "vals": [6, 0, 99, 724, 10]}, {"dt": "2019-09-20_13:00", "vals": [21, 1, 48, 722, 11]}, {"dt": "2019-09-20_19:00", "vals": [17, 0, 51, 720, null]}, {"dt": "2019-09-21_01:00", "vals": [10, 0, 90, 720, 12]}, {"dt": "2019-09-21_07:00", "vals": [9, 0, 96, 720, null]}, {"dt": "2019-09-21_13:00", "vals": [22, 1, 41, 720, 18]}, {"dt": "2019-09-21_19:00", "vals": [18, 0, 55, 719, null]}], "siRange": "15.09.2019 - 21.09.2019", "meteoRange": "15.09.2019 - 21.09.2019", "maxSiWeek": [{"dt": "15.09.2019", "val": 0.1, "name": "Диоксид серы"}, {"dt": "16.09.2019", "val": 0.3, "name": "Сероводород"}, {"dt": "17.09.2019", "val": 0.2, "name": "Сероводород"}, {"dt": "18.09.2019", "val": 0.2, "name": "Сероводород"}, {"dt": "19.09.2019", "val": 0.2, "name": "Оксид углерода"}, {"dt": "20.09.2019", "val": 0.3, "name": "Сероводород"}, {"dt": "21.09.2019", "val": 0.2, "name": "Оксид углерода"}], "primsSS": [{"dt": "2019-09-15_00:00", "vals": [null, 0.012, 0.3, null, null, null, 0, null, null, null, null, 0.021, 0]}, {"dt": "2019-09-16_00:00", "vals": [null, 0.007, 0.1, null, null, null, 0.001, null, null, null, null, 0.024, 0]}, {"dt": "2019-09-17_00:00", "vals": [null, 0.008, 0.3, null, null, null, 0.001, null, null, null, null, 0.016, 0]}, {"dt": "2019-09-18_00:00", "vals": [null, 0.003, 0.3, null, null, null, 0.001, null, null, null, null, 0.032, 0]}, {"dt": "2019-09-19_00:00", "vals": [null, 0.027, 0.6, null, null, null, 0.001, null, null, null, null, 0.024, 0]}, {"dt": "2019-09-20_00:00", "vals": [null, 0.006, 0.4, null, null, null, 0.001, null, null, null, null, 0.042, 0]}, {"dt": "2019-09-21_00:00", "vals": [null, 0.012, 0.5, null, null, null, 0, null, null, null, null, 0.038, 0]}], "mpcAD": [{"name": "Взвешенные в-ва", "val": 0.15}, {"name": "Диоксид серы", "val": 0.05}, {"name": "Оксид углерода", "val": 3}, {"name": "Диоксид азота", "val": 0.1}, {"name": "Оксид азота", "val": null}, {"name": "Озон", "val": 0.1}, {"name": "Сероводород", "val": null}, {"name": "Сумма углеводородов", "val": 5}, {"name": "Аммиак", "val": 0.1}, {"name": "Формальдегид", "val": 0.01}, {"name": "Метан", "val": null}, {"name": "Частицы 10 мкм (сут.)", "val": 0.06}, {"name": "Частицы 2.5 мкм (сут.)", "val": 0.035}], "ispel": 0}, {"ind": "38020103", "name": "Ангарск", "nom": "25", "place": "ул.Ворошилова, д.49", "label": "Ангарск, ул.Ворошилова, д.49", "lng": "103.882727", "lat": "52.530861", "date": "21.09.2019", "si": [{"name": "Взвешенные в-ва", "val": -32768}, {"name": "Диоксид серы", "val": 0}, {"name": "Оксид углерода", "val": 0.6}, {"name": "Диоксид азота", "val": 1}, {"name": "Оксид азота", "val": 1.3}, {"name": "Сероводород", "val": 0.1}, {"name": "Аммиак", "val": -32768}, {"name": "Формальдегид", "val": -32768}], "maxSi": 1.3, "meteoParamsNames": ["\"Температура\"", "\"Скорость ветра\"", "\"Влажность отн.\"", "\"Давление\"", "\"Направление ветра\""], "meteoParamsValues": [{"dt": "2019-09-15_01:00", "vals": [4, 0, 76, 728, null]}, {"dt": "2019-09-15_07:00", "vals": [2, 1, 86, 726, 200]}, {"dt": "2019-09-15_13:00", "vals": [11, 1, 75, 723, 207]}, {"dt": "2019-09-15_19:00", "vals": [12, 0, 75, 722, null]}, {"dt": "2019-09-16_01:00", "vals": [8, 0, 79, 722, 332]}, {"dt": "2019-09-16_07:00", "vals": [6, 1, 85, 723, 289]}, {"dt": "2019-09-16_13:00", "vals": [9, 1, 87, 725, 315]}, {"dt": "2019-09-16_19:00", "vals": [9, 1, 76, 728, 299]}, {"dt": "2019-09-17_01:00", "vals": [5, 0, 89, 731, null]}, {"dt": "2019-09-17_07:00", "vals": [6, 1, 89, 731, 200]}, {"dt": "2019-09-17_13:00", "vals": [15, 1, 74, 730, 217]}, {"dt": "2019-09-17_19:00", "vals": [14, 1, 74, 728, 201]}, {"dt": "2019-09-18_01:00", "vals": [8, 1, 83, 727, 200]}, {"dt": "2019-09-18_07:00", "vals": [6, 1, 86, 726, 196]}, {"dt": "2019-09-18_13:00", "vals": [19, 1, 73, 726, 329]}, {"dt": "2019-09-18_19:00", "vals": [16, 0, 77, 725, 222]}, {"dt": "2019-09-19_01:00", "vals": [12, 1, 85, 727, 317]}, {"dt": "2019-09-19_07:00", "vals": [11, 1, 84, 729, 310]}, {"dt": "2019-09-19_13:00", "vals": [16, 1, 74, 729, 269]}, {"dt": "2019-09-19_19:00", "vals": [14, 0, 75, 728, null]}, {"dt": "2019-09-20_01:00", "vals": [8, 1, 90, 729, 196]}, {"dt": "2019-09-20_07:00", "vals": [5, 1, 90, 729, 197]}, {"dt": "2019-09-20_13:00", "vals": [21, 1, 73, 727, 217]}, {"dt": "2019-09-20_19:00", "vals": [19, 1, 74, 725, 202]}, {"dt": "2019-09-21_01:00", "vals": [11, 2, 75, 724, 200]}, {"dt": "2019-09-21_07:00", "vals": [7, 1, 87, 725, 194]}, {"dt": "2019-09-21_19:00", "vals": [19, 0, 73, 724, null]}], "siRange": "15.09.2019 - 21.09.2019", "meteoRange": "15.09.2019 - 21.09.2019", "maxSiWeek": [{"dt": "15.09.2019", "val": 1.5, "name": "Диоксид азота"}, {"dt": "16.09.2019", "val": 1.5, "name": "Диоксид азота"}, {"dt": "17.09.2019", "val": 1.1, "name": "Диоксид азота"}, {"dt": "18.09.2019", "val": 1.1, "name": "Диоксид азота"}, {"dt": "19.09.2019", "val": 1.6, "name": "Диоксид азота"}, {"dt": "20.09.2019", "val": 1.4, "name": "Диоксид азота"}, {"dt": "21.09.2019", "val": 1.3, "name": "Оксид азота"}], "primsSS": [{"dt": "2019-09-15_00:00", "vals": [null, 0.004, 0.4, 0.202, 0.078, 0.001, null, null]}, {"dt": "2019-09-16_00:00", "vals": [null, 0.001, 0.2, 0.143, 0.075, 0, null, null]}, {"dt": "2019-09-17_00:00", "vals": [null, 0.009, 0.4, 0.137, 0.085, 0.001, null, null]}, {"dt": "2019-09-18_00:00", "vals": [null, 0.002, 0.9, 0.146, 0.16, 0, null, null]}, {"dt": "2019-09-19_00:00", "vals": [null, 0.001, 1, 0.188, 0.173, 0, null, null]}, {"dt": "2019-09-20_00:00", "vals": [null, 0.012, 0.8, 0.147, 0.16, 0.001, null, null]}, {"dt": "2019-09-21_00:00", "vals": [null, 0.004, 1.4, 0.153, 0.234, 0.001, null, null]}], "mpcAD": [{"name": "Взвешенные в-ва", "val": 0.15}, {"name": "Диоксид серы", "val": 0.05}, {"name": "Оксид углерода", "val": 3}, {"name": "Диоксид азота", "val": 0.1}, {"name": "Оксид азота", "val": null}, {"name": "Сероводород", "val": null}, {"name": "Аммиак", "val": 0.1}, {"name": "Формальдегид", "val": 0.01}], "ispel": 0}, {"ind": "38020104", "name": "Ангарск", "nom": "41", "place": "ул.Московская, п.о.30", "label": "Ангарск, ул.Московская, п.о.30", "lng": "103.881717", "lat": "52.541858", "date": "21.09.2019", "si": [{"name": "Взвешенные в-ва", "val": -32768}, {"name": "Диоксид серы", "val": 0.2}, {"name": "Оксид углерода", "val": 0.5}, {"name": "Диоксид азота", "val": 0.3}, {"name": "Оксид азота", "val": 1}, {"name": "Озон", "val": 0}, {"name": "Сероводород", "val": 0.3}, {"name": "Фторид водорода", "val": -32768}, {"name": "Формальдегид", "val": -32768}, {"name": "Частицы 10 мкм (сут.)", "val": 0.1}], "maxSi": 1, "meteoParamsNames": ["\"Температура\"", "\"Скорость ветра\"", "\"Влажность отн.\"", "\"Давление\"", "\"Направление ветра\""], "meteoParamsValues": [{"dt": "2019-09-15_01:00", "vals": [4, 0, 73, 728, null]}, {"dt": "2019-09-15_07:00", "vals": [2, 1, 90, 726, 50]}, {"dt": "2019-09-15_13:00", "vals": [11, 0, 47, 724, 89]}, {"dt": "2019-09-15_19:00", "vals": [11, 0, 57, 722, null]}, {"dt": "2019-09-16_01:00", "vals": [8, 0, 78, 723, null]}, {"dt": "2019-09-16_07:00", "vals": [5, 0, 93, 723, null]}, {"dt": "2019-09-16_13:00", "vals": [9, 1, 95, 725, 232]}, {"dt": "2019-09-16_19:00", "vals": [9, 0, 77, 728, 227]}, {"dt": "2019-09-17_01:00", "vals": [4, 0, 98, 731, null]}, {"dt": "2019-09-17_07:00", "vals": [6, 1, 94, 732, 42]}, {"dt": "2019-09-17_13:00", "vals": [15, 1, 49, 731, 143]}, {"dt": "2019-09-17_19:00", "vals": [13, 0, 58, 728, 45]}, {"dt": "2019-09-18_01:00", "vals": [8, 0, 88, 728, null]}, {"dt": "2019-09-18_07:00", "vals": [6, 0, 90, 727, null]}, {"dt": "2019-09-18_13:00", "vals": [19, 1, 47, 727, 287]}, {"dt": "2019-09-19_01:00", "vals": [11, 0, 94, 728, null]}, {"dt": "2019-09-19_07:00", "vals": [10, 0, 92, 729, null]}, {"dt": "2019-09-19_13:00", "vals": [17, 1, 53, 729, 166]}, {"dt": "2019-09-19_19:00", "vals": [12, 0, 77, 729, null]}, {"dt": "2019-09-20_01:00", "vals": [8, 1, 97, 729, 38]}, {"dt": "2019-09-20_07:00", "vals": [6, 0, 95, 729, 42]}, {"dt": "2019-09-20_13:00", "vals": [20, 1, 50, 727, 40]}, {"dt": "2019-09-20_19:00", "vals": [19, 1, 45, 725, 41]}, {"dt": "2019-09-21_01:00", "vals": [11, 1, 72, 725, 35]}, {"dt": "2019-09-21_13:00", "vals": [24, 0, 35, 725, null]}, {"dt": "2019-09-21_19:00", "vals": [18, 0, 70, 724, null]}], "siRange": "15.09.2019 - 21.09.2019", "meteoRange": "15.09.2019 - 21.09.2019", "maxSiWeek": [{"dt": "15.09.2019", "val": 0.1, "name": "Диоксид серы"}, {"dt": "16.09.2019", "val": 0.1, "name": "Оксид углерода"}, {"dt": "17.09.2019", "val": 0.2, "name": "Диоксид серы"}, {"dt": "18.09.2019", "val": 0.1, "name": "Оксид углерода"}, {"dt": "19.09.2019", "val": 0.5, "name": "Оксид азота"}, {"dt": "20.09.2019", "val": 0.3, "name": "Сероводород"}, {"dt": "21.09.2019", "val": 1, "name": "Оксид азота"}], "primsSS": [{"dt": "2019-09-15_00:00", "vals": [null, 0.012, 0.3, 0.006, 0.014, 0.003, 0.001, null, null, 0.018]}, {"dt": "2019-09-16_00:00", "vals": [null, 0.003, 0.2, 0, 0.005, 0.003, 0, null, null, 0.022]}, {"dt": "2019-09-17_00:00", "vals": [null, 0.029, 0.5, 0.014, 0.03, 0.003, 0.001, null, null, 0.009]}, {"dt": "2019-09-18_00:00", "vals": [null, 0.005, 0.4, 0.002, 0.018, 0.004, 0, null, null, 0.035]}, {"dt": "2019-09-19_00:00", "vals": [null, 0.002, 0.6, 0.011, 0.053, 0.003, 0, null, null, 0.028]}, {"dt": "2019-09-20_00:00", "vals": [null, 0.023, 0.4, 0.014, 0.027, 0.004, 0.001, null, null, 0.052]}, {"dt": "2019-09-21_00:00", "vals": [null, 0.04, 1, 0.027, 0.143, 0.004, 0.001, null, null, 0.036]}], "mpcAD": [{"name": "Взвешенные в-ва", "val": 0.15}, {"name": "Диоксид серы", "val": 0.05}, {"name": "Оксид углерода", "val": 3}, {"name": "Диоксид азота", "val": 0.1}, {"name": "Оксид азота", "val": null}, {"name": "Озон", "val": 0.1}, {"name": "Сероводород", "val": null}, {"name": "Фторид водорода", "val": 0.014}, {"name": "Формальдегид", "val": 0.01}, {"name": "Частицы 10 мкм (сут.)", "val": 0.06}], "ispel": 0}, {"ind": "38020102", "name": "Байкальск", "nom": "47", "place": "Промбаза, МС", "label": "Байкальск, Промбаза, МС", "lng": "104.174733", "lat": "51.51615", "date": "21.09.2019", "si": [{"name": "Взвешенные в-ва", "val": -32768}, {"name": "Диоксид серы", "val": -32768}, {"name": "Оксид углерода", "val": -32768}, {"name": "Диоксид азота", "val": 0.6}, {"name": "Оксид азота", "val": 0}, {"name": "Озон", "val": 0.2}, {"name": "Сероводород", "val": -32768}, {"name": "Сумма углеводородов", "val": -32768}, {"name": "Аммиак", "val": 0}, {"name": "Частицы 10 мкм", "val": -32768}, {"name": "Метан", "val": -32768}, {"name": "Частицы 2.5 мкм", "val": -32768}, {"name": "Частицы 10 мкм (сут.)", "val": 0}, {"name": "Частицы 2.5 мкм (сут.)", "val": 0}], "maxSi": 0.6, "meteoParamsNames": ["\"Температура\"", "\"Скорость ветра\"", "\"Влажность отн.\"", "\"Давление\"", "\"Направление ветра\""], "meteoParamsValues": [{"dt": "2019-09-15_01:00", "vals": [4, 1, 99, 724, 214]}, {"dt": "2019-09-15_07:00", "vals": [3, 1, 99, 722, 242]}, {"dt": "2019-09-15_13:00", "vals": [10, 2, 65, 720, 55]}, {"dt": "2019-09-15_19:00", "vals": [8, 0, 91, 719, null]}, {"dt": "2019-09-16_01:00", "vals": [5, 0, null, 718, null]}, {"dt": "2019-09-16_07:00", "vals": [7, 0, 99, 719, 268]}, {"dt": "2019-09-16_13:00", "vals": [13, 1, 66, 720, 139]}, {"dt": "2019-09-16_19:00", "vals": [9, 0, null, 724, 232]}, {"dt": "2019-09-17_01:00", "vals": [6, 0, null, 727, 215]}, {"dt": "2019-09-17_07:00", "vals": [7, 0, null, 728, 250]}, {"dt": "2019-09-17_13:00", "vals": [13, 2, 66, 727, 74]}, {"dt": "2019-09-17_19:00", "vals": [8, 0, 93, 725, null]}, {"dt": "2019-09-18_01:00", "vals": [6, 0, null, 724, 229]}, {"dt": "2019-09-18_07:00", "vals": [7, 0, null, 723, 214]}, {"dt": "2019-09-18_13:00", "vals": [12, 2, 91, 723, 53]}, {"dt": "2019-09-18_19:00", "vals": [9, 0, 99, 722, 223]}, {"dt": "2019-09-19_01:00", "vals": [8, 1, null, 723, 261]}, {"dt": "2019-09-19_07:00", "vals": [11, 0, 99, 725, 208]}, {"dt": "2019-09-19_13:00", "vals": [15, 2, 66, 725, 53]}, {"dt": "2019-09-19_19:00", "vals": [11, 0, null, 725, 197]}, {"dt": "2019-09-20_01:00", "vals": [7, 0, null, 725, 268]}, {"dt": "2019-09-20_07:00", "vals": [6, 0, null, 726, null]}, {"dt": "2019-09-20_13:00", "vals": [14, 2, 68, 724, 55]}, {"dt": "2019-09-20_19:00", "vals": [10, 0, 97, 723, null]}, {"dt": "2019-09-21_01:00", "vals": [7, 0, null, 722, 251]}, {"dt": "2019-09-21_07:00", "vals": [7, 0, null, 722, 237]}], "siRange": "15.09.2019 - 21.09.2019", "meteoRange": "15.09.2019 - 21.09.2019", "maxSiWeek": [{"dt": "15.09.2019", "val": 0.6, "name": "Диоксид азота"}, {"dt": "16.09.2019", "val": 0.7, "name": "Диоксид азота"}, {"dt": "17.09.2019", "val": 0.6, "name": "Диоксид азота"}, {"dt": "18.09.2019", "val": 0.7, "name": "Диоксид азота"}, {"dt": "19.09.2019", "val": 0.7, "name": "Диоксид азота"}, {"dt": "20.09.2019", "val": 0.7, "name": "Диоксид азота"}, {"dt": "21.09.2019", "val": 0.6, "name": "Диоксид азота"}], "primsSS": [{"dt": "2019-09-15_00:00", "vals": [null, 0.001, null, 0.087, 0, 0.04, 0, null, 0, null, null, null, 0.007, 0]}, {"dt": "2019-09-16_00:00", "vals": [null, 0.003, null, 0.113, 0, 0.03, 0.001, null, 0, null, null, null, 0.008, 0]}, {"dt": "2019-09-17_00:00", "vals": [null, 0.001, null, 0.109, 0, 0.038, 0, null, 0, null, null, null, 0.008, 0]}, {"dt": "2019-09-18_00:00", "vals": [null, 0.001, null, 0.112, 0, 0.032, 0, null, 0, null, null, null, 0.008, 0]}, {"dt": "2019-09-19_00:00", "vals": [null, 0.002, null, 0.121, 0, 0.044, 0.002, null, 0, null, null, null, 0.011, 0]}, {"dt": "2019-09-20_00:00", "vals": [null, 0.001, null, 0.119, 0, 0.039, 0, null, 0, null, null, null, 0.011, 0]}, {"dt": "2019-09-21_00:00", "vals": [null, null, null, 0.111, 0, 0.025, null, null, 0, null, null, null, 0.012, 0]}], "mpcAD": [{"name": "Взвешенные в-ва", "val": 0.15}, {"name": "Диоксид серы", "val": 0.05}, {"name": "Оксид углерода", "val": 3}, {"name": "Диоксид азота", "val": 0.1}, {"name": "Оксид азота", "val": null}, {"name": "Озон", "val": 0.1}, {"name": "Сероводород", "val": null}, {"name": "Сумма углеводородов", "val": 5}, {"name": "Аммиак", "val": 0.1}, {"name": "Частицы 10 мкм", "val": 0.06}, {"name": "Метан", "val": null}, {"name": "Частицы 2.5 мкм", "val": 0.035}, {"name": "Частицы 10 мкм (сут.)", "val": 0.06}, {"name": "Частицы 2.5 мкм (сут.)", "val": 0.035}], "ispel": 0}]}]}